Workbook

Sheet Cover
A1: 🌱 SG CONSUMER | OKIRU ESG INTELLIGENCE TOOLKIT v1.6 | Net-Zero Edition
A2: King V · IFRS S1/S2 · GARP/GRAP · ISO 14001/45001/27001/26000 · GRI · EEA · WSP/ATR · SBTi CNZS 2.0 | Powered by Okiru Consulting
A4: ENTITY INFORMATION
B5: Entity | C5: SG Consumer / SuperGroup SG Consumer (Pty) Ltd
B6: Reporting Period | C6: FY 2025/2026 | July 2025 – June 2026
B7: Reporting Consultant | C7: Okiru Consulting | www.okiru.co.za
B8: Version | C8: v1.7 | May 2026 | SG Consumer Live Data Load (Coba submission)
B9: Last Updated | C9: 2026-05-27
B10: Baseline Year (for SBTi) | C10: FY 2025/26
B11: Net-Zero Target Year | C11: 2050 (SBTi CNZS 2.0)
B12: B-BBEE Sector | C12: Generic / FMCG Distribution
A14: SHEET NAVIGATOR — Click sheet tabs to navigate | Blue cells = enter data | Green = auto-calculated
B15: Sheet | C15: Description | D15: Type
B16: ESG_Dashboard | C16: Master ESG summary — E·S·G scores, GHG tiles, KPIs | D16: ⚙️ AUTO
B17: E_Data | C17: Environmental raw data — 9 months actuals | D17: 🔵 DATA ENTRY
B18: S_Data | C18: Social — EE headcount, H&S, WSP/ATR, OFO codes | D18: 🔵 DATA ENTRY
B19: G_Data | C19: Governance — board, risk, POPIA, ethics | D19: 🔵 DATA ENTRY
B20: Fleet_Register | C20: 134-vehicle register — L/100km, tCO₂e, EV | D20: 🔵 DATA ENTRY
B21: Waste_Register | C21: Oricol, Oracle, Cority waste streams | D21: 🔵 DATA ENTRY
B22: Driver_Debrief | C22: Route completion %, excess km, fatigue flags | D22: 🔵 DATA ENTRY
B23: EE_Scorecard | C23: EEA2 scoring — Black%, female%, PWD% | D23: ⚙️ AUTO
B24: E_Scorecard | C24: Environmental score /100 — net-zero lens | D24: ⚙️ AUTO
B25: S_Scorecard | C25: Social score /100 — EE+WSP+H&S+Community | D25: ⚙️ AUTO
B26: G_Scorecard | C26: Governance score /100 — King V+IFRS+GARP | D26: ⚙️ AUTO
... B35: ISO_14083 | C35: Transport emissions per ISO 14083 / GLEC — trip register, intensity, customer alloc | D35: 🔵 DATA ENTRY
A36: COLOUR GUIDE: 🔵 Blue text = User input (enter data) | 🟢 Green bg = Auto-calculated | 🟡 Amber = Target/benchmark | 🔴 Red = Gap/below target | B36: B_BBEE_ESG | C36: B-BBEE Generic Code element mapping → status level + procurement recognition | D36: ⚙️ AUTO
B37: Materiality_Matrix | C37: Impact × Likelihood scoring with single/double materiality toggle | D37: ⚙️ AUTO
B38: Carbon_Tax | C38: Section 12L liability calc — Tier 1 + Tier 2 + mitigation scenarios | D38: ⚙️ AUTO
B39: Glossary | C39: Technical terms, definitions, source citations (98 entries) | D39: 📋 REFERENCE
B40: Assumptions | C40: Strategy toggles + thresholds + EFs (single source of truth) | D40: ⚙️ TOGGLES
A41: COLOUR GUIDE: 🔵 Blue text = User input (enter data) | 🟢 Green bg = Auto-calculated | 🟡 Amber = Target/benchmark | 🔴 Red = Gap/below target | 🟧 Orange bg = Strategy toggle
B42: Data_Status | C42: Live data tracker — every field with source, status, refresh date | D42: 📊 TRACKER

Sheet Assumptions
A1: ⚙ ASSUMPTIONS — Single source of truth for thresholds, weights, emission factors, targets
A2: Edit values in the BLUE cells to retune the toolkit. All scorecards reference this sheet — one edit cascades everywhere.
A3: 🔒 THIS INSTANCE IS CONFIGURED FOR SUPERGROUP — Transport / FMCG Distribution | Sector-locked deep build
A4: To deploy for a different sector (ICT, Financial Services, Mining, etc.) start from the Generic template — do not retrofit by changing the Sector toggle below. Each sector fork has bespoke depth (e.g. ISO 14083 for transport, task-based emissions for ICT, financed emissions for FinServ).
A6: BLOCK 0 — STRATEGY TOGGLES ★ PRIMARY CONTROLS — change these to retune the whole toolkit
A7: Setting | B7: Active value | C7: Options | D7: Code | E7: Effect on toolkit | F7: Cell ref
A8: Scoring stance | B8: Standard | C8: Lean / Standard / Strict | D8: STANCE | E8: Drives the banding floor (Lean 30% / Std 50% / Strict 70%) for partial credit on all quantitative indicators | F8: Assumptions!B6
A9: Banding floor (auto from stance) | B9: =IF(B8="Lean",0.3,IF(B8="Strict",0.7,0.5)) -> 0.5 | C9: 0.30 / 0.50 / 0.70 | D9: STANCE_FLR | E9: Below Actual/Target × this %, score = 0. Above, pro-rata. | F9: Assumptions!B7
A10: Sector | B10: Transport / FMCG Distribution | C10: See list → | D10: SECTOR | E10: 🔒 Sector-locked for this SuperGroup instance. The toolkit is configured around transport/distribution logic (ISO 14083, Fleet_Register, Driver_Debrief). To use for another sector, fork from the Generic template — do not change this dropdown. | F10: Assumptions!B8
A11: Primary reporting standard | B11: King V + IFRS S1/S2 | C11: SA / IFRS / GRI / ESRS / TCFD | D11: STD_PRIMARY | E11: Determines emphasis in dashboard, executive summary, and standards map | F11: Assumptions!B9
A12: Materiality basis | B12: Single (financial — IFRS) | C12: Single / Double / Dynamic | D12: MAT_BASIS | E12: Single: financial only (IFRS). Double: financial + impact (ESRS). Dynamic: both, evolving over time. | F12: Assumptions!B10
A13: Reporting currency | B13: ZAR | C13: See list → | D13: CCY | E13: Drives currency symbol on CSI, Carbon Tax, training spend, and procurement | F13: Assumptions!B11
A14: Currency symbol (auto)
A15: Carbon tax display | B15: Both (current + escalated) | C15: Current / Escalated / Both | D15: TAX_MODE | E15: Side-by-side liability view: Tier 1 (current) vs Tier 2 (escalated forward-looking) | F15: Assumptions!B13
A16: ★ How toggles work: change a value in column B → all scorecards and the dashboard recompute. The current scoring stance ("Standard") gives 50% banding floor; switch to "Lean" to use 30% (encourages early progress); switch to "Strict" for 70% (closer to B-BBEE binary).
A28: BLOCK 1 — EMISSION FACTORS (DEFRA 2024 · Eskom NERSA 2024 · GHG Protocol)
A29: Factor | B29: Value | C29: Unit | D29: Code | E29: Source / Reference | F29: Last Updated
A30: Diesel — road freight | B30: 2.68 | C30: kgCO₂e/L | D30: EF_DIESEL | E30: DEFRA 2024 — Mobile combustion, HGV diesel | F30: 2025-01-01
A31: Petrol — business vehicles | B31: 2.31 | C31: kgCO₂e/L | D31: EF_PETROL | E31: DEFRA 2024 — Passenger car petrol | F31: 2025-01-01
A32: LPG — forklifts | B32: 1.51 | C32: kgCO₂e/kg | D32: EF_LPG | E32: DEFRA 2024 — LPG combustion | F32: 2025-01-01
A33: Electricity — Eskom grid | B33: 0.82 | C33: kgCO₂e/kWh | D33: EF_ELEC | E33: Eskom NERSA 2024 — grid emission factor | F33: 2025-01-01
A34: Solar PV — onsite generation | B34: 0.025 | C34: kgCO₂e/kWh | D34: EF_SOLAR | E34: IEA / GHG Protocol — solar PV lifecycle | F34: 2025-01-01
A35: Municipal water | B35: 0.000344 | C35: tCO₂e/kL | D35: EF_WATER | E35: GHG Protocol — water supply & treatment | F35: 2025-01-01
A36: Waste to landfill | B36: 0.58 | C36: tCO₂e/tonne | D36: EF_LANDFILL | E36: DEFRA 2024 — landfilled commercial waste | F36: 2025-01-01
A37: Carbon Tax Tier 1 rate (ZAR) | B37: 236 | C37: ZAR/tCO₂e | D37: TAX_T1 | E37: SA Carbon Tax Act — Tier 1 rate 2025 (taxable above threshold) | F37: 2025-01-01
A38: Carbon Tax Tier 2 rate (ZAR) | B38: 640 | C38: ZAR/tCO₂e | D38: TAX_T2 | E38: SA Carbon Tax Act — projected escalation 2026 | F38: 2025-01-01
A39: Carbon Tax basic allowance | B39: 0.6 | C39: % exempt | D39: TAX_ALLOW | E39: SA Carbon Tax Act s7 — basic 60% tax-free allowance | F39: 2025-01-01
A41: BLOCK 2 — SCORING THRESHOLDS (used by E/S/G scorecards for banded scoring)
A42: Threshold | B42: Value | C42: Unit | D42: Code | E42: Used by / Applies to | F42: Rationale
A43: Scope 1+2 YoY reduction target | B43: 0.1 | C43: % | D43: THR_GHG_YOY | E43: E_Scorecard row 6 | F43: SBTi near-term: minimum 4.2% pa for 1.5°C; 10% stretch target
A44: Renewable electricity minimum | B44: 0.2 | C44: % | D44: THR_RE | E44: E_Scorecard row 13 | F44: RE100 entry threshold; SBTi Scope 2 lever
A45: Fleet L/100km tolerance over norm | B45: 1.05 | C45: multiplier | D45: THR_FUEL_TOL | E45: Fleet_Register, E_Scorecard row 15 | F45: 5% tolerance above OEM norm before flagged
A46: EV fleet % minimum (current) | B46: 0.05 | C46: % | D46: THR_EV_MIN | E46: E_Scorecard row 17 | F46: Min credible EV transition stake
A47: EV fleet % target 2030 | B47: 0.2 | C47: % | D47: THR_EV_2030 | E47: NetZero_Roadmap | F47: SBTi-aligned transport transition
A48: Waste diversion target | B48: 0.75 | C48: % | D48: THR_WASTE | E48: E_Scorecard row 19, Waste_Register | F48: ISO 14001 / NEMWA hierarchy alignment
A49: Waste diversion excellence | B49: 0.9 | C49: % | D49: THR_WASTE_X | E49: E_Scorecard row 19 | F49: Best-practice diversion (Oricol CPT benchmark)
A50: % Black employees target | B50: 0.6 | C50: % | D50: THR_BLACK | E50: EE_Scorecard, S_Scorecard row 5 | F50: EEA s27 demographic alignment; B-BBEE Mgt Control
A51: % Black female mgmt target | B51: 0.3 | C51: % | D51: THR_BFM | E51: EE_Scorecard, S_Scorecard row 6 | F51: B-BBEE Mgt Control sub-target
A52: % Persons with Disabilities target | B52: 0.02 | C52: % | D52: THR_PWD | E52: EE_Scorecard, S_Scorecard row 8 | F52: EEA s6 / Code of Good Practice on PWD
A53: Training hours per employee target | B53: 40 | C53: hours | D53: THR_TRAIN_HR | E53: S_Scorecard row 14 | F53: GRI 404-1; B-BBEE SD typical benchmark
A54: Mandatory grant recovery target | B54: 0.8 | C54: % | D54: THR_GRANT | E54: S_Scorecard row 15 | F54: SDL Act — full grant recovery achievable
... A65: Pillar target (FY26) | B65: 0.75 | C65: % | D65: TGT_PILLAR | E65: ESG_Dashboard column I | F65: Internal stretch target
A67: BLOCK 3 — B-BBEE GENERIC CODES (Statement 000 — Generic Scorecard weights — for B_BBEE_ESG sheet)
A68: Ownership | B68: 25 | C68: — | D68: BB_OWN | E68: Statement 100 | F68: Governance
A69: Management Control | B69: 19 | C69: Black 60%, BlackFem 30% | D69: BB_MC | E69: Statement 200 | F69: Social
A70: Skills Development | B70: 25 | C70: 6% payroll spend | D70: BB_SD | E70: Statement 300 | F70: Social
A71: Enterprise & Supplier Development | B71: 40 | C71: PP 25/QSE 15 | D71: BB_ESD | E71: Statement 400 | F71: Social/Governance
A72: Socio-Economic Development | B72: 5 | C72: 1% NPAT | D72: BB_SED | E72: Statement 500 | F72: Social
A73: TOTAL POINTS
A75: BLOCK 4 — B-BBEE STATUS LEVELS (Generic Code — used by B_BBEE_ESG status formula)
A76: Level 1 | B76: 100 | C76: 135% | D76: LVL_1
A77: Level 2 | B77: 95 | C77: 125% | D77: LVL_2
A78: Level 3 | B78: 90 | C78: 110% | D78: LVL_3
A79: Level 4
A80: Level 5 | B80: 75 | C80: 80% | D80: LVL_5
A81: Level 6
A82: Level 7 | B82: 55 | C82: 50% | D82: LVL_7
A83: Level 8 | B83: 40 | C83: 10% | D83: LVL_8
A84: Non-compliant | B84: 0 | C84: 0% | D84: LVL_NC
A86: BLOCK 5 — SCORING RUBRIC (universal banding logic applied across all scorecards)
A87: Quantitative — target met | B87: Actual ≥ Target | C87: Full points | D87: ✓ Met | E87: Diversion 91% vs 75% → full 5 pts | F87: Linear ramp up to max
A88: Quantitative — partial | B88: 50% ≤ Actual/Target < 100% | C88: Pro-rata (50-99%) | D88: ⚠ Partial | E88: Diversion 60% vs 75% → 4 pts | F88: MIN(Max, Actual/Target × Max)
A89: Quantitative — gap | B89: Actual/Target < 50% | C89: Zero | D89: ✗ Gap | E89: Diversion 30% vs 75% → 0 pts | F89: No partial credit below 50%
A90: Inverse metric (lower better) | B90: Actual ≤ Target | C90: Full points | D90: ✓ Met | E90: LTIFR 1.5 vs 2.0 → full 8 pts | F90: For LTIFR, fatalities, gaps
A91: Inverse — partial | B91: Target < Actual ≤ 2×Target | C91: Pro-rata | D91: ⚠ Partial | E91: LTIFR 3.0 vs 2.0 → 4 pts | F91: MAX(0, Max × (2-Actual/Target))
A92: Inverse — gap | B92: Actual > 2× Target | C92: Zero | D92: ✗ Gap | E92: LTIFR 5.0 vs 2.0 → 0 pts | F92: Hard floor
A93: Binary (Y/N) | B93: Yes = full / Partial = 50% / No = 0 | C93: Full / Half / Zero | D93: ✓/⚠/✗ | E93: EE Plan submitted → 5 pts | F93: For policy/compliance items
A94: Existence (count > 0) | B94: Source > 0 → full; else 0 | C94: Full or zero | D94: ✓ Met / ✗ Gap | E94: Fleet diesel logged → 5 pts | F94: For "baseline established" items
A95: Trend (YoY) | B95: ≥ target reduction | C95: Full points | D95: ✓ Met | E95: 10% YoY → full 10 pts | F95: Requires prior-year baseline
A97: BLOCK 6 — PILLAR WEIGHTS (used to compute overall ESG score)
A98: Environmental (E) | B98: 0.4 | C98: 108 | D98: WT_E | E98: GHG-weighted; FMCG/Distribution is fuel-intensive
A99: Social (S) | B99: 0.3 | C99: 100 | D99: WT_S | E99: Strong EE Act + SDL exposure in SA market
A100: Governance (G) | B100: 0.3 | C100: 100 | D100: WT_G | E100: King V mandatory for JSE-aligned firms
A101: TOTAL | B101: 1 | C101: 308 | D101: WT_TOT | E101: Must sum to 100%
A103: BLOCK 7 — ENTITY & REPORTING SETTINGS (overrides Cover sheet — toggle for template vs live instance)
A104: Entity name | B104: SG Consumer / SuperGroup SG Consumer (Pty) Ltd | D104: ENT_NAME | E104: Replace with client name on fork
A105: Reporting period | B105: FY 2025/2026 | Jul 2025 – Jun 2026 | D105: ENT_FY | E105: Used in headers and exports
A106: Baseline year (SBTi) | B106: FY 2025/26 | D106: ENT_BASE | E106: Locks Scope 1+2 baseline for YoY
A107: Net-zero target year | B107: 2050 | D107: ENT_NZ | E107: SBTi CNZS 2.0
A108: B-BBEE sector code | B108: Generic Code (Statement 000) | D108: ENT_BBEE | E108: Toggle: Generic / Transport / Agri / etc.
A109: Currency | B109: ZAR | D109: ENT_CCY | E109: For Carbon Tax + CSI
A110: Consultant | B110: Okiru Consulting | www.okiru.co.za | D110: ENT_CONS | E110: Branding
A111: Number of data months (current) | B111: 9 | D111: ENT_MOS | E111: Used to annualise YTD for full-year projection
A112: Annualisation factor | B112: =12/B111 -> 1.3333333 | D112: ENT_ANN | E112: Auto: 12 ÷ months entered

Sheet Audit_Log
A1: 📋 AUDIT LOG — Version control · change history · sign-offs
A2: Log every formula change, threshold update, scope extension. Critical for ISAE 3000 / external assurance trail.
A4: VERSION HISTORY
A5: Version | B5: Date | C5: Author | D5: Section | E5: Change Description | F5: Signed off by
A6: v1.0 | B6: 2025-09-01 | C6: Khethiwe Nkuna | D6: All sheets | E6: Initial toolkit build for SG Consumer FY25/26 baseline | F6: C Myezwa
A7: v1.1 | B7: 2025-11-15 | C7: Okiru Consulting | D7: E_Data | E7: Added SCOPE 1B–1D (generator, LPG, business cars) | F7: Z Mnanzana
A8: v1.2 | B8: 2026-01-10 | C8: Okiru Consulting | D8: Fleet_Register | E8: Added 134-vehicle register with L/100km norms by class | F8: Z Mnanzana
A9: v1.3 | B9: 2026-02-22 | C9: Okiru Consulting | D9: King5_Scorecard | E9: Migrated to Apply & Explain methodology — all 17 principles | F9: C Myezwa
A10: v1.4 | B10: 2026-04-01 | C10: Okiru Consulting | D10: NetZero_Roadmap | E10: Added SBTi CNZS 2.0 pathway and OER tier mapping | F10: C Myezwa
A11: v1.5 | B11: 2026-05-14 | C11: Okiru Consulting | D11: Engine rebuild | E11: Full scoring engine rebuild: Assumptions sheet, banded scoring, audit columns, dashboard charts, Materiality_Matrix, B_BBEE_ESG, Carbon_Tax. Productised template + SG Consumer live instance. | F11: [pending]
A12: v1.6 | B12: 2026-05-25 | C12: Okiru Consulting | D12: G_Data, King5_Scorecard, IFRS_S1_S2, GARP_GRAP, ISO_Tracker, SAQ_Supplier | E12: Populated governance evidence from SG Consumer policy stack (Code of Ethics, CSI/SED, EE & Workplace Diversity, Supplier Code — all Rev 2 dated 30 Jan 2023) + SG Consumer POPI Act Consent (Jan 2026). Updates: G_Data Y/N flags with traceable source notes; King V Apply/Explain status for 17 principles; IFRS S1/S2 Partially Disclosed flags where policy commitments exist without operational evidence; GARP_GRAP control evidence column populated; ISO 14001/45001/26000/27001 clause-level status. No formulas changed. | F12: [pending C Myezwa]
A13: 2026-05-27 | B13: v1.7 | C13: SG Consumer data load — Coba 27 May 2026 submission | D13: Payroll R10,331,940.87; FTE 426; Board comp (Group, 7 directors); CSI/SED beneficiaries (10 programmes, R45k budget); H&S incidents (19 from SHE register); Be Heard hotline confirmed | E13: Okiru Consulting | F13: Outstanding: EEA2 race/gender split for 426 FTE; Scope 3 business travel km; CSI per-project spend split; POPIA case data (HO)
A14: FORMULA CHANGE LOG — v1.5 engine rebuild (target counts; populated in Step 2)
A15: Sheet | B15: Cells touched | C15: From | D15: To | E15: Rationale | F15: Tested
A16: E_Scorecard | B16: C6:C29 | C16: 17 hardcoded zeros | D16: Banded scoring referencing E_Data + Assumptions | E16: Engine rebuild — every score must trace to source | F16: pending
A17: S_Scorecard | B17: C6:C27 | C17: 16 hardcoded zeros | D17: Banded scoring referencing S_Data + Assumptions | E17: Engine rebuild | F17: pending
A18: G_Scorecard | B18: C6:C25 | C18: 13 hardcoded zeros | D18: Banded scoring referencing G_Data + Assumptions | E18: Engine rebuild | F18: pending
A19: G_Data | B19: F5:F24 | C19: All zeros (no logic) | D19: Banded Y/N + count scoring | E19: Wire governance data to G_Scorecard | F19: pending
A20: GARP_GRAP | B20: F:H | C20: No formulas | D20: Severity × Likelihood scoring; control modifier | E20: Materiality matrix feed | F20: pending
A21: ESG_Dashboard | B21: B25,B27:B29,B31 | C21: Hardcoded =0 | D21: Live pulls from data + scorecard sheets | E21: Make KPI tiles real | F21: pending
A22: Standards_Map | B22: I column | C22: References still valid | D22: Add Audit_Log + Assumptions cross-refs | E22: Complete the map | F22: pending
A25: SIGN-OFF — required before publishing to client
A26: Role | B26: Name | C26: Date | D26: Signature | E26: Scope of approval
A27: Senior ESG Consultant | B27: Khethiwe Nkuna | E27: Technical accuracy of E/S/G scoring
A28: Managing Director | B28: Chengetai Myezwa | E28: Client suitability and risk
A29: Senior B-BBEE Consultant | B29: Zoleka Mnanzana | E29: B-BBEE Generic Code element alignment
A30: Client representative | B30: [Client name] | E30: Acceptance and data accuracy

Sheet ESG_Dashboard
A1: 🌱 ESG INTELLIGENCE DASHBOARD — SG Consumer | FY 2025/26 | Powered by Okiru Consulting
A2: Net-Zero · King V · IFRS S1/S2 · GARP/GRAP · ISO 14001/45001/27001 · Employment Equity · WSP/ATR
A4: ESG PILLAR SCORES | L4: EXECUTIVE SUMMARY — Board view
A5: Pillar | B5: Score | C5: Max | D5: % Score | E5: Rating | F5: Key Gap | G5: Net-Zero Link | H5: Standards | I5: Target FY26 | J5: Status | L5: Overall ESG Score | M5: =TEXT(D9,"0.0%") -> 44.6%
A6: 🟢 Environmental (E) | B6: =E_Scorecard!D30 -> 36 | C6: 108 | D6: =IFERROR(B6/C6,0) -> 0.33333333 | E6: =IF(D6>=Assumptions!$B$62,"★★★ Excellent",IF(D6>=Assumptions!$B$63,"★★ Good",IF(D6>=Assumptions!$B$64,"★ Adequate","⚠ Attention"))) -> ⚠ Attention | F6: GHG Scope 1+2+3 | G6: Fleet diesel dominant | H6: IFRS S2/GRI 305/ISO14001 | I6: ≥75/100 | J6: =IF(D6>=Assumptions!$B$65,"✓ On Track","⚠ Behind") -> ⚠ Behind | L6: Rating | M6: =IF(D9>=Assumptions!$B$62,"★★★ Excellent",IF(D9>=Assumptions!$B$63,"★★ Good",IF(D9>=Assumptions!$B$64,"★ Adequate","⚠ Needs Attention"))) -> ⚠ Needs Attention
A7: 🔵 Social (S) | B7: =S_Scorecard!D28 -> 33 | C7: 100 | D7: =IFERROR(B7/C7,0) -> 0.33 | E7: =IF(D7>=Assumptions!$B$62,"★★★ Excellent",IF(D7>=Assumptions!$B$63,"★★ Good",IF(D7>=Assumptions!$B$64,"★ Adequate","⚠ Attention"))) -> ⚠ Attention | F7: EE targets | G7: EE + WSP compliance | H7: EEA/GRI 405/ISO45001 | I7: ≥75/100 | J7: =IF(D7>=Assumptions!$B$65,"✓ On Track","⚠ Behind") -> ⚠ Behind | L7: Strongest pillar | M7: =INDEX(A6:A8,MATCH(MAX(D6:D8),D6:D8,0)) -> 🟣 Governance (G)
A8: 🟣 Governance (G) | B8: =G_Scorecard!D26 -> 64.852941 | C8: 100 | D8: =IFERROR(B8/C8,0) -> 0.64852941 | E8: =IF(D8>=Assumptions!$B$62,"★★★ Excellent",IF(D8>=Assumptions!$B$63,"★★ Good",IF(D8>=Assumptions!$B$64,"★ Adequate","⚠ Attention"))) -> ★ Adequate | F8: King V full adoption | G8: IFRS S2 + King V P10 | H8: King V/IFRS S1-S2/POPIA | I8: ≥75/100 | J8: =IF(D8>=Assumptions!$B$65,"✓ On Track","⚠ Behind") -> ⚠ Behind | L8: Weakest pillar | M8: =INDEX(A6:A8,MATCH(MIN(D6:D8),D6:D8,0)) -> 🔵 Social (S)
A9: OVERALL ESG SCORE | D9: =IFERROR((E_Scorecard!D30/100+S_Scorecard!D28/100+G_Scorecard!D26/100)/3,0) -> 0.44617647 | L9: Material risks | M9: =GARP_GRAP!C28&" of "&GARP_GRAP!C27&" risks logged" -> 12 of 18 risks logged
L10: King V status | M10: =King5_Scorecard!E21&"/170 ("&TEXT(King5_Scorecard!E22,"0.0%")&")" -> 135/170 (79.4%)
A11: GHG EMISSIONS SUMMARY (tCO₂e) | 9 months actuals Jul-25 to Mar-26
A12: Scope | B12: Jul-25 | C12: Aug-25 | D12: Sep-25 | E12: Oct-25 | F12: Nov-25 | G12: Dec-25 | H12: Jan-26 | I12: Feb-26 | J12: Mar-26 | K12: YTD Total | L12: Annualised | M12: YoY Target | N12: Status
A13: Scope 1 — Fleet Diesel | B13: =IFERROR(E_Data!C75,0) -> 79354.07 | C13: =IFERROR(E_Data!D75,0) -> 68178.89 | D13: =IFERROR(E_Data!E75,0) -> 65076.46 | E13: =IFERROR(E_Data!F75,0) -> 73386.91 | F13: =IFERROR(E_Data!G75,0) -> 67294.64 | G13: =IFERROR(E_Data!H75,0) -> 57589.35 | H13: =IFERROR(E_Data!I75,0) -> 48740.43 | I13: =IFERROR(E_Data!J75,0) -> 63979.73 | J13: =IFERROR(E_Data!K75,0) -> 65865.05 | K13: =IFERROR(SUM(B13:J13),0) -> 589465.53 | L13: =IFERROR(K13*Assumptions!$B$112,0) -> 785954.04 | M13: — baseline year — | N13: ○ Baseline
A14: Scope 1 — Generator | B14: =IFERROR(E_Data!C76,0) -> 1289.14 | C14: =IFERROR(E_Data!D76,0) -> 0 | D14: =IFERROR(E_Data!E76,0) -> 0 | E14: =IFERROR(E_Data!F76,0) -> 0 | F14: =IFERROR(E_Data!G76,0) -> 0 | G14: =IFERROR(E_Data!H76,0) -> 295 | H14: =IFERROR(E_Data!I76,0) -> 0 | I14: =IFERROR(E_Data!J76,0) -> 0 | J14: =IFERROR(E_Data!K76,0) -> 597 | K14: =IFERROR(SUM(B14:J14),0) -> 2181.14 | L14: =IFERROR(K14*Assumptions!$B$112,0) -> 2908.1867 | M14: — baseline year — | N14: ○ Baseline
A15: Scope 1 — LPG Forklifts | B15: =IFERROR(E_Data!C77,0) -> 0 | C15: =IFERROR(E_Data!D77,0) -> 570 | D15: =IFERROR(E_Data!E77,0) -> 190 | E15: =IFERROR(E_Data!F77,0) -> 190 | F15: =IFERROR(E_Data!G77,0) -> 380 | G15: =IFERROR(E_Data!H77,0) -> 570 | H15: =IFERROR(E_Data!I77,0) -> 380 | I15: =IFERROR(E_Data!J77,0) -> 0 | J15: =IFERROR(E_Data!K77,0) -> 0 | K15: =IFERROR(SUM(B15:J15),0) -> 2280 | L15: =IFERROR(K15*Assumptions!$B$112,0) -> 3040 | M15: — baseline year — | N15: ○ Baseline
A16: Scope 2 — Electricity (grid) | B16: =IFERROR(E_Data!C82,0) -> 288638.88 | C16: =IFERROR(E_Data!D82,0) -> 304665.02 | D16: =IFERROR(E_Data!E82,0) -> 294858.49 | E16: =IFERROR(E_Data!F82,0) -> 263387.94 | F16: =IFERROR(E_Data!G82,0) -> 255634.03 | G16: =IFERROR(E_Data!H82,0) -> 290165.23 | H16: =IFERROR(E_Data!I82,0) -> 261690.52 | I16: =IFERROR(E_Data!J82,0) -> 315712.51 | J16: =IFERROR(E_Data!K82,0) -> 314825.82 | K16: =IFERROR(SUM(B16:J16),0) -> 2589578.4 | L16: =IFERROR(K16*Assumptions!$B$112,0) -> 3452771.3 | M16: — baseline year — | N16: ○ Baseline
A17: Scope 3 — Water | B17: =IFERROR(E_Data!C83,0) -> 409.41 | C17: =IFERROR(E_Data!D83,0) -> 391.39 | D17: =IFERROR(E_Data!E83,0) -> 380.72 | E17: =IFERROR(E_Data!F83,0) -> 534.81 | F17: =IFERROR(E_Data!G83,0) -> 476.36 | G17: =IFERROR(E_Data!H83,0) -> 499.53 | H17: =IFERROR(E_Data!I83,0) -> 533.01 | I17: =IFERROR(E_Data!J83,0) -> 560.94 | J17: =IFERROR(E_Data!K83,0) -> 570.24 | K17: =IFERROR(SUM(B17:J17),0) -> 4356.41 | L17: =IFERROR(K17*Assumptions!$B$112,0) -> 5808.5467 | M17: — baseline year — | N17: ○ Baseline
A18: TOTAL GHG (Scope 1+2+3) | B18: =SUM(B13:B17) -> 369691.5 | C18: =SUM(C13:C17) -> 373805.3 | D18: =SUM(D13:D17) -> 360505.67 | E18: =SUM(E13:E17) -> 337499.66 | F18: =SUM(F13:F17) -> 323785.03 | G18: =SUM(G13:G17) -> 349119.11 | H18: =SUM(H13:H17) -> 311343.96 | I18: =SUM(I13:I17) -> 380253.18 | ... K18: =SUM(K13:K17) -> 3187861.5 | L18: =K18*Assumptions!$B$112 -> 4250482 | M18: — baseline year — | N18: ○ Baseline
A19: KEY NET-ZERO & ESG KPIs — YTD FY2025/26
A20: KPI | B20: Value | C20: Benchmark | D20: Source
A21: Total fleet diesel (litres YTD) | B21: =E_Data!L19 -> 589465.53 | C21: <600,000 L target | D21: Fleet_Register
A22: Total fleet tCO₂e Scope 1 | B22: =IFERROR(E_Data!L79,0) -> 594980.49 | C22: <1,600 tCO₂e | D22: E_Data
A23: Total electricity kWh YTD | B23: =E_Data!L46 -> 2589578.4 | C23: Monitor vs prior year | D23: Utility_Bills
A24: Total electricity tCO₂e Scope 2 | B24: =IFERROR(E_Data!L82,0) -> 2589578.4 | C24: Target: reduce 10% YoY | D24: E_Data
A25: Fleet avg L/100km vs norm | B25: =IFERROR(AVERAGEIFS(Fleet_Register!K4:K19,Fleet_Register!K4:K19,">0"),"No data") -> No data | C25: ≤ vehicle norm | D25: Fleet_Register
A26: Oricol CPT waste diversion % | B26: =Waste_Register!B16 -> 0.911 | C26: ≥90% — Target Met ✓ | D26: Waste_Register
A27: EE: % Black employees | B27: =EE_Scorecard!B5 -> 0 | C27: ≥60% | D27: EE_Scorecard
A28: WSP submitted to SETA | B28: =S_Data!B45 -> 0 | C28: Yes — Required | D28: S_Data
A29: LTIFR YTD | B29: =IFERROR(S_Data!G35,"No data") -> Awaiting hours worked | C29: <2.0 | D29: S_Data
A30: King V score | B30: =King5_Scorecard!E21 -> 135 | C30: ≥100/170 | D30: King5_Scorecard
A31: IFRS S1/S2 disclosures | B31: =IFERROR(COUNTIF(IFRS_S1_S2!D4:D40,"Yes")/MAX(1,COUNTA(IFRS_S1_S2!A4:A40)-COUNTBLANK(IFRS_S1_S2!A4:A40)),0) -> 0 | C31: ≥80% disclosed | D31: IFRS_S1_S2
A32: ISO 14001 certification status | C32: Certified (target) | D32: ISO_Tracker
A75: Materiality data (auto)
A76: Risk | B76: Severity | C76: Likelihood | D76: Risk Score
A77: =GARP_GRAP!B5 -> Climate Physical Risk | B77: =IF(GARP_GRAP!E5="High",5,IF(GARP_GRAP!E5="Medium",3,IF(GARP_GRAP!E5="Low",1,IF(GARP_GRAP!E5="Req",4,0)))) -> 5 | C77: =GARP_GRAP!I5 -> 4 | D77: =GARP_GRAP!J5 -> 20
A78: =GARP_GRAP!B6 -> Climate Transition Risk | B78: =IF(GARP_GRAP!E6="High",5,IF(GARP_GRAP!E6="Medium",3,IF(GARP_GRAP!E6="Low",1,IF(GARP_GRAP!E6="Req",4,0)))) -> 5 | C78: =GARP_GRAP!I6 -> 5 | D78: =GARP_GRAP!J6 -> 25
A79: =GARP_GRAP!B7 -> Operational Risk — Fleet | B79: =IF(GARP_GRAP!E7="High",5,IF(GARP_GRAP!E7="Medium",3,IF(GARP_GRAP!E7="Low",1,IF(GARP_GRAP!E7="Req",4,0)))) -> 5 | C79: =GARP_GRAP!I7 -> 5 | D79: =GARP_GRAP!J7 -> 25
A80: =GARP_GRAP!B8 -> Regulatory Risk — EE Act | B80: =IF(GARP_GRAP!E8="High",5,IF(GARP_GRAP!E8="Medium",3,IF(GARP_GRAP!E8="Low",1,IF(GARP_GRAP!E8="Req",4,0)))) -> 3 | C80: =GARP_GRAP!I8 -> 3 | D80: =GARP_GRAP!J8 -> 9
A81: =GARP_GRAP!B9 -> Regulatory Risk — POPIA | B81: =IF(GARP_GRAP!E9="High",5,IF(GARP_GRAP!E9="Medium",3,IF(GARP_GRAP!E9="Low",1,IF(GARP_GRAP!E9="Req",4,0)))) -> 3 | C81: =GARP_GRAP!I9 -> 3 | D81: =GARP_GRAP!J9 -> 9
A82: =GARP_GRAP!B10 -> Financial Risk — SDL/WSP | B82: =IF(GARP_GRAP!E10="High",5,IF(GARP_GRAP!E10="Medium",3,IF(GARP_GRAP!E10="Low",1,IF(GARP_GRAP!E10="Req",4,0)))) -> 3 | C82: =GARP_GRAP!I10 -> 3 | D82: =GARP_GRAP!J10 -> 9
A83: =GARP_GRAP!B11 -> Reputational Risk — ESG | B83: =IF(GARP_GRAP!E11="High",5,IF(GARP_GRAP!E11="Medium",3,IF(GARP_GRAP!E11="Low",1,IF(GARP_GRAP!E11="Req",4,0)))) -> 3 | C83: =GARP_GRAP!I11 -> 3 | D83: =GARP_GRAP!J11 -> 9
A84: =GARP_GRAP!B12 -> Environmental Risk — Waste | B84: =IF(GARP_GRAP!E12="High",5,IF(GARP_GRAP!E12="Medium",3,IF(GARP_GRAP!E12="Low",1,IF(GARP_GRAP!E12="Req",4,0)))) -> 1 | C84: =GARP_GRAP!I12 -> 2 | D84: =GARP_GRAP!J12 -> 2
A85: =GARP_GRAP!B13 -> Supply Chain Risk | B85: =IF(GARP_GRAP!E13="High",5,IF(GARP_GRAP!E13="Medium",3,IF(GARP_GRAP!E13="Low",1,IF(GARP_GRAP!E13="Req",4,0)))) -> 3 | C85: =GARP_GRAP!I13 -> 4 | D85: =GARP_GRAP!J13 -> 12
A86: =GARP_GRAP!B14 -> Technology Risk | B86: =IF(GARP_GRAP!E14="High",5,IF(GARP_GRAP!E14="Medium",3,IF(GARP_GRAP!E14="Low",1,IF(GARP_GRAP!E14="Req",4,0)))) -> 1 | C86: =GARP_GRAP!I14 -> 2 | D86: =GARP_GRAP!J14 -> 2

Sheet E_Data
A1: E_DATA — ENVIRONMENTAL RAW DATA | SG Consumer | FY 2025/26
A3: EMISSION FACTORS (DEFRA 2024 / Eskom NERSA 2024) — edit only if factors updated
A4: EF_DIESEL | B4: 2.68 | C4: kgCO₂e/L | D4: Road freight diesel (DEFRA 2024)
A5: EF_PETROL | B5: 2.31 | C5: kgCO₂e/L | D5: Business car petrol
A6: EF_LPG | B6: 1.51 | C6: kgCO₂e/kg | D6: LPG forklifts (DBN warehouse)
A7: EF_ELEC | B7: 0.82 | C7: kgCO₂e/kWh | D7: Eskom grid — NERSA 2024
A8: EF_SOLAR | B8: 0.025 | C8: kgCO₂e/kWh | D8: Solar PV (onsite generation)
A9: EF_WATER | B9: 0.000344 | C9: tCO₂e/kL | D9: Municipal water (GHG Protocol)
A10: EF_LANDFILL | B10: 0.58 | C10: tCO₂e/tonne | D10: Waste to landfill
A12: SCOPE 1A — ROAD FREIGHT DIESEL (Fleet litres per depot) [Source: Mariette Dashboard fuel consumption sheet]
A13: Depot/Source | B13: Unit | C13: Jul-25 | D13: Aug-25 | E13: Sep-25 | F13: Oct-25 | G13: Nov-25 | H13: Dec-25 | I13: Jan-26 | J13: Feb-26 | K13: Mar-26 | L13: YTD Total | M13: tCO₂e YTD | N13: Source File
A14: SG Consumer – BLOEM | B14: litres | C14: 17639.52 | D14: 12721.25 | E14: 5877.41 | F14: 6836 | G14: 5002 | H14: 6977 | I14: 4713 | J14: 6995.19 | K14: 5922 | L14: =SUM(C14:K14) -> 72683.37 | M14: =L14*E_Data!$B$4/1000 -> 194.79143 | N14: Mariette/STATS/DASHBOARD 2025-2026
A15: SG Consumer – CPT | B15: litres | C15: 6789 | D15: 6039 | E15: 5927 | F15: 6936 | G15: 5857 | H15: 6518 | I15: 4171.01 | J15: 3146 | K15: 6417 | L15: =SUM(C15:K15) -> 51800.01 | M15: =L15*E_Data!$B$4/1000 -> 138.82403 | N15: Mariette/STATS/DASHBOARD 2025-2026
A16: SG Consumer – DBN | B16: litres | C16: 17716.57 | D16: 14729.31 | E16: 16273.31 | F16: 18434 | G16: 18357.36 | H16: 18828 | I16: 13750.41 | J16: 19177.8 | K16: 19512.38 | L16: =SUM(C16:K16) -> 156779.14 | M16: =L16*E_Data!$B$4/1000 -> 420.1681 | N16: Mariette/STATS/DASHBOARD 2025-2026
A17: SG Consumer – ISANDO | B17: litres | C17: 35757.98 | D17: 33349.25 | E17: 35581.74 | F17: 39804.91 | G17: 36773.79 | H17: 23998.48 | I17: 24838.14 | J17: 33208.74 | K17: 32745.8 | L17: =SUM(C17:K17) -> 296058.83 | M17: =L17*E_Data!$B$4/1000 -> 793.43766 | N17: Mariette/STATS/DASHBOARD 2025-2026
A18: SG Consumer – PE | B18: litres | C18: 1451 | D18: 1340.08 | E18: 1417 | F18: 1376 | G18: 1304.49 | H18: 1267.87 | I18: 1267.87 | J18: 1452 | K18: 1267.87 | L18: =SUM(C18:K18) -> 12144.18 | M18: =L18*E_Data!$B$4/1000 -> 32.546402 | N18: Mariette/STATS/DASHBOARD 2025-2026
A19: TOTAL FLEET DIESEL | C19: =C14+C15+C16+C17+C18 -> 79354.07 | D19: =D14+D15+D16+D17+D18 -> 68178.89 | E19: =E14+E15+E16+E17+E18 -> 65076.46 | F19: =F14+F15+F16+F17+F18 -> 73386.91 | G19: =G14+G15+G16+G17+G18 -> 67294.64 | H19: =H14+H15+H16+H17+H18 -> 57589.35 | I19: =I14+I15+I16+I17+I18 -> 48740.43 | J19: =J14+J15+J16+J17+J18 -> 63979.73 | ... L19: =L14+L15+L16+L17+L18 -> 589465.53 | M19: =L19*E_Data!$B$4/1000 -> 1579.7676
A21: SCOPE 1B — GENERATOR DIESEL (litres per depot) [Source: Mariette Dashboard / Bowser Recon]
A22: Depot | B22: Unit | C22: Jul-25 | D22: Aug-25 | E22: Sep-25 | F22: Oct-25 | G22: Nov-25 | H22: Dec-25 | I22: Jan-26 | J22: Feb-26 | K22: Mar-26 | L22: YTD Total | M22: tCO₂e YTD
A23: Generator – BLOEM | B23: litres | C23: 650 | D23: 0 | E23: 0 | F23: 0 | G23: 0 | H23: 0 | I23: 0 | J23: 0 | K23: 597 | L23: =SUM(C23:K23) -> 1247 | M23: =L23*E_Data!$B$4/1000 -> 3.34196
A24: Generator – CPT | B24: litres | C24: 0 | D24: 0 | E24: 0 | F24: 0 | G24: 0 | H24: 0 | I24: 0 | J24: 0 | K24: 0 | L24: =SUM(C24:K24) -> 0 | M24: =L24*E_Data!$B$4/1000 -> 0
A25: Generator – DBN | B25: litres | C25: 639.14 | D25: 0 | E25: 0 | F25: 0 | G25: 0 | H25: 0 | I25: 0 | J25: 0 | K25: 0 | L25: =SUM(C25:K25) -> 639.14 | M25: =L25*E_Data!$B$4/1000 -> 1.7128952
A26: Generator – ISANDO | B26: litres | C26: 0 | D26: 0 | E26: 0 | F26: 0 | G26: 0 | H26: 0 | I26: 0 | J26: 0 | K26: 0 | L26: =SUM(C26:K26) -> 0 | M26: =L26*E_Data!$B$4/1000 -> 0
A27: Generator – PE | B27: litres | C27: 0 | D27: 0 | E27: 0 | F27: 0 | G27: 0 | H27: 295 | I27: 0 | J27: 0 | K27: 0 | L27: =SUM(C27:K27) -> 295 | M27: =L27*E_Data!$B$4/1000 -> 0.7906
A28: TOTAL GENERATOR | C28: =C23+C24+C25+C26+C27 -> 1289.14 | D28: =D23+D24+D25+D26+D27 -> 0 | E28: =E23+E24+E25+E26+E27 -> 0 | F28: =F23+F24+F25+F26+F27 -> 0 | G28: =G23+G24+G25+G26+G27 -> 0 | H28: =H23+H24+H25+H26+H27 -> 295 | I28: =I23+I24+I25+I26+I27 -> 0 | J28: =J23+J24+J25+J26+J27 -> 0 | ... L28: =L23+L24+L25+L26+L27 -> 2181.14 | M28: =L28*E_Data!$B$4/1000 -> 5.8454552
A30: SCOPE 1C — LPG FORKLIFTS (kg per depot) [Source: Mariette Dashboard gas-forklifts sheet]
A31: Depot/Unit | B31: Unit | C31: Jul-25 | D31: Aug-25 | E31: Sep-25 | F31: Oct-25 | G31: Nov-25 | H31: Dec-25 | I31: Jan-26 | J31: Feb-26 | K31: Mar-26 | L31: YTD kg | M31: tCO₂e YTD
A32: LPG Forklifts – DBN | B32: kg | C32: 0 | D32: 570 | E32: 190 | F32: 190 | G32: 380 | H32: 570 | I32: 380 | J32: 0 | K32: 0 | L32: =SUM(C32:K32) -> 2280 | M32: =L32*E_Data!$B$6/1000 -> 3.4428
A33: NOTE: BLOEM, CPT, ISANDO, PE use electric/lithium-battery forklifts — no LPG emissions. Sanulac data confirms depot-level forklift types.
A35: SCOPE 1D — ROAD BUSINESS (Solly's car, ISANDO) [Source: Mariette Dashboard fuel consumption sheet]
A36: Source | B36: Unit | C36: Jul-25 | D36: Aug-25 | E36: Sep-25 | F36: Oct-25 | G36: Nov-25 | H36: Dec-25 | I36: Jan-26 | J36: Feb-26 | K36: Mar-26 | L36: YTD | M36: tCO₂e
A37: Solly's Car – ISANDO | B37: litres | C37: 139.81 | D37: 142.25 | E37: 93.22 | F37: 109.49 | G37: 143.81 | H37: 74.68 | I37: 109.59 | J37: 98 | K37: 142.97 | L37: =SUM(C37:K37) -> 1053.82 | M37: =L37*E_Data!$B$5/1000 -> 2.4343242
A39: SCOPE 2 — ELECTRICITY (kWh per depot/landlord) [Source: Mariette Utility Bills 2025-26]
A40: Depot / Landlord | B40: Unit | C40: Jul-25 | D40: Aug-25 | E40: Sep-25 | F40: Oct-25 | G40: Nov-25 | H40: Dec-25 | I40: Jan-26 | J40: Feb-26 | K40: Mar-26 | L40: YTD kWh | M40: tCO₂e YTD | N40: Landlord
A41: SG Consumer – BLOEM | B41: kWh | C41: 20495 | D41: 26100 | E41: 26118 | F41: 13295 | G41: 12343 | H41: 12343 | I41: 12343 | J41: 8126 | K41: 8131 | L41: =SUM(C41:K41) -> 139294 | M41: =L41*E_Data!$B$7/1000 -> 114.22108 | N41: KAVOD
A42: SG Consumer – CPT | B42: kWh | C42: 35751.88 | D42: 37731.52 | E42: 37625.99 | F42: 31990.94 | G42: 32243.53 | H42: 32243.53 | I42: 32524.52 | J42: 33991.51 | K42: 39024.17 | L42: =SUM(C42:K42) -> 313127.59 | M42: =L42*E_Data!$B$7/1000 -> 256.76462 | N42: SPEAR
A43: SG Consumer – DBN | B43: kWh | C43: 73374 | D43: 74374 | E43: 74374 | F43: 67241 | G43: 68442 | H43: 65167 | I43: 51805 | J43: 119050 | K43: 75298 | L43: =SUM(C43:K43) -> 669125 | M43: =L43*E_Data!$B$7/1000 -> 548.6825 | N43: EXCELLERATE
A44: SG Consumer – ISANDO | B44: kWh | C44: 147015 | D44: 152733 | E44: 143245 | F44: 137371 | G44: 126447 | H44: 165869 | I44: 149823 | J44: 138674 | K44: 137607 | L44: =SUM(C44:K44) -> 1298784 | M44: =L44*E_Data!$B$7/1000 -> 1065.0029 | N44: LEXSHELL 280 INVESTMENTS
A45: SG Consumer – PE | B45: kWh | C45: 12003 | D45: 13726.5 | E45: 13495.5 | F45: 13490 | G45: 16158.5 | H45: 14542.7 | I45: 15195 | J45: 15871 | K45: 54765.65 | L45: =SUM(C45:K45) -> 169247.85 | M45: =L45*E_Data!$B$7/1000 -> 138.78324 | N45: CLEMLEN INVESTMENTS NO 10
A46: TOTAL ELECTRICITY | C46: =C41+C42+C43+C44+C45 -> 288638.88 | D46: =D41+D42+D43+D44+D45 -> 304665.02 | E46: =E41+E42+E43+E44+E45 -> 294858.49 | F46: =F41+F42+F43+F44+F45 -> 263387.94 | G46: =G41+G42+G43+G44+G45 -> 255634.03 | H46: =H41+H42+H43+H44+H45 -> 290165.23 | I46: =I41+I42+I43+I44+I45 -> 261690.52 | J46: =J41+J42+J43+J44+J45 -> 315712.51 | ... M46: =M41+M42+M43+M44+M45 -> 2123.4543
A48: SOLAR GENERATION (enter kWh generated — reduces Scope 2) [JHB: Graeme Barand system; DBN: EDGE cert in progress]
A49: Solar Source | B49: kWh | C49: Jul-25 | D49: Aug-25 | E49: Sep-25 | F49: Oct-25 | G49: Nov-25 | H49: Dec-25 | I49: Jan-26 | J49: Feb-26 | K49: Mar-26 | L49: YTD kWh | M49: tCO₂e avoided
A50: Solar – ISANDO (JHB) | B50: kWh | C50: 0 | D50: 0 | E50: 0 | F50: 0 | G50: 0 | H50: 0 | I50: 0 | J50: 0 | K50: 0 | L50: =SUM(C50:K50) -> 0 | M50: =-L50*E_Data!$B$8/1000 -> 0
A51: Solar – DBN (EDGE) | B51: kWh | C51: 0 | D51: 0 | E51: 0 | F51: 0 | G51: 0 | H51: 0 | I51: 0 | J51: 0 | K51: 0 | L51: =SUM(C51:K51) -> 0 | M51: =-L51*E_Data!$B$8/1000 -> 0
A52: Solar – CPT | B52: kWh | C52: 0 | D52: 0 | E52: 0 | F52: 0 | G52: 0 | H52: 0 | I52: 0 | J52: 0 | K52: 0 | L52: =SUM(C52:K52) -> 0 | M52: =-L52*E_Data!$B$8/1000 -> 0
A53: Solar – BLOEM | B53: kWh | C53: 0 | D53: 0 | E53: 0 | F53: 0 | G53: 0 | H53: 0 | I53: 0 | J53: 0 | K53: 0 | L53: =SUM(C53:K53) -> 0 | M53: =-L53*E_Data!$B$8/1000 -> 0
A54: Solar – PE | B54: kWh | C54: 0 | D54: 0 | E54: 0 | F54: 0 | G54: 0 | H54: 0 | I54: 0 | J54: 0 | K54: 0 | L54: =SUM(C54:K54) -> 0 | M54: =-L54*E_Data!$B$8/1000 -> 0
A56: WATER CONSUMPTION (kL per depot) [Source: Mariette electricity & water sheet — utility bills data]
A57: Depot | B57: Unit | C57: Jul-25 | D57: Aug-25 | E57: Sep-25 | F57: Oct-25 | G57: Nov-25 | H57: Dec-25 | I57: Jan-26 | J57: Feb-26 | K57: Mar-26 | L57: YTD kL | M57: tCO₂e YTD
A58: SG Consumer – BLOEM | B58: kL | C58: 45.57 | D58: 45.57 | E58: 45.57 | F58: 35 | G58: 35 | H58: 35 | I58: 35 | J58: 67.95 | K58: 67.95 | L58: =SUM(C58:K58) -> 412.61 | M58: =L58*E_Data!$B$9 -> 0.14193784
A59: SG Consumer – CPT | B59: kL | C59: 0 | D59: 0 | E59: 0 | F59: 0 | G59: 50 | H59: 50 | I59: 0 | J59: 0 | K59: 0 | L59: =SUM(C59:K59) -> 100 | M59: =L59*E_Data!$B$9 -> 0.0344
A60: SG Consumer – DBN | B60: kL | C60: 47 | D60: 48 | E60: 48 | F60: 99.6 | G60: 108.1 | H60: 112.6 | I60: 135.2 | J60: 229.4 | K60: 117.78 | L60: =SUM(C60:K60) -> 945.68 | M60: =L60*E_Data!$B$9 -> 0.32531392
A61: SG Consumer – ISANDO | B61: kL | C61: 243 | D61: 256 | E61: 241 | F61: 241 | G61: 200 | H61: 227 | I61: 255 | J61: 211 | K61: 258 | L61: =SUM(C61:K61) -> 2132 | M61: =L61*E_Data!$B$9 -> 0.733408
A62: SG Consumer – PE | B62: kL | C62: 73.84 | D62: 41.82 | E62: 46.15 | F62: 159.21 | G62: 83.26 | H62: 74.93 | I62: 107.81 | J62: 52.59 | K62: 126.51 | L62: =SUM(C62:K62) -> 766.12 | M62: =L62*E_Data!$B$9 -> 0.26354528
A63: TOTAL WATER | C63: =C58+C59+C60+C61+C62 -> 409.41 | D63: =D58+D59+D60+D61+D62 -> 391.39 | E63: =E58+E59+E60+E61+E62 -> 380.72 | F63: =F58+F59+F60+F61+F62 -> 534.81 | G63: =G58+G59+G60+G61+G62 -> 476.36 | H63: =H58+H59+H60+H61+H62 -> 499.53 | I63: =I58+I59+I60+I61+I62 -> 533.01 | J63: =J58+J59+J60+J61+J62 -> 560.94 | ... M63: =M58+M59+M60+M61+M62 -> 1.498605
A65: WASTE DATA (% recycled per month from Cority; Oricol Mar-26 actual) [Source: Mariette waste sheet + Oricol sustainability report]
A66: Metric | B66: Unit | C66: Jul-25 | D66: Aug-25 | E66: Sep-25 | F66: Oct-25 | G66: Nov-25 | H66: Dec-25 | I66: Jan-26 | J66: Feb-26 | K66: Mar-26 | L66: YTD Avg | M66: Target
A67: % Waste Recycled (all depots) | B67: % | C67: 10.65 | D67: 16.24 | E67: 11.06 | F67: 8.89 | G67: 26.42 | H67: 10.68 | I67: 4.6 | J67: 13.73 | K67: 9.56 | L67: =AVERAGE(C67:K67) -> 12.425556 | M67: 30%+
A68: CPT Oricol — Total Waste (kg) | B68: kg | C68: — | D68: — | E68: — | F68: — | G68: — | H68: — | I68: — | J68: — | K68: — | L68: 22470 | M68: Mar-26 actual
A69: CPT Oricol — % Landfill | B69: % | C69: — | D69: — | E69: — | F69: — | G69: — | H69: — | I69: — | J69: — | K69: — | L69: 8.9 | M69: <10% target
A70: CPT Oricol — % Diversion (recycled+recovery) | B70: % | C70: — | D70: — | E70: — | F70: — | G70: — | H70: — | I70: — | J70: — | K70: — | L70: 91.1 | M70: >90% ✓
A71: Landfill tCO₂e (CPT Mar-26 estimate) | B71: tCO₂e | C71: — | D71: — | E71: — | F71: — | G71: — | H71: — | I71: — | J71: — | K71: — | L71: =L68*L69/100*E_Data!$B$10/1000 -> 1.1599014
A73: GHG EMISSIONS SUMMARY — SCOPE 1 + 2 + 3 (tCO₂e) [Auto-calculated from sections above]
A74: Scope / Category | B74: Unit | C74: Jul-25 | D74: Aug-25 | E74: Sep-25 | F74: Oct-25 | G74: Nov-25 | H74: Dec-25 | I74: Jan-26 | J74: Feb-26 | K74: Mar-26 | L74: YTD Total | M74: % of Total
A75: Scope 1A — Fleet Diesel | B75: tCO₂e | C75: =E_Data!C14+E_Data!C15+E_Data!C16+E_Data!C17+E_Data!C18 -> 79354.07 | D75: =E_Data!D14+E_Data!D15+E_Data!D16+E_Data!D17+E_Data!D18 -> 68178.89 | E75: =E_Data!E14+E_Data!E15+E_Data!E16+E_Data!E17+E_Data!E18 -> 65076.46 | F75: =E_Data!F14+E_Data!F15+E_Data!F16+E_Data!F17+E_Data!F18 -> 73386.91 | G75: =E_Data!G14+E_Data!G15+E_Data!G16+E_Data!G17+E_Data!G18 -> 67294.64 | H75: =E_Data!H14+E_Data!H15+E_Data!H16+E_Data!H17+E_Data!H18 -> 57589.35 | I75: =E_Data!I14+E_Data!I15+E_Data!I16+E_Data!I17+E_Data!I18 -> 48740.43 | J75: =E_Data!J14+E_Data!J15+E_Data!J16+E_Data!J17+E_Data!J18 -> 63979.73 | K75: =E_Data!K14+E_Data!K15+E_Data!K16+E_Data!K17+E_Data!K18 -> 65865.05 | L75: =SUM(C75:K75) -> 589465.53
A76: Scope 1B — Generator Diesel | B76: tCO₂e | C76: =E_Data!C23+E_Data!C24+E_Data!C25+E_Data!C26+E_Data!C27 -> 1289.14 | D76: =E_Data!D23+E_Data!D24+E_Data!D25+E_Data!D26+E_Data!D27 -> 0 | E76: =E_Data!E23+E_Data!E24+E_Data!E25+E_Data!E26+E_Data!E27 -> 0 | F76: =E_Data!F23+E_Data!F24+E_Data!F25+E_Data!F26+E_Data!F27 -> 0 | G76: =E_Data!G23+E_Data!G24+E_Data!G25+E_Data!G26+E_Data!G27 -> 0 | H76: =E_Data!H23+E_Data!H24+E_Data!H25+E_Data!H26+E_Data!H27 -> 295 | I76: =E_Data!I23+E_Data!I24+E_Data!I25+E_Data!I26+E_Data!I27 -> 0 | J76: =E_Data!J23+E_Data!J24+E_Data!J25+E_Data!J26+E_Data!J27 -> 0 | K76: =E_Data!K23+E_Data!K24+E_Data!K25+E_Data!K26+E_Data!K27 -> 597 | L76: =SUM(C76:K76) -> 2181.14
A77: Scope 1C — LPG Forklifts (DBN) | B77: tCO₂e | C77: =E_Data!C32 -> 0 | D77: =E_Data!D32 -> 570 | E77: =E_Data!E32 -> 190 | F77: =E_Data!F32 -> 190 | G77: =E_Data!G32 -> 380 | H77: =E_Data!H32 -> 570 | I77: =E_Data!I32 -> 380 | J77: =E_Data!J32 -> 0 | K77: =E_Data!K32 -> 0 | L77: =SUM(C77:K77) -> 2280
A78: Scope 1D — Business Cars | B78: tCO₂e | C78: =E_Data!C37 -> 139.81 | D78: =E_Data!D37 -> 142.25 | E78: =E_Data!E37 -> 93.22 | F78: =E_Data!F37 -> 109.49 | G78: =E_Data!G37 -> 143.81 | H78: =E_Data!H37 -> 74.68 | I78: =E_Data!I37 -> 109.59 | J78: =E_Data!J37 -> 98 | K78: =E_Data!K37 -> 142.97 | L78: =SUM(C78:K78) -> 1053.82
A79: SCOPE 1 TOTAL (tCO₂e) | C79: =SUM(C75,C76,C77,C78) -> 80783.02 | D79: =SUM(D75,D76,D77,D78) -> 68891.14 | E79: =SUM(E75,E76,E77,E78) -> 65359.68 | F79: =SUM(F75,F76,F77,F78) -> 73686.4 | G79: =SUM(G75,G76,G77,G78) -> 67818.45 | H79: =SUM(H75,H76,H77,H78) -> 58529.03 | I79: =SUM(I75,I76,I77,I78) -> 49230.02 | J79: =SUM(J75,J76,J77,J78) -> 64077.73 | ... L79: =SUM(L75,L76,L77,L78) -> 594980.49
A80: Scope 2 — Grid Electricity (location-based) | B80: tCO₂e | C80: =E_Data!C46 -> 288638.88 | D80: =E_Data!D46 -> 304665.02 | E80: =E_Data!E46 -> 294858.49 | F80: =E_Data!F46 -> 263387.94 | G80: =E_Data!G46 -> 255634.03 | H80: =E_Data!H46 -> 290165.23 | I80: =E_Data!I46 -> 261690.52 | J80: =E_Data!J46 -> 315712.51 | ... L80: =E_Data!L46 -> 2589578.4
A81: Scope 2 Solar Offset (negative — enter generation) | B81: tCO₂e | C81: =SUM(E_Data!C50+E_Data!C51+E_Data!C52+E_Data!C53+E_Data!C54) -> 0 | D81: =SUM(E_Data!D50+E_Data!D51+E_Data!D52+E_Data!D53+E_Data!D54) -> 0 | E81: =SUM(E_Data!E50+E_Data!E51+E_Data!E52+E_Data!E53+E_Data!E54) -> 0 | F81: =SUM(E_Data!F50+E_Data!F51+E_Data!F52+E_Data!F53+E_Data!F54) -> 0 | G81: =SUM(E_Data!G50+E_Data!G51+E_Data!G52+E_Data!G53+E_Data!G54) -> 0 | H81: =SUM(E_Data!H50+E_Data!H51+E_Data!H52+E_Data!H53+E_Data!H54) -> 0 | I81: =SUM(E_Data!I50+E_Data!I51+E_Data!I52+E_Data!I53+E_Data!I54) -> 0 | J81: =SUM(E_Data!J50+E_Data!J51+E_Data!J52+E_Data!J53+E_Data!J54) -> 0 | ... L81: =SUM(E_Data!L50+E_Data!L51+E_Data!L52+E_Data!L53+E_Data!L54) -> 0
A82: SCOPE 2 NET (tCO₂e) | C82: =C80+C81 -> 288638.88 | D82: =D80+D81 -> 304665.02 | E82: =E80+E81 -> 294858.49 | F82: =F80+F81 -> 263387.94 | G82: =G80+G81 -> 255634.03 | H82: =H80+H81 -> 290165.23 | I82: =I80+I81 -> 261690.52 | J82: =J80+J81 -> 315712.51 | ... L82: =L80+L81 -> 2589578.4
A83: Scope 3 — Water Consumption | B83: tCO₂e | C83: =E_Data!C63 -> 409.41 | D83: =E_Data!D63 -> 391.39 | E83: =E_Data!E63 -> 380.72 | F83: =E_Data!F63 -> 534.81 | G83: =E_Data!G63 -> 476.36 | H83: =E_Data!H63 -> 499.53 | I83: =E_Data!I63 -> 533.01 | J83: =E_Data!J63 -> 560.94 | ... L83: =E_Data!L63 -> 4356.41
A84: TOTAL GHG (Scope 1+2+3) tCO₂e | C84: =C79+C82+C83 -> 369831.31 | D84: =D79+D82+D83 -> 373947.55 | E84: =E79+E82+E83 -> 360598.89 | F84: =F79+F82+F83 -> 337609.15 | G84: =G79+G82+G83 -> 323928.84 | H84: =H79+H82+H83 -> 349193.79 | I84: =I79+I82+I83 -> 311453.55 | J84: =J79+J82+J83 -> 380351.18 | ... L84: =L79+L82+L83 -> 3188915.3
A85: % by scope — Scope 1 | B85: % | C85: =IFERROR(C79/C84,0) -> 0.21843207 | D85: =IFERROR(D79/D84,0) -> 0.18422675 | E85: =IFERROR(E79/E84,0) -> 0.18125314 | F85: =IFERROR(F79/F84,0) -> 0.21825949 | G85: =IFERROR(G79/G84,0) -> 0.20936219 | H85: =IFERROR(H79/H84,0) -> 0.16761189 | I85: =IFERROR(I79/I84,0) -> 0.15806537 | J85: =IFERROR(J79/J84,0) -> 0.16846991 | ... L85: =IFERROR(L79/L84,0) -> 0.1865777
A86: % by scope — Scope 2 (net) | B86: % | C86: =IFERROR(C82/C84,0) -> 0.78046091 | D86: =IFERROR(D82/D84,0) -> 0.81472661 | E86: =IFERROR(E82/E84,0) -> 0.81769106 | F86: =IFERROR(F82/F84,0) -> 0.7801564 | G86: =IFERROR(G82/G84,0) -> 0.78916724 | H86: =IFERROR(H82/H84,0) -> 0.83095759 | I86: =IFERROR(I82/I84,0) -> 0.84022327 | J86: =IFERROR(J82/J84,0) -> 0.83005529 | ... L86: =IFERROR(L82/L84,0) -> 0.81205619
A88: NET-ZERO TARGETS (SBTi CNZS 2.0) — Baseline: FY2025/26 | Target: −50% Scope 1+2 by 2030 | Net-Zero by 2050
A89: Target | B89: Baseline tCO₂e | C89: 2030 Target | D89: 2040 Target | E89: 2050 Target | F89: Current YTD | G89: On Track?
A90: Scope 1+2 Combined | B90: 0 | C90: =B90*0.5 -> 0 | D90: =B90*0.1 -> 0 | E90: Net-Zero | F90: =L79+L82 -> 3184558.9 | G90: =IF(B90=0,"Set baseline",IF(F90<=C90,"✓ On Track","⚠ Gap")) -> Set baseline

Sheet Fleet_Register
A1: FLEET REGISTER — Per-Vehicle CO₂ | L/100km | EV Mix | Service Status [Source: Updated Fleet List Feb 2026]
A3: Reg | B3: Depot | C3: Model/Category | D3: GVM (kg) | E3: Tare (kg) | F3: Carry (kg) | G3: Fuel Cap (L) | H3: Tracking | I3: Monthly km | J3: Monthly Litres | K3: L/100km Actual | L3: L/100km Norm | M3: Monthly tCO₂e | N3: Service Status | O3: Licence Expiry
A4: JR45DZGP | B4: SGTSPFMCG | C4: 11-Seater Bus | D4: 3445 | E4: 2395 | F4: 1050 | G4: 100 | H4: I-CAM | I4: 0 | J4: 0 | K4: =IFERROR(J4/I4*100,0) -> 0 | L4: 30 | M4: =J4*E_Data!$B$4/1000 -> 0 | N4: =IF(L4=0,"N/A",IF(K4=0,"No data",IF(K4<=L4*1.05,"✓ Good",IF(K4<=L4*1.15,"⚠ Alert","🔴 High")))) -> No data
A5: KY75THGP | B5: SGTSPFMCG | C5: HINO 1627 8T Fridge | D5: 16000 | E5: 8180 | F5: 7820 | G5: 390 | H5: I-CAM | I5: 0 | J5: 0 | K5: =IFERROR(J5/I5*100,0) -> 0 | L5: 26.5 | M5: =J5*E_Data!$B$4/1000 -> 0 | N5: =IF(L5=0,"N/A",IF(K5=0,"No data",IF(K5<=L5*1.05,"✓ Good",IF(K5<=L5*1.15,"⚠ Alert","🔴 High")))) -> No data
A6: KY82RLGP | B6: SGTBLOEM | C6: HINO 614 2.5T | D6: 5500 | E6: 3220 | F6: 2280 | G6: 100 | H6: I-CAM | I6: 0 | J6: 0 | K6: =IFERROR(J6/I6*100,0) -> 0 | L6: 18 | M6: =J6*E_Data!$B$4/1000 -> 0 | N6: =IF(L6=0,"N/A",IF(K6=0,"No data",IF(K6<=L6*1.05,"✓ Good",IF(K6<=L6*1.15,"⚠ Alert","🔴 High")))) -> No data
A7: KY98LTGP | B7: SGTSPFMCG | C7: HINO 816 4T Curtain | D7: 8000 | E7: 4180 | F7: 3820 | G7: 200 | H7: I-CAM | I7: 0 | J7: 0 | K7: =IFERROR(J7/I7*100,0) -> 0 | L7: 22 | M7: =J7*E_Data!$B$4/1000 -> 0 | N7: =IF(L7=0,"N/A",IF(K7=0,"No data",IF(K7<=L7*1.05,"✓ Good",IF(K7<=L7*1.15,"⚠ Alert","🔴 High")))) -> No data
A8: KY98MRGP | B8: SGTSPFMCG | C8: HINO 816 4T Curtain | D8: 8000 | E8: 4180 | F8: 3820 | G8: 200 | H8: I-CAM | I8: 0 | J8: 0 | K8: =IFERROR(J8/I8*100,0) -> 0 | L8: 22 | M8: =J8*E_Data!$B$4/1000 -> 0 | N8: =IF(L8=0,"N/A",IF(K8=0,"No data",IF(K8<=L8*1.05,"✓ Good",IF(K8<=L8*1.15,"⚠ Alert","🔴 High")))) -> No data
A9: KZ00LCGP | B9: SGTBLOEM | C9: HINO 500 1627 8T Fridge | D9: 16000 | E9: 8180 | F9: 7820 | G9: 390 | H9: I-CAM | I9: 0 | J9: 0 | K9: =IFERROR(J9/I9*100,0) -> 0 | L9: 26.5 | M9: =J9*E_Data!$B$4/1000 -> 0 | N9: =IF(L9=0,"N/A",IF(K9=0,"No data",IF(K9<=L9*1.05,"✓ Good",IF(K9<=L9*1.15,"⚠ Alert","🔴 High")))) -> No data
A10: KZ00LHGP | B10: SGTBLOEM | C10: HINO 500 1627 8T Fridge | D10: 16000 | E10: 8180 | F10: 7820 | G10: 390 | H10: I-CAM | I10: 0 | J10: 0 | K10: =IFERROR(J10/I10*100,0) -> 0 | L10: 26.5 | M10: =J10*E_Data!$B$4/1000 -> 0 | N10: =IF(L10=0,"N/A",IF(K10=0,"No data",IF(K10<=L10*1.05,"✓ Good",IF(K10<=L10*1.15,"⚠ Alert","🔴 High")))) -> No data
A11: KZ97BKGP | B11: SGTSPFMCG | C11: HINO 1627 8T Fridge | D11: 16000 | E11: 8180 | F11: 7820 | G11: 390 | H11: I-CAM | I11: 0 | J11: 0 | K11: =IFERROR(J11/I11*100,0) -> 0 | L11: 26.5 | M11: =J11*E_Data!$B$4/1000 -> 0 | N11: =IF(L11=0,"N/A",IF(K11=0,"No data",IF(K11<=L11*1.05,"✓ Good",IF(K11<=L11*1.15,"⚠ Alert","🔴 High")))) -> No data
A12: LB45BMGP | B12: SGTBLOEM | C12: HINO 1627 16T Fridge | D12: 25380 | E12: 9360 | F12: 16020 | G12: 390 | H12: I-CAM | I12: 0 | J12: 0 | K12: =IFERROR(J12/I12*100,0) -> 0 | L12: 26.5 | M12: =J12*E_Data!$B$4/1000 -> 0 | N12: =IF(L12=0,"N/A",IF(K12=0,"No data",IF(K12<=L12*1.05,"✓ Good",IF(K12<=L12*1.15,"⚠ Alert","🔴 High")))) -> No data
A13: LB45BXGP | B13: SGTBLOEM | C13: HINO 1627 16T Curtain | D13: 25380 | E13: 9360 | F13: 16020 | G13: 390 | H13: I-CAM | I13: 0 | J13: 0 | K13: =IFERROR(J13/I13*100,0) -> 0 | L13: 26.5 | M13: =J13*E_Data!$B$4/1000 -> 0 | N13: =IF(L13=0,"N/A",IF(K13=0,"No data",IF(K13<=L13*1.05,"✓ Good",IF(K13<=L13*1.15,"⚠ Alert","🔴 High")))) -> No data
A14: LC36DCGP | B14: SGTBLOEM | C14: HINO 500 1627 16T Fridge | D14: 25380 | E14: 9340 | F14: 16040 | G14: 390 | H14: I-CAM | I14: 0 | J14: 0 | K14: =IFERROR(J14/I14*100,0) -> 0 | L14: 26.5 | M14: =J14*E_Data!$B$4/1000 -> 0 | N14: =IF(L14=0,"N/A",IF(K14=0,"No data",IF(K14<=L14*1.05,"✓ Good",IF(K14<=L14*1.15,"⚠ Alert","🔴 High")))) -> No data
A15: MK66VTGP | B15: SGTSPFMCG | C15: HINO 700 32T | D15: 42000 | E15: 9060 | F15: 32940 | G15: 1000 | H15: I-CAM | I15: 0 | J15: 0 | K15: =IFERROR(J15/I15*100,0) -> 0 | L15: 55 | M15: =J15*E_Data!$B$4/1000 -> 0 | N15: =IF(L15=0,"N/A",IF(K15=0,"No data",IF(K15<=L15*1.05,"✓ Good",IF(K15<=L15*1.15,"⚠ Alert","🔴 High")))) -> No data
... A19: LC09YVGP | B19: SGTPE | C19: HINO 1627 16T Curtain | D19: 25380 | E19: 9320 | F19: 16060 | G19: 390 | H19: I-CAM | I19: 0 | J19: 0 | K19: =IFERROR(J19/I19*100,0) -> 0 | L19: 26.5 | M19: =J19*E_Data!$B$4/1000 -> 0 | N19: =IF(L19=0,"N/A",IF(K19=0,"No data",IF(K19<=L19*1.05,"✓ Good",IF(K19<=L19*1.15,"⚠ Alert","🔴 High")))) -> No data
A21: FLEET SUMMARY (from Fleet Summary Totals Per Type sheet)
A22: Depot | B22: Total Vehicles | C22: 32T Scania | D22: 16T | E22: 8T | F22: 4T | G22: Trailers | H22: EV Vehicles
A23: SGTBLOEM | B23: 16 | C23: 2 | D23: 7 | E23: 2 | F23: 0 | G23: 4 | H23: 0
A24: SGTCPT | B24: 14 | C24: 2 | D24: 2 | E24: 3 | F24: 3 | G24: 4 | H24: 0
A25: SGTDBN | B25: 19 | C25: 3 | D25: 8 | E25: 3 | F25: 0 | G25: 4 | H25: 0
A26: SGTPE | B26: 6 | C26: 0 | D26: 1 | E26: 3 | F26: 2 | G26: 0 | H26: 0
A27: SGTSPFMCG | B27: 79 | C27: 12 | D27: 7 | E27: 11 | F27: 8 | G27: 34 | H27: 0
A28: TOTAL | B28: 134 | C28: 19 | D28: 25 | E28: 22 | F28: 13 | G28: 46 | H28: 0
A30: EV FLEET TRANSITION PLAN | MAXUS eDeliver 3 (3.5T, range 330km) & eDeliver 5 (1T, range 320km) | Target: 20% EV mix by 2030 | EF_SOLAR offset applies to EV charging
A31: EV Model | B31: Range (km) | C31: Payload (kg) | D31: Charge kWh | E31: tCO₂e/km (grid) | F31: vs Diesel saving | G31: Recommended depot
A32: MAXUS eDeliver 3 | B32: 330 | C32: 900 | D32: 35 | E32: =E_Data!$B$7*35/330/1000 -> 8.6969697e-05 | F32: =IFERROR(D32*0.0001,0) -> 0.0035 | G32: CPT/PE short runs
A33: MAXUS eDeliver 5 | B33: 320 | C33: 1075 | D33: 42 | E33: =E_Data!$B$7*42/320/1000 -> 0.000107625 | F33: =IFERROR(D33*0.0001,0) -> 0.0042 | G33: BLOEM/JHB urban

Sheet ISO_14083
A1: 🚚 ISO 14083 / GLEC — TRANSPORT EMISSIONS | Per-trip · Intensity · Customer Allocation
A2: ISO 14083:2023 quantification methodology for transport chain GHG emissions. Calculates emissions at journey/leg level, enables intensity metrics (gCO₂e/t·km), and supports per-customer allocation for client-ready reporting. See Glossary for ISO 14083, GLEC, t·km, TKM, allocation methods.
A4: BLOCK 1 — TRIP REGISTER | Each row = one trip/journey | Pre-seeded with Apr-26 data from Driver_Debrief
A5: Trip ID | B5: Date | C5: Depot | D5: Vehicle Reg | E5: Route ID | F5: Mode | G5: Vehicle Class | H5: Fuel Type | I5: Distance (km) | J5: Load (tonnes) | K5: Tonne-km (t·km) | L5: Customer | M5: Allocation Basis | N5: Loaded? | O5: Fuel Used (L)
A6: T-26040001 | B6: 2026-04-01 | C6: SGTPE | D6: KZ00LRGP | E6: 010426EJ002 | F6: Road | G6: Light | H6: Diesel | I6: 2 | J6: 0.5 | K6: =IFERROR(I6*J6,0) -> 1 | L6: Engen Express | M6: Weight | N6: Yes
A7: T-26040002 | B7: 2026-04-01 | C7: SGTPE | D7: LC09YVGP | E7: 010426EJ005 | F7: Road | G7: Heavy | H7: Diesel | I7: 1 | J7: 8 | K7: =IFERROR(I7*J7,0) -> 8 | L7: Engen Express | M7: Weight | N7: Yes
A8: T-26040003 | B8: 2026-04-01 | C8: SGTPE | D8: KZ00LRGP | E8: 010426EL001 | F8: Road | G8: Light | H8: Diesel | I8: 37 | J8: 1.2 | K8: =IFERROR(I8*J8,0) -> 44.4 | L8: Engen Logistics | M8: Weight | N8: Yes
A9: T-26040004 | B9: 2026-04-01 | C9: SGTPE | D9: LC22HRGP | E9: 010426EL003 | F9: Road | G9: Medium | H9: Diesel | I9: 55 | J9: 3.8 | K9: =IFERROR(I9*J9,0) -> 209 | L9: Engen Logistics | M9: Weight | N9: Yes
A10: T-26040005 | B10: 2026-04-01 | C10: SGTBLOEM | D10: LB45BMGP | E10: 010426FC001 | F10: Road | G10: Heavy | H10: Diesel | I10: 449 | J10: 16 | K10: =IFERROR(I10*J10,0) -> 7184 | L10: Famous Brands | M10: Weight | N10: Yes
A11: T-26040006 | B11: 2026-04-01 | C11: SGTBLOEM | D11: LB45BMGP | E11: 010426FL001 | F11: Road | G11: Heavy | H11: Diesel | I11: 28 | J11: 12.5 | K11: =IFERROR(I11*J11,0) -> 350 | L11: Famous Brands | M11: Weight | N11: Yes
A12: T-26040007 | B12: 2026-04-01 | C12: SGTSPFMCG | D12: KZ97BKGP | E12: 010426GC001 | F12: Road | G12: Heavy | H12: Diesel | I12: 972 | J12: 8 | K12: =IFERROR(I12*J12,0) -> 7776 | L12: Shared (3 customers) | M12: Weight | N12: Yes
K13: =IFERROR(I13*J13,0) -> 0
K14: =IFERROR(I14*J14,0) -> 0
K15: =IFERROR(I15*J15,0) -> 0
K16: =IFERROR(I16*J16,0) -> 0
K17: =IFERROR(I17*J17,0) -> 0
K18: =IFERROR(I18*J18,0) -> 0
K19: =IFERROR(I19*J19,0) -> 0
K20: =IFERROR(I20*J20,0) -> 0
K21: =IFERROR(I21*J21,0) -> 0
K22: =IFERROR(I22*J22,0) -> 0
K23: =IFERROR(I23*J23,0) -> 0
K24: =IFERROR(I24*J24,0) -> 0
K25: =IFERROR(I25*J25,0) -> 0
A26: TOTAL | I26: =SUM(I6:I25) -> 1544 | J26: =SUM(J6:J25) -> 50 | K26: =SUM(K6:K25) -> 15572.4 | O26: =SUM(O6:O25) -> 0
A28: BLOCK 2 — PER-TRIP EMISSIONS | Fuel-based (preferred) or distance-based fallback per ISO 14083 §7
A29: Trip ID | B29: Method | C29: Fuel kgCO₂e | D29: Dist kgCO₂e | E29: Trip tCO₂e | F29: gCO₂e/km | G29: gCO₂e/t·km | H29: Customer | I29: Customer tCO₂e | J29: Empty trip? | K29: Intensity vs avg
A30: =IF(A6="","",A6) -> T-26040001 | B30: =IF(A6="","",IF(O6>0,"Fuel-based","Distance-based")) -> Distance-based | C30: =IFERROR(IF(O6>0,IF(H6="Diesel",O6*Assumptions!$B$30,IF(H6="Petrol",O6*Assumptions!$B$31,IF(H6="LPG",O6*Assumptions!$B$32,IF(H6="Electric",I6*0.35*Assumptions!$B$33,O6*Assumptions!$B$30)))),""),"") | D30: =IFERROR(I6*IF(G6="Light",18,IF(G6="Medium",22,IF(G6="Heavy",26.5,IF(G6="Articulated",35,22))))/100*Assumptions!$B$30,0) -> 0.9648 | E30: =IFERROR(IF(A6="","",IF(O6>0,C30,D30)/1000),0) -> 0.0009648 | F30: =IFERROR(E30*1000000/I6,0) -> 482.4 | G30: =IFERROR(E30*1000000/K6,0) -> 964.8 | H30: =IF(L6="","",L6) -> Engen Express | I30: =IFERROR(IF(L6="","",IF(ISNUMBER(SEARCH("Shared",L6)),E30/3,E30)),"") -> 0.0009648 | J30: =IF(A6="","",IF(N6="No","⚠ Backhaul","")) | K30: =IF(A6="","",IF(G30<=80,"✓ Best",IF(G30<=150,"○ Good",IF(G30<=300,"⚠ Avg","✗ High")))) -> ✗ High
A31: =IF(A7="","",A7) -> T-26040002 | B31: =IF(A7="","",IF(O7>0,"Fuel-based","Distance-based")) -> Distance-based | C31: =IFERROR(IF(O7>0,IF(H7="Diesel",O7*Assumptions!$B$30,IF(H7="Petrol",O7*Assumptions!$B$31,IF(H7="LPG",O7*Assumptions!$B$32,IF(H7="Electric",I7*0.35*Assumptions!$B$33,O7*Assumptions!$B$30)))),""),"") | D31: =IFERROR(I7*IF(G7="Light",18,IF(G7="Medium",22,IF(G7="Heavy",26.5,IF(G7="Articulated",35,22))))/100*Assumptions!$B$30,0) -> 0.7102 | E31: =IFERROR(IF(A7="","",IF(O7>0,C31,D31)/1000),0) -> 0.0007102 | F31: =IFERROR(E31*1000000/I7,0) -> 710.2 | G31: =IFERROR(E31*1000000/K7,0) -> 88.775 | H31: =IF(L7="","",L7) -> Engen Express | I31: =IFERROR(IF(L7="","",IF(ISNUMBER(SEARCH("Shared",L7)),E31/3,E31)),"") -> 0.0007102 | J31: =IF(A7="","",IF(N7="No","⚠ Backhaul","")) | K31: =IF(A7="","",IF(G31<=80,"✓ Best",IF(G31<=150,"○ Good",IF(G31<=300,"⚠ Avg","✗ High")))) -> ○ Good
A32: =IF(A8="","",A8) -> T-26040003 | B32: =IF(A8="","",IF(O8>0,"Fuel-based","Distance-based")) -> Distance-based | C32: =IFERROR(IF(O8>0,IF(H8="Diesel",O8*Assumptions!$B$30,IF(H8="Petrol",O8*Assumptions!$B$31,IF(H8="LPG",O8*Assumptions!$B$32,IF(H8="Electric",I8*0.35*Assumptions!$B$33,O8*Assumptions!$B$30)))),""),"") | D32: =IFERROR(I8*IF(G8="Light",18,IF(G8="Medium",22,IF(G8="Heavy",26.5,IF(G8="Articulated",35,22))))/100*Assumptions!$B$30,0) -> 17.8488 | E32: =IFERROR(IF(A8="","",IF(O8>0,C32,D32)/1000),0) -> 0.0178488 | F32: =IFERROR(E32*1000000/I8,0) -> 482.4 | G32: =IFERROR(E32*1000000/K8,0) -> 402 | H32: =IF(L8="","",L8) -> Engen Logistics | I32: =IFERROR(IF(L8="","",IF(ISNUMBER(SEARCH("Shared",L8)),E32/3,E32)),"") -> 0.0178488 | J32: =IF(A8="","",IF(N8="No","⚠ Backhaul","")) | K32: =IF(A8="","",IF(G32<=80,"✓ Best",IF(G32<=150,"○ Good",IF(G32<=300,"⚠ Avg","✗ High")))) -> ✗ High
A33: =IF(A9="","",A9) -> T-26040004 | B33: =IF(A9="","",IF(O9>0,"Fuel-based","Distance-based")) -> Distance-based | C33: =IFERROR(IF(O9>0,IF(H9="Diesel",O9*Assumptions!$B$30,IF(H9="Petrol",O9*Assumptions!$B$31,IF(H9="LPG",O9*Assumptions!$B$32,IF(H9="Electric",I9*0.35*Assumptions!$B$33,O9*Assumptions!$B$30)))),""),"") | D33: =IFERROR(I9*IF(G9="Light",18,IF(G9="Medium",22,IF(G9="Heavy",26.5,IF(G9="Articulated",35,22))))/100*Assumptions!$B$30,0) -> 32.428 | E33: =IFERROR(IF(A9="","",IF(O9>0,C33,D33)/1000),0) -> 0.032428 | F33: =IFERROR(E33*1000000/I9,0) -> 589.6 | G33: =IFERROR(E33*1000000/K9,0) -> 155.15789 | H33: =IF(L9="","",L9) -> Engen Logistics | I33: =IFERROR(IF(L9="","",IF(ISNUMBER(SEARCH("Shared",L9)),E33/3,E33)),"") -> 0.032428 | J33: =IF(A9="","",IF(N9="No","⚠ Backhaul","")) | K33: =IF(A9="","",IF(G33<=80,"✓ Best",IF(G33<=150,"○ Good",IF(G33<=300,"⚠ Avg","✗ High")))) -> ⚠ Avg
A34: =IF(A10="","",A10) -> T-26040005 | B34: =IF(A10="","",IF(O10>0,"Fuel-based","Distance-based")) -> Distance-based | C34: =IFERROR(IF(O10>0,IF(H10="Diesel",O10*Assumptions!$B$30,IF(H10="Petrol",O10*Assumptions!$B$31,IF(H10="LPG",O10*Assumptions!$B$32,IF(H10="Electric",I10*0.35*Assumptions!$B$33,O10*Assumptions!$B$30)))),""),"") | D34: =IFERROR(I10*IF(G10="Light",18,IF(G10="Medium",22,IF(G10="Heavy",26.5,IF(G10="Articulated",35,22))))/100*Assumptions!$B$30,0) -> 318.8798 | E34: =IFERROR(IF(A10="","",IF(O10>0,C34,D34)/1000),0) -> 0.3188798 | F34: =IFERROR(E34*1000000/I10,0) -> 710.2 | G34: =IFERROR(E34*1000000/K10,0) -> 44.3875 | H34: =IF(L10="","",L10) -> Famous Brands | I34: =IFERROR(IF(L10="","",IF(ISNUMBER(SEARCH("Shared",L10)),E34/3,E34)),"") -> 0.3188798 | J34: =IF(A10="","",IF(N10="No","⚠ Backhaul","")) | K34: =IF(A10="","",IF(G34<=80,"✓ Best",IF(G34<=150,"○ Good",IF(G34<=300,"⚠ Avg","✗ High")))) -> ✓ Best
A35: =IF(A11="","",A11) -> T-26040006 | B35: =IF(A11="","",IF(O11>0,"Fuel-based","Distance-based")) -> Distance-based | C35: =IFERROR(IF(O11>0,IF(H11="Diesel",O11*Assumptions!$B$30,IF(H11="Petrol",O11*Assumptions!$B$31,IF(H11="LPG",O11*Assumptions!$B$32,IF(H11="Electric",I11*0.35*Assumptions!$B$33,O11*Assumptions!$B$30)))),""),"") | D35: =IFERROR(I11*IF(G11="Light",18,IF(G11="Medium",22,IF(G11="Heavy",26.5,IF(G11="Articulated",35,22))))/100*Assumptions!$B$30,0) -> 19.8856 | E35: =IFERROR(IF(A11="","",IF(O11>0,C35,D35)/1000),0) -> 0.0198856 | F35: =IFERROR(E35*1000000/I11,0) -> 710.2 | G35: =IFERROR(E35*1000000/K11,0) -> 56.816 | H35: =IF(L11="","",L11) -> Famous Brands | I35: =IFERROR(IF(L11="","",IF(ISNUMBER(SEARCH("Shared",L11)),E35/3,E35)),"") -> 0.0198856 | J35: =IF(A11="","",IF(N11="No","⚠ Backhaul","")) | K35: =IF(A11="","",IF(G35<=80,"✓ Best",IF(G35<=150,"○ Good",IF(G35<=300,"⚠ Avg","✗ High")))) -> ✓ Best
A36: =IF(A12="","",A12) -> T-26040007 | B36: =IF(A12="","",IF(O12>0,"Fuel-based","Distance-based")) -> Distance-based | C36: =IFERROR(IF(O12>0,IF(H12="Diesel",O12*Assumptions!$B$30,IF(H12="Petrol",O12*Assumptions!$B$31,IF(H12="LPG",O12*Assumptions!$B$32,IF(H12="Electric",I12*0.35*Assumptions!$B$33,O12*Assumptions!$B$30)))),""),"") | D36: =IFERROR(I12*IF(G12="Light",18,IF(G12="Medium",22,IF(G12="Heavy",26.5,IF(G12="Articulated",35,22))))/100*Assumptions!$B$30,0) -> 690.3144 | E36: =IFERROR(IF(A12="","",IF(O12>0,C36,D36)/1000),0) -> 0.6903144 | F36: =IFERROR(E36*1000000/I12,0) -> 710.2 | G36: =IFERROR(E36*1000000/K12,0) -> 88.775 | H36: =IF(L12="","",L12) -> Shared (3 customers) | I36: =IFERROR(IF(L12="","",IF(ISNUMBER(SEARCH("Shared",L12)),E36/3,E36)),"") -> 0.2301048 | J36: =IF(A12="","",IF(N12="No","⚠ Backhaul","")) | K36: =IF(A12="","",IF(G36<=80,"✓ Best",IF(G36<=150,"○ Good",IF(G36<=300,"⚠ Avg","✗ High")))) -> ○ Good
A37: =IF(A13="","",A13) | B37: =IF(A13="","",IF(O13>0,"Fuel-based","Distance-based")) | C37: =IFERROR(IF(O13>0,IF(H13="Diesel",O13*Assumptions!$B$30,IF(H13="Petrol",O13*Assumptions!$B$31,IF(H13="LPG",O13*Assumptions!$B$32,IF(H13="Electric",I13*0.35*Assumptions!$B$33,O13*Assumptions!$B$30)))),""),"") | D37: =IFERROR(I13*IF(G13="Light",18,IF(G13="Medium",22,IF(G13="Heavy",26.5,IF(G13="Articulated",35,22))))/100*Assumptions!$B$30,0) -> 0 | E37: =IFERROR(IF(A13="","",IF(O13>0,C37,D37)/1000),0) | F37: =IFERROR(E37*1000000/I13,0) -> 0 | G37: =IFERROR(E37*1000000/K13,0) -> 0 | H37: =IF(L13="","",L13) | I37: =IFERROR(IF(L13="","",IF(ISNUMBER(SEARCH("Shared",L13)),E37/3,E37)),"") | J37: =IF(A13="","",IF(N13="No","⚠ Backhaul","")) | K37: =IF(A13="","",IF(G37<=80,"✓ Best",IF(G37<=150,"○ Good",IF(G37<=300,"⚠ Avg","✗ High"))))
A38: =IF(A14="","",A14) | B38: =IF(A14="","",IF(O14>0,"Fuel-based","Distance-based")) | C38: =IFERROR(IF(O14>0,IF(H14="Diesel",O14*Assumptions!$B$30,IF(H14="Petrol",O14*Assumptions!$B$31,IF(H14="LPG",O14*Assumptions!$B$32,IF(H14="Electric",I14*0.35*Assumptions!$B$33,O14*Assumptions!$B$30)))),""),"") | D38: =IFERROR(I14*IF(G14="Light",18,IF(G14="Medium",22,IF(G14="Heavy",26.5,IF(G14="Articulated",35,22))))/100*Assumptions!$B$30,0) -> 0 | E38: =IFERROR(IF(A14="","",IF(O14>0,C38,D38)/1000),0) | F38: =IFERROR(E38*1000000/I14,0) -> 0 | G38: =IFERROR(E38*1000000/K14,0) -> 0 | H38: =IF(L14="","",L14) | I38: =IFERROR(IF(L14="","",IF(ISNUMBER(SEARCH("Shared",L14)),E38/3,E38)),"") | J38: =IF(A14="","",IF(N14="No","⚠ Backhaul","")) | K38: =IF(A14="","",IF(G38<=80,"✓ Best",IF(G38<=150,"○ Good",IF(G38<=300,"⚠ Avg","✗ High"))))
A39: =IF(A15="","",A15) | B39: =IF(A15="","",IF(O15>0,"Fuel-based","Distance-based")) | C39: =IFERROR(IF(O15>0,IF(H15="Diesel",O15*Assumptions!$B$30,IF(H15="Petrol",O15*Assumptions!$B$31,IF(H15="LPG",O15*Assumptions!$B$32,IF(H15="Electric",I15*0.35*Assumptions!$B$33,O15*Assumptions!$B$30)))),""),"") | D39: =IFERROR(I15*IF(G15="Light",18,IF(G15="Medium",22,IF(G15="Heavy",26.5,IF(G15="Articulated",35,22))))/100*Assumptions!$B$30,0) -> 0 | E39: =IFERROR(IF(A15="","",IF(O15>0,C39,D39)/1000),0) | F39: =IFERROR(E39*1000000/I15,0) -> 0 | G39: =IFERROR(E39*1000000/K15,0) -> 0 | H39: =IF(L15="","",L15) | I39: =IFERROR(IF(L15="","",IF(ISNUMBER(SEARCH("Shared",L15)),E39/3,E39)),"") | J39: =IF(A15="","",IF(N15="No","⚠ Backhaul","")) | K39: =IF(A15="","",IF(G39<=80,"✓ Best",IF(G39<=150,"○ Good",IF(G39<=300,"⚠ Avg","✗ High"))))
A40: =IF(A16="","",A16) | B40: =IF(A16="","",IF(O16>0,"Fuel-based","Distance-based")) | C40: =IFERROR(IF(O16>0,IF(H16="Diesel",O16*Assumptions!$B$30,IF(H16="Petrol",O16*Assumptions!$B$31,IF(H16="LPG",O16*Assumptions!$B$32,IF(H16="Electric",I16*0.35*Assumptions!$B$33,O16*Assumptions!$B$30)))),""),"") | D40: =IFERROR(I16*IF(G16="Light",18,IF(G16="Medium",22,IF(G16="Heavy",26.5,IF(G16="Articulated",35,22))))/100*Assumptions!$B$30,0) -> 0 | E40: =IFERROR(IF(A16="","",IF(O16>0,C40,D40)/1000),0) | F40: =IFERROR(E40*1000000/I16,0) -> 0 | G40: =IFERROR(E40*1000000/K16,0) -> 0 | H40: =IF(L16="","",L16) | I40: =IFERROR(IF(L16="","",IF(ISNUMBER(SEARCH("Shared",L16)),E40/3,E40)),"") | J40: =IF(A16="","",IF(N16="No","⚠ Backhaul","")) | K40: =IF(A16="","",IF(G40<=80,"✓ Best",IF(G40<=150,"○ Good",IF(G40<=300,"⚠ Avg","✗ High"))))
A41: =IF(A17="","",A17) | B41: =IF(A17="","",IF(O17>0,"Fuel-based","Distance-based")) | C41: =IFERROR(IF(O17>0,IF(H17="Diesel",O17*Assumptions!$B$30,IF(H17="Petrol",O17*Assumptions!$B$31,IF(H17="LPG",O17*Assumptions!$B$32,IF(H17="Electric",I17*0.35*Assumptions!$B$33,O17*Assumptions!$B$30)))),""),"") | D41: =IFERROR(I17*IF(G17="Light",18,IF(G17="Medium",22,IF(G17="Heavy",26.5,IF(G17="Articulated",35,22))))/100*Assumptions!$B$30,0) -> 0 | E41: =IFERROR(IF(A17="","",IF(O17>0,C41,D41)/1000),0) | F41: =IFERROR(E41*1000000/I17,0) -> 0 | G41: =IFERROR(E41*1000000/K17,0) -> 0 | H41: =IF(L17="","",L17) | I41: =IFERROR(IF(L17="","",IF(ISNUMBER(SEARCH("Shared",L17)),E41/3,E41)),"") | J41: =IF(A17="","",IF(N17="No","⚠ Backhaul","")) | K41: =IF(A17="","",IF(G41<=80,"✓ Best",IF(G41<=150,"○ Good",IF(G41<=300,"⚠ Avg","✗ High"))))
... A49: =IF(A25="","",A25) | B49: =IF(A25="","",IF(O25>0,"Fuel-based","Distance-based")) | C49: =IFERROR(IF(O25>0,IF(H25="Diesel",O25*Assumptions!$B$30,IF(H25="Petrol",O25*Assumptions!$B$31,IF(H25="LPG",O25*Assumptions!$B$32,IF(H25="Electric",I25*0.35*Assumptions!$B$33,O25*Assumptions!$B$30)))),""),"") | D49: =IFERROR(I25*IF(G25="Light",18,IF(G25="Medium",22,IF(G25="Heavy",26.5,IF(G25="Articulated",35,22))))/100*Assumptions!$B$30,0) -> 0 | E49: =IFERROR(IF(A25="","",IF(O25>0,C49,D49)/1000),0) | F49: =IFERROR(E49*1000000/I25,0) -> 0 | G49: =IFERROR(E49*1000000/K25,0) -> 0 | H49: =IF(L25="","",L25) | I49: =IFERROR(IF(L25="","",IF(ISNUMBER(SEARCH("Shared",L25)),E49/3,E49)),"") | J49: =IF(A25="","",IF(N25="No","⚠ Backhaul","")) | K49: =IF(A25="","",IF(G49<=80,"✓ Best",IF(G49<=150,"○ Good",IF(G49<=300,"⚠ Avg","✗ High"))))
A50: TOTAL | E50: =SUM(E30:E49) -> 1.0810316 | G50: =IFERROR(AVERAGEIF(G30:G49,">0"),0) -> 257.24448 | I50: =SUM(I30:I49) -> 0.620822
A52: BLOCK 3 — INTENSITY METRICS | Performance benchmarks aligned to GLEC framework
A53: Metric | B53: Value | C53: Unit | D53: Benchmark | E53: vs Benchmark | F53: Source / Note
A54: Total trips logged | B54: =COUNTIF(A6:A25,"T-*") -> 7 | C54: count | D54: n/a
A55: Total distance (km) | B55: =SUM(I6:I25) -> 1544 | C55: km | D55: n/a
A56: Total load (tonnes) | B56: =SUM(J6:J25) -> 50 | C56: t | D56: n/a
A57: Total tonne-km (t·km) | B57: =SUM(K6:K25) -> 15572.4 | C57: t·km | D57: n/a | F57: Distance × Load — ISO 14083 §6.2 activity unit
A58: Total emissions (tCO₂e) | B58: =SUM(E30:E49) -> 1.0810316 | C58: tCO₂e | D58: n/a
A59: Avg intensity (gCO₂e/t·km) | B59: =IFERROR(SUM(E30:E49)*1000000/SUM(K6:K25),0) -> 69.419717 | C59: gCO₂e/t·km | D59: 80 | E59: =IF(B59<=D59,"✓ Met",IF(B59<=D59*1.5,"⚠ Partial","✗ Gap")) -> ✓ Met | F59: GLEC heavy road freight benchmark: ~80 g/t·km
A60: Avg intensity (gCO₂e/km) | B60: =IFERROR(SUM(E30:E49)*1000000/SUM(I6:I25),0) -> 700.15 | C60: gCO₂e/km | D60: 900 | E60: =IF(B60<=D60,"✓ Met",IF(B60<=D60*1.5,"⚠ Partial","✗ Gap")) -> ✓ Met | F60: DEFRA heavy HGV diesel: ~1,095 g/km
A61: Avg emissions per trip (tCO₂e) | B61: =IFERROR(SUM(E30:E49)/COUNTIF(A6:A25,"T-*"),0) -> 0.15443309 | C61: tCO₂e/trip | D61: —
A62: Empty/backhaul ratio | B62: =IFERROR(COUNTIF(N6:N25,"No")/COUNTIF(A6:A25,"T-*"),0) -> 0 | C62: % | D62: 0.15 | E62: =IF(B62<=D62,"✓ Met",IF(B62<=D62*1.5,"⚠ Partial","✗ Gap")) -> ✓ Met | F62: Target ≤15% for fleet efficiency
A63: Loaded ratio | B63: =IFERROR(COUNTIF(N6:N25,"Yes")/COUNTIF(A6:A25,"T-*"),0) -> 1 | C63: % | D63: 0.85 | E63: =IF(B63>=D63,"✓ Met",IF(B63>=D63*0.7,"⚠ Partial","✗ Gap")) -> ✓ Met | F63: Target ≥85%
A65: BLOCK 4 — CUSTOMER EMISSIONS | Client-ready reporting — allocation per ISO 14083 §8
A66: Customer | B66: Trips | C66: Distance (km) | D66: Load (t·km) | E66: Emissions (tCO₂e) | F66: Intensity (g/t·km) | G66: % of Total | H66: Report Status
A67: Engen Express | B67: =COUNTIF(L$6:L$25,"Engen Express") -> 2 | C67: =SUMIF(L$6:L$25,"Engen Express",I$6:I$25) -> 3 | D67: =SUMIF(L$6:L$25,"Engen Express",K$6:K$25) -> 9 | E67: =SUMIF(H$30:H$49,"Engen Express",I$30:I$49) -> 0.001675 | F67: =IFERROR(E67*1000000/D67,0) -> 186.11111 | G67: =IFERROR(E67/SUM(E$67:E$70),0) -> 0.0026980358 | H67: =IF(AND(B67>0,E67>0),"📋 Client-ready","○ No data") -> 📋 Client-ready
A68: Engen Logistics | B68: =COUNTIF(L$6:L$25,"Engen Logistics") -> 2 | C68: =SUMIF(L$6:L$25,"Engen Logistics",I$6:I$25) -> 92 | D68: =SUMIF(L$6:L$25,"Engen Logistics",K$6:K$25) -> 253.4 | E68: =SUMIF(H$30:H$49,"Engen Logistics",I$30:I$49) -> 0.0502768 | F68: =IFERROR(E68*1000000/D68,0) -> 198.40884 | G68: =IFERROR(E68/SUM(E$67:E$70),0) -> 0.080984243 | H68: =IF(AND(B68>0,E68>0),"📋 Client-ready","○ No data") -> 📋 Client-ready
A69: Famous Brands | B69: =COUNTIF(L$6:L$25,"Famous Brands") -> 2 | C69: =SUMIF(L$6:L$25,"Famous Brands",I$6:I$25) -> 477 | D69: =SUMIF(L$6:L$25,"Famous Brands",K$6:K$25) -> 7534 | E69: =SUMIF(H$30:H$49,"Famous Brands",I$30:I$49) -> 0.3387654 | F69: =IFERROR(E69*1000000/D69,0) -> 44.964879 | G69: =IFERROR(E69/SUM(E$67:E$70),0) -> 0.54567235 | H69: =IF(AND(B69>0,E69>0),"📋 Client-ready","○ No data") -> 📋 Client-ready
A70: Shared (3 customers) | B70: =COUNTIF(L$6:L$25,"Shared (3 customers)") -> 1 | C70: =SUMIF(L$6:L$25,"Shared (3 customers)",I$6:I$25) -> 972 | D70: =SUMIF(L$6:L$25,"Shared (3 customers)",K$6:K$25) -> 7776 | E70: =SUMIF(H$30:H$49,"Shared (3 customers)",I$30:I$49) -> 0.2301048 | F70: =IFERROR(E70*1000000/D70,0) -> 29.591667 | G70: =IFERROR(E70/SUM(E$67:E$70),0) -> 0.37064537 | H70: =IF(AND(B70>0,E70>0),"📋 Client-ready","○ No data") -> 📋 Client-ready
A71: TOTAL — CUSTOMER ALLOCATED | B71: =SUM(B67:B70) -> 7 | C71: =SUM(C67:C70) -> 1544 | D71: =SUM(D67:D70) -> 15572.4 | E71: =SUM(E67:E70) -> 0.620822 | F71: =IFERROR(E71*1000000/D71,0) -> 39.866816 | G71: =SUM(G67:G70) -> 1
A73: BLOCK 5 — OPERATIONAL SUMMARY | Fleet performance + route efficiency | ISO 14083 §9 reporting
A74: Avg distance per trip | B74: =IFERROR(SUM(I6:I25)/COUNTIF(A6:A25,"T-*"),0) -> 220.57143 | C74: km
A75: Avg load per trip | B75: =IFERROR(SUM(J6:J25)/COUNTIF(A6:A25,"T-*"),0) -> 7.1428571 | C75: t
A76: Avg t·km per trip | B76: =IFERROR(SUM(K6:K25)/COUNTIF(A6:A25,"T-*"),0) -> 2224.6286 | C76: t·km
A77: Longest single trip | B77: =MAX(I6:I25) -> 972 | C77: km
A78: Shortest single trip | B78: =IFERROR(minifs(I6:I25,I6:I25,">0"),0) -> 0 | C78: km
A79: Trips with fuel data | B79: =COUNTIF(O6:O25,">0") -> 0 | C79: count
A80: Trips on default factors | B80: =COUNTIF(A6:A25,"T-*")-COUNTIF(O6:O25,">0") -> 7 | C80: count
A81: Fuel-based emissions % | B81: =IFERROR(COUNTIF(O6:O25,">0")/COUNTIF(A6:A25,"T-*"),0) -> 0 | C81: %

Sheet Waste_Register
A1: WASTE REGISTER — Oricol Environmental | Oracle | Valour Brands | Cority [GRI 306 | ISO 14001 | Net-Zero]
A3: WASTE STREAMS — Monthly data entry [Source: Waste contractors + Cority cardboard data]
A4: Month | B4: Depot | C4: Waste Type | D4: Total kg | E4: Recycled kg | F4: Landfill kg | G4: Diverted % | H4: Landfill tCO₂e | I4: Contractor | J4: Invoice Ref
A5: Mar-26 | B5: CPT | C5: Commercial/Industrial (landfill) | D5: 2000 | E5: 0 | F5: 2000 | G5: =IFERROR(E5/D5,0) -> 0 | H5: =F5*0.58/1000 -> 1.16 | I5: Oricol Environmental | J5: Mar-26 actual
A6: Mar-26 | B6: CPT | C6: Commercial/Industrial (recycled) | D6: 6580 | E6: 6580 | F6: 0 | G6: =IFERROR(E6/D6,0) -> 1 | H6: =F6*0.58/1000 -> 0 | I6: Oricol Environmental | J6: Mar-26 actual
A7: Mar-26 | B7: CPT | C7: Paper/Cardboard K4 | D7: 1100 | E7: 1100 | F7: 0 | G7: =IFERROR(E7/D7,0) -> 1 | H7: =F7*0.58/1000 -> 0 | I7: Oricol Environmental | J7: Mar-26 actual
A8: Mar-26 | B8: CPT | C8: LDPE Shrinkwrap | D8: 880 | E8: 880 | F8: 0 | G8: =IFERROR(E8/D8,0) -> 1 | H8: =F8*0.58/1000 -> 0 | I8: Oricol Environmental | J8: Mar-26 actual
A9: Mar-26 | B9: ALL | C9: TOTAL (Oricol Big Numbers) | D9: 22470 | E9: 20470 | F9: 2000 | G9: 91.1% | H9: =F9*0.58/1000 -> 1.16 | I9: Oricol Environmental | J9: Oricol Big Numbers
A11: CORITY CARDBOARD RECYCLING % — Monthly (from Mariette Dashboard waste sheet)
A12: Month | B12: Jul-25 | C12: Aug-25 | D12: Sep-25 | E12: Oct-25 | F12: Nov-25 | G12: Dec-25 | H12: Jan-26 | I12: Feb-26 | J12: Mar-26
A13: % Recycled (all depots) | B13: 0.1065 | C13: 0.1624 | D13: 0.1106 | E13: 0.0889 | F13: 0.2642 | G13: 0.1068 | H13: 0.046 | I13: 0.1373 | J13: 0.0956
A15: WASTE SCORECARD — vs ISO 14001 + Net-Zero targets
A16: Oricol CPT diversion rate (Mar-26) | B16: =91.1% -> 0.911 | C16: ≥90% | D16: ✓ Met | E16: 5
A17: Average monthly % recycled (Cority) | B17: =AVERAGE(B13:J13) -> 0.12425556 | C17: ≥25% | E17: 4
A18: Total landfill tCO₂e YTD | B18: =SUMIF(F4:F40,">0",F4:F40)*0.58/1000 -> 2.3201532 | C18: Minimise | E18: 3
A19: Waste contractor sustainability rating | B19: IMS-T-149 Oricol score | C19: ≥80% | E19: 3
A20: ISO 14001 waste aspect managed | C20: Yes | E20: 3

Sheet Driver_Debrief
A1: DRIVER DEBRIEF — Route Completion | Customer Hit % | Planned vs Actual km | Net-Zero km Efficiency [Source: DriverDebriefSummary.xlsx]
A3: Date | B3: Depot | C3: Driver Name | D3: Vehicle Reg | E3: Route | F3: Cust Hit% | G3: Plan Stops | H3: Act Stops | I3: Variance | J3: Plan km | K3: Act km | L3: km Excess | M3: Net-Zero Note / Action
A4: 2026-04-01 | B4: SGTPE | C4: Hubrey Malgas | D4: KZ00LRGP | E4: 010426EJ002 | F4: 1 | G4: 1 | H4: 1 | I4: 0 | J4: 2 | K4: 2 | L4: =K4-J4 -> 0 | M4: ✓ On route
A5: 2026-04-01 | B5: SGTPE | C5: NO DATA | D5: LC09YVGP | E5: 010426EJ005 | F5: 1 | G5: 1 | H5: 1 | I5: 0 | J5: 1 | K5: 1 | L5: =K5-J5 -> 0 | M5: ✓ On route
A6: 2026-04-01 | B6: SGTPE | C6: Hubrey Malgas | D6: KZ00LRGP | E6: 010426EL001 | F6: 1 | G6: 3 | H6: 3 | I6: 0 | J6: 37 | K6: 37 | L6: =K6-J6 -> 0 | M6: ✓ On route
A7: 2026-04-01 | B7: SGTPE | C7: James Jantjies | D7: LC22HRGP | E7: 010426EL003 | F7: 0.85 | G7: 7 | H7: 6 | I7: 1 | J7: 55 | K7: 55 | L7: =K7-J7 -> 0 | M7: ✓ On route
A8: 2026-04-01 | B8: SGTBLOEM | C8: TG Kwababa | D8: LB45BMGP | E8: 010426FC001 | F8: 1 | G8: 4 | H8: 4 | I8: 0 | J8: 449 | K8: 449 | L8: =K8-J8 -> 0 | M8: ✓ On route
A9: 2026-04-01 | B9: SGTBLOEM | C9: G Kwababa | D9: LB45BMGP | E9: 010426FL001 | F9: 1 | G9: 2 | H9: 2 | I9: 0 | J9: 28 | K9: 28 | L9: =K9-J9 -> 0 | M9: ✓ On route
A10: 2026-04-01 | B10: SGTSPFMCG | C10: Osbar Naka | D10: KZ97BKGP | E10: 010426GC001 | F10: 0.66 | G10: 15 | H10: 10 | I10: 5 | J10: 847 | K10: 972 | L10: =K10-J10 -> 125 | M10: ⚠ 66% hit rate — 5 stops missed, 125km excess — fatigue/routing review required
A11: → ADD NEW DEBRIEF ROWS BELOW (paste from DriverDebriefSummary.xlsx export)
L12: =IFERROR(K12-J12,0) -> 0
L13: =IFERROR(K13-J13,0) -> 0
L14: =IFERROR(K14-J14,0) -> 0
L15: =IFERROR(K15-J15,0) -> 0
L16: =IFERROR(K16-J16,0) -> 0
L17: =IFERROR(K17-J17,0) -> 0
L18: =IFERROR(K18-J18,0) -> 0
L19: =IFERROR(K19-J19,0) -> 0
L20: =IFERROR(K20-J20,0) -> 0
L21: =IFERROR(K21-J21,0) -> 0
L22: =IFERROR(K22-J22,0) -> 0
L23: =IFERROR(K23-J23,0) -> 0
... L41: =IFERROR(K41-J41,0) -> 0
A44: DEBRIEF KPI SUMMARY — feeds S_Scorecard and Net-Zero km efficiency
A45: KPI | B45: Value | C45: Benchmark
A46: Average Customer Hit % | B46: =IFERROR(AVERAGEIF(F4:F40,">0",F4:F40),0) -> 0.93 | C46: ≥95% = full score
A47: Total Excess km (waste driving) | B47: =IFERROR(SUM(L4:L40),0) -> 125 | C47: Target: 0 excess km
A48: Excess km as % of total planned | B48: =IFERROR(SUM(L4:L40)/SUM(J4:J40),0) -> 0.088090204 | C48: Target: <2%
A49: Estimated Scope 1 from excess km | B49: =IFERROR(SUM(L4:L40)*0.003,0) -> 0.375 | C49: Fleet avg CO₂/km estimate
A50: Routes <80% customer hit rate | B50: =IFERROR(COUNTIF(F4:F40,"<0.8"),0) -> 1 | C50: Target: 0
A51: Driver fatigue flags this period | B51: =0 -> 0 | C51: Target: 0

Sheet S_Data
A1: S_DATA — SOCIAL RAW DATA | H&S · EE Headcount · Training · Community [Sources: Accidently / HR / SETA / Cority]
A3: EMPLOYMENT EQUITY — HEADCOUNT BY OCCUPATIONAL LEVEL & RACE [EEA2 format | Source: HR payroll system]
A4: Occupational Level | B4: Af M | C4: Col M | D4: Ind M | E4: Wht M | F4: Af F | G4: Col F | H4: Ind F | I4: Wht F | J4: For M | K4: For F | L4: TOTAL
A5: Top Management (EEA2 L1) | B5: 0 | C5: 0 | D5: 0 | E5: 0 | F5: 0 | G5: 0 | H5: 0 | I5: 0 | J5: 0 | K5: 0 | L5: =SUM(B5:K5) -> 0
A6: Senior Management (EEA2 L2) | B6: 0 | C6: 0 | D6: 0 | E6: 0 | F6: 0 | G6: 0 | H6: 0 | I6: 0 | J6: 0 | K6: 0 | L6: =SUM(B6:K6) -> 0
A7: Professionally Qualified (EEA2 L3) | B7: 0 | C7: 0 | D7: 0 | E7: 0 | F7: 0 | G7: 0 | H7: 0 | I7: 0 | J7: 0 | K7: 0 | L7: =SUM(B7:K7) -> 0
A8: Skilled Technical (EEA2 L4) | B8: 0 | C8: 0 | D8: 0 | E8: 0 | F8: 0 | G8: 0 | H8: 0 | I8: 0 | J8: 0 | K8: 0 | L8: =SUM(B8:K8) -> 0
A9: Semi-Skilled (EEA2 L5) | B9: 0 | C9: 0 | D9: 0 | E9: 0 | F9: 0 | G9: 0 | H9: 0 | I9: 0 | J9: 0 | K9: 0 | L9: =SUM(B9:K9) -> 0
A10: Unskilled (EEA2 L6) | B10: 0 | C10: 0 | D10: 0 | E10: 0 | F10: 0 | G10: 0 | H10: 0 | I10: 0 | J10: 0 | K10: 0 | L10: =SUM(B10:K10) -> 0
A11: Non-Permanent | B11: 0 | C11: 0 | D11: 0 | E11: 0 | F11: 0 | G11: 0 | H11: 0 | I11: 0 | J11: 0 | K11: 0 | L11: =SUM(B11:K11) -> 0
A12: TOTAL ALL LEVELS | B12: =SUM(B5,B6,B7,B8,B9,B10,B11) -> 0 | C12: =SUM(C5,C6,C7,C8,C9,C10,C11) -> 0 | D12: =SUM(D5,D6,D7,D8,D9,D10,D11) -> 0 | E12: =SUM(E5,E6,E7,E8,E9,E10,E11) -> 0 | F12: =SUM(F5,F6,F7,F8,F9,F10,F11) -> 0 | G12: =SUM(G5,G6,G7,G8,G9,G10,G11) -> 0 | H12: =SUM(H5,H6,H7,H8,H9,H10,H11) -> 0 | I12: =SUM(I5,I6,I7,I8,I9,I10,I11) -> 0 | ... L12: =SUM(L5,L6,L7,L8,L9,L10,L11) -> 0
A14: EE TARGETS & GAP ANALYSIS [EEA Section 20 targets]
A15: Level | B15: Total | C15: % Black | D15: Target % Black | E15: % Black Female | F15: Target % BlkF | G15: % PWD | H15: Target % PWD | I15: Gap Black | J15: Score /10
A16: Top Management (EEA2 L1) | B16: =S_Data!L5 -> 0 | C16: =IFERROR((S_Data!B5+S_Data!C5+S_Data!D5+S_Data!F5+S_Data!G5+S_Data!H5)/S_Data!L5,0) -> 0 | D16: 0.55 | E16: =IFERROR((S_Data!F5+S_Data!G5+S_Data!H5)/S_Data!L5,0) -> 0 | F16: 0.3 | G16: =0 -> 0 | H16: 0.02 | I16: =C16-D16 -> -0.55 | J16: =MAX(0,MIN(10,10*(C16/D16))) -> 0
A17: Senior Management (EEA2 L2) | B17: =S_Data!L6 -> 0 | C17: =IFERROR((S_Data!B6+S_Data!C6+S_Data!D6+S_Data!F6+S_Data!G6+S_Data!H6)/S_Data!L6,0) -> 0 | D17: 0.55 | E17: =IFERROR((S_Data!F6+S_Data!G6+S_Data!H6)/S_Data!L6,0) -> 0 | F17: 0.3 | G17: =0 -> 0 | H17: 0.02 | I17: =C17-D17 -> -0.55 | J17: =MAX(0,MIN(10,10*(C17/D17))) -> 0
A18: Professionally Qualified (EEA2 L3) | B18: =S_Data!L7 -> 0 | C18: =IFERROR((S_Data!B7+S_Data!C7+S_Data!D7+S_Data!F7+S_Data!G7+S_Data!H7)/S_Data!L7,0) -> 0 | D18: 0.55 | E18: =IFERROR((S_Data!F7+S_Data!G7+S_Data!H7)/S_Data!L7,0) -> 0 | F18: 0.3 | G18: =0 -> 0 | H18: 0.02 | I18: =C18-D18 -> -0.55 | J18: =MAX(0,MIN(10,10*(C18/D18))) -> 0
A19: Skilled Technical (EEA2 L4) | B19: =S_Data!L8 -> 0 | C19: =IFERROR((S_Data!B8+S_Data!C8+S_Data!D8+S_Data!F8+S_Data!G8+S_Data!H8)/S_Data!L8,0) -> 0 | D19: 0.55 | E19: =IFERROR((S_Data!F8+S_Data!G8+S_Data!H8)/S_Data!L8,0) -> 0 | F19: 0.3 | G19: =0 -> 0 | H19: 0.02 | I19: =C19-D19 -> -0.55 | J19: =MAX(0,MIN(10,10*(C19/D19))) -> 0
A20: Semi-Skilled (EEA2 L5) | B20: =S_Data!L9 -> 0 | C20: =IFERROR((S_Data!B9+S_Data!C9+S_Data!D9+S_Data!F9+S_Data!G9+S_Data!H9)/S_Data!L9,0) -> 0 | D20: 0.55 | E20: =IFERROR((S_Data!F9+S_Data!G9+S_Data!H9)/S_Data!L9,0) -> 0 | F20: 0.3 | G20: =0 -> 0 | H20: 0.02 | I20: =C20-D20 -> -0.55 | J20: =MAX(0,MIN(10,10*(C20/D20))) -> 0
A21: Unskilled (EEA2 L6) | B21: =S_Data!L10 -> 0 | C21: =IFERROR((S_Data!B10+S_Data!C10+S_Data!D10+S_Data!F10+S_Data!G10+S_Data!H10)/S_Data!L10,0) -> 0 | D21: 0.55 | E21: =IFERROR((S_Data!F10+S_Data!G10+S_Data!H10)/S_Data!L10,0) -> 0 | F21: 0.3 | G21: =0 -> 0 | H21: 0.02 | I21: =C21-D21 -> -0.55 | J21: =MAX(0,MIN(10,10*(C21/D21))) -> 0
J22: =AVERAGE(J16,J17,J18,J19,J20,J21) -> 0
A24: HEALTH & SAFETY [ISO 45001 | Source: Accidently system | Cority report | Driver debrief]
A25: H&S Metric | B25: Unit | C25: Q1 Jul-Sep | D25: Q2 Oct-Dec | E25: Q3 Jan-Mar | F25: Q4 Apr-Jun | G25: YTD | H25: Target
A26: Total employees (for LTIFR calc) | B26: headcount | C26: 426 | D26: 426 | E26: 426 | F26: 426 | G26: 426 | H26: < 2.0 | I26: Source: Coba HR data, 426 FTE excl. labour brokers (constant across quarters pending monthly updates)
A27: Hours worked YTD | B27: hours | C27: 0 | D27: 0 | E27: 0 | F27: 0 | G27: =SUM(C27:F27) -> 0
A28: Fatalities YTD | B28: count | C28: — | D28: — | E28: — | F28: — | G28: — | H28: 0
A29: Lost Time Injuries YTD | B29: count | C29: 1 | D29: 2 | E29: 1 | F29: 0 | G29: =SUM(C29:F29) -> 4 | I29: Source: SHE Incidents register Jul-25 to Apr-26 (Wallace Arends, Ndumiso Mkhize, Joseph Sebeko, Tendani Matumba)
A30: Medical Treatment Injuries (MTI) | B30: count | C30: 0 | D30: 0 | E30: 3 | F30: 0 | G30: =SUM(C30:F30) -> 3
A31: First Aid Cases | B31: count | C31: 0 | D31: 0 | E31: 0 | F31: 0 | G31: =SUM(C31:F31) -> 0
A32: Near Miss incidents | B32: count | C32: 0 | D32: 0 | E32: 1 | F32: 0 | G32: =SUM(C32:F32) -> 1
A33: Vehicle accidents (fleet) | B33: count | C33: 1 | D33: 4 | E33: 3 | F33: 0 | G33: =SUM(C33:F33) -> 8
A34: Driver fatigue incidents (debrief) | B34: count | C34: 0 | D34: 0 | E34: 0 | F34: 0 | G34: =SUM(C34:F34) -> 0
A35: LTIFR (auto-calc) | B35: rate | C35: — | D35: — | E35: — | F35: — | G35: =IF(SUM(C27:F27)>0,SUM(C29:F29)*1000000/SUM(C27:F27),"Awaiting hours worked") -> Awaiting hours worked | H35: < 2.0
A36: TRIFR (LTI+MTI per M hrs) | B36: rate | C36: — | D36: — | E36: — | F36: — | G36: =IF(SUM(C27:F27)>0,(SUM(C29:F29)+SUM(C30:F30))*1000000/SUM(C27:F27),"Awaiting hours worked") -> Awaiting hours worked | H36: < 4.0
A37: H&S training hours YTD | B37: hours | C37: 0 | D37: 0 | E37: 0 | F37: 0 | G37: =SUM(C37:F37) -> 0
A38: % employees with H&S induction | B38: percent | C38: 0 | D38: 0 | E38: 0 | F38: 0 | G38: =SUM(C38:F38) -> 0
A39: Safety files active (all suppliers) | B39: Yes/No | C39: 0 | D39: 0 | E39: 0 | F39: 0 | G39: =SUM(C39:F39) -> 0
A41: WSP / ATR — WORKPLACE SKILLS PLAN & ANNUAL TRAINING REPORT [Source: HR | SETA submission | SDL returns]
A42: Metric | B42: Value | C42: Target/Requirement | D42: Score /5
A43: Leviable payroll (R) | B43: 10331941 | C43: SDL Act s3 | E43: Source: SG Consumer (Coba) HR data — payroll excl. labour brokers, 27 May 2026
A44: SDL levy paid (1% of payroll) | B44: =IFERROR(B43*0.01,0) -> 103319.41 | C44: 1% mandatory
A45: WSP submitted to SETA (Y/N) | C45: Yes by 30 Apr | D45: =IF(B45="Yes",5,0) -> 0
A46: ATR submitted to SETA (Y/N) | C46: Yes by 30 Apr | D46: =IF(B46="Yes",5,0) -> 0
A47: Mandatory grant claimed (R) | C47: 20% of SDL levy
A48: Discretionary grant applied (R) | C48: Up to 49.5%
A49: Total training hours delivered | C49: ≥40 hrs/employee
A50: Training spend (R) | C50: ≥1% payroll
A51: % employees with training YTD | C51: ≥80%
A52: Black employees trained (%) | C52: ≥70% of trained
A53: Female employees trained (%) | C53: ≥50% of trained
A54: Youth (≤35) trained (%) | C54: ≥30% of trained
A55: PWD employees trained (%) | C55: ≥2% of trained
A57: OFO CODES — TRAINING INTERVENTIONS [WSP mandatory — aligned to SETA OFO database]
A58: OFO Code | B58: Occupation | C58: Learners (#) | D58: Programme | E58: Duration | F58: SETA | G58: Status | H58: Net-Zero Link
A59: 911101 | B59: Heavy Motor Vehicle Drivers | C59: 77 | D59: Fatigue Risk Management | E59: 2 days | F59: TETA | G59: WSP | H59: Scope 1 fuel efficiency
A60: 911101 | B60: Heavy Motor Vehicle Drivers | C60: 77 | D60: Defensive/Eco Driving | E60: 1 day | F60: TETA | G60: WSP | H60: Fleet CO₂ reduction
A61: 334101 | B61: SHEQ Officers | C61: 5 | D61: ISO 14001 Environmental Audit | E61: 5 days | F61: WRSETA | G61: WSP | H61: Environmental compliance
A62: 334101 | B62: SHEQ Officers | C62: 5 | D62: ISO 45001 H&S Management | E62: 3 days | F62: WRSETA | G62: WSP | H62: H&S compliance
A63: 241301 | B63: HR Practitioners | C63: 3 | D63: EEA Reporting & EE Plan | E63: 2 days | F63: WRSETA | G63: WSP | H63: Social — EE Act
A64: 121101 | B64: Operations Managers | C64: 8 | D64: ESG Reporting & Net-Zero | E64: 3 days | F64: WRSETA | G64: WSP | H64: All pillars
A65: 413201 | B65: Data Capturers | C65: 10 | D65: ESG Data Management | E65: 2 days | F65: WRSETA | G65: WSP | H65: Data quality
A66: 732101 | B66: Forklift Operators | C66: 25 | D66: Electric Forklift Certification | E66: 2 days | F66: TETA | G66: WSP | H66: EV transition
A67: 912101 | B67: Warehouse Workers | C67: 50 | D67: Environmental Awareness | E67: 1 day | F67: WRSETA | G67: WSP | H67: ISO 14001 awareness
G68: Add more rows below →
A70: COMMUNITY & SOCIAL INVESTMENT [CSI | Social Calendar 2026 | ISO 26000]
A71: Initiative | B71: Month | C71: Beneficiaries | D71: Spend (R) | E71: Category | F71: Net-Zero Link
A72: Mandela Day | B72: Jul-25 | C72: Community service (90-100% Black beneficiaries) | E72: CSI — Community | F72: GRI 413
A73: Casual Day Stickers (Kerin) | B73: Sep-25 | C73: Persons with disabilities (75-90% Black) | E73: CSI — Disability | F73: Social inclusion
A74: Mobility Golf Day | B74: Oct-25 | C74: Charitable fundraiser (75-90% Black) | E74: CSI — Fundraiser | F74: GRI 413
A75: CHOC Foundation | B75: Ongoing | C75: Childhood cancer support (75-90% Black) | E75: CSI — Health | F75: Social impact
A76: SA Guide Dog Association | B76: Ongoing | C76: Visually impaired mobility (70-85% Black) | E76: CSI — Disability | F76: Social inclusion
A77: Friends of Valkenburg Trust | B77: Ongoing | C77: Mental health support (75-90% Black) | E77: CSI — Mental Health | F77: GRI 413
A78: Blanket Drive (Stephanie / SG Mktg) | B78: May-26 | C78: Winter relief, in-kind (90-100% Black) | E78: CSI — Community Relief | F78: GRI 413
A79: Wings of Inspiration | B79: Ongoing | C79: Charitable movement (90-100% Black) | E79: CSI — Community | F79: GRI 413
A80: Gerald Fitzpatrick Donations | B80: Ongoing | C80: Elderly women care home (75-90% Black) | E80: SED — Enterprise Dev | F80: B-BBEE SED
A81: Jicama 89 | B81: Ongoing | C81: Children with visual impairments (100% Black) | E81: SED — Enterprise Dev | F81: B-BBEE SED
A82: TOTAL CSI/SED SPEND YTD (R) | D82: =SUM(D72:D81) -> 0 | E82: Budget allocation R45,000 (Coba May 2026)

Sheet G_Data
A1: G_DATA — GOVERNANCE RAW DATA [King V | IFRS S1/S2 | GARP/GRAP | POPIA | Board]
A3: BOARD & GOVERNANCE
A4: Governance Metric | B4: Current Value | C4: Target/Req | D4: Source | E4: King V Ref | F4: Score /5
A5: Board members (total) | B5: 7 | D5: Source: Coba 27 May 2026 — SG Holdings Ltd Board: 2 Exec (Mountford CEO, Brown CFO) + 5 NEDs (Chitalu Chair, Cathrall Lead Ind, Mehlomakulu, Mnisi, Phalane). John Mackay = Co Sec. | E5: P1-P16 | F5: =IF(B5>0,5,0) -> 5
A6: Independent non-executive directors | B6: 5 | D6: Source: Coba 27 May 2026 — 5 of 5 NEDs disclosed as Independent (Chitalu, Cathrall, Mehlomakulu, Mnisi, Phalane) | E6: P1-P16 | F6: =IFERROR(IF(B5=0,0,IF(B6/B5>=0.5,5,IF(B6/B5>=0.5*Assumptions!$B$9,5*B6/B5/0.5,0))),0) -> 5
A7: Executive directors | B7: 2 | D7: Source: Coba 27 May 2026 — Group ED: Peter Mountford (CEO), Colin Brown (CFO/Debt Officer). [Prior placeholder of 5 referred to SG Consumer divisional execs — different scope.] | E7: P1-P16 | F7: =IFERROR(IF(B5=0,0,IF(B7/B5<=0.4,5,MAX(0,5*(1-((B7/B5)-0.4)*2)))),0) -> 5
A8: % Black board members | B8: 0.42857143 | D8: Source: Coba 27 May 2026 — Black SA directors: Mehlomakulu, Mnisi, Phalane (3 of 7). Note: Chitalu (Zambian Chair) is African but not SA-EEA Black designated. Confirm classification with Co Sec. | E8: P1-P16 | F8: =IFERROR(IF(B8>=Assumptions!$B$50,5,IF(B8>=Assumptions!$B$50*Assumptions!$B$9,5*B8/Assumptions!$B$50,0)),0) -> 3.5714286
A9: % Female board members | B9: 0.14285714 | D9: Source: Coba 27 May 2026 — 1 female NED (Pitsi Mnisi) of 7. Gap vs 50% target = -35.7pp. Material gender diversity risk. | E9: P1-P16 | F9: =IFERROR(IF(B9>=0.5,5,IF(B9>=0.5*Assumptions!$B$9,5*B9/0.5,0)),0) -> 0
A10: Board meetings held YTD | B10: 4 | D10: Source: Inferred JSE-listed minimum (4/yr). Awaiting confirmation from Company Secretary John Mackay. | E10: P1-P16 | F10: =IFERROR(IF(B10>=4,5,IF(B10>=4*Assumptions!$B$9,5*B10/4,0)),0) -> 5
A11: Audit committee meetings YTD | B11: 4 | D11: Source: Coba 27 May 2026 — Cathrall chairs Audit Committee; assumed 4 meetings YTD (confirm minute count from Co Sec). | E11: P1-P16 | F11: =IFERROR(IF(B11>=4,5,IF(B11>=4*Assumptions!$B$9,5*B11/4,0)),0) -> 5
A12: Risk committee active (Y/N) | B12: Yes | D12: Source: Coba 27 May 2026 — Cathrall confirmed as Risk Committee Chair. [Updated from "Partial".] | E12: P1-P16 | F12: =IF(B12="Yes",5,IF(B12="Partial",2.5,0)) -> 5
A13: Social & Ethics committee active (Y/N) | B13: Yes | D13: Group Social and Ethics Committee — CSI/SED Policy §7 (identifies/approves/coordinates CSI & SED initiatives and budgets; monitors all CSI/SED expenditure) | E13: P1-P16 | F13: =IF(B13="Yes",5,IF(B13="Partial",2.5,0)) -> 5
A14: ESG linked to executive remuneration (Y/N) | D14: Not disclosed in supplied policies — confirm from Remco report | E14: P1-P16 | F14: =IF(B14="Yes",5,IF(B14="Partial",2.5,0)) -> 0
A15: Code of ethics in place (Y/N) | B15: Yes | D15: Super Group Code of Business Standards and Ethics — Rev 2, 30 Jan 2023, approved by SG Executive Committee (Public disclosure) | E15: P1-P16 | F15: =IF(B15="Yes",5,IF(B15="Partial",2.5,0)) -> 5
A16: Whistleblower hotline active (Y/N) | B16: Yes | D16: Source: Coba 27 May 2026 confirmed — Be Heard (https://beheard.co.za/make-a-disclosure/) 0800-007-117 anonymous 24/365. Case-count/response-time data requested from HO, confidential at Group level. | E16: P1-P16 | F16: =IF(B16="Yes",5,IF(B16="Partial",2.5,0)) -> 5
A17: POPIA Information Officer appointed (Y/N) | B17: Partial | D17: POPI Act compliance framework in place (Code of Ethics §6); SG Consumer POPI consent operational (Jan 2026 letter). Formal Information Officer appointment letter required as evidence. | E17: P1-P16 | F17: =IF(B17="Yes",5,IF(B17="Partial",2.5,0)) -> 2.5
A18: POPIA impact assessment done (Y/N) | B18: Partial | D18: Active POPI consent process suggests assessment performed — formal PIA documentation required as evidence | E18: P1-P16 | F18: =IF(B18="Yes",5,IF(B18="Partial",2.5,0)) -> 2.5
A19: External assurance of ESG report (Y/N) | D19: Not disclosed in supplied policies — confirm from latest integrated report | E19: P1-P16 | F19: =IF(B19="Yes",5,IF(B19="Partial",2.5,0)) -> 0
A20: Integrated report published (Y/N) | B20: Yes | D20: Source: Coba 27 May 2026 — SG Holdings JSE-listed publishes Integrated Report incl. ESG section (Group level). CSI/SED Policy §15(b)(v) confirms. | E20: P1-P16 | F20: =IF(B20="Yes",5,IF(B20="Partial",2.5,0)) -> 5
A21: Risk register updated (Y/N) | B21: Partial | D21: Risk-based approach evidenced (Code of Ethics §11 — pragmatic risk-based environmental performance); formal risk register documentation required | E21: P1-P16 | F21: =IF(B21="Yes",5,IF(B21="Partial",2.5,0)) -> 2.5
A22: Number of material risks identified | D22: Not disclosed in supplied policies — confirm count from risk register | E22: P1-P16 | F22: =IFERROR(IF(B22>=Assumptions!$B$61,5,IF(B22>=Assumptions!$B$61*Assumptions!$B$9,5*B22/Assumptions!$B$61,0)),0) -> 0
A23: Climate risk in risk register (Y/N) | B23: Partial | D23: GHG/emissions commitments in Code of Ethics §11; explicit climate risk in formal register requires confirmation | E23: P1-P16 | F23: =IF(B23="Yes",5,IF(B23="Partial",2.5,0)) -> 2.5
A24: Anti-corruption training done (Y/N) | B24: Partial | D24: Code of Ethics §8 and Supplier Code §5 establish zero-tolerance anti-bribery/corruption framework + whistleblower hotline; formal training records required as evidence | E24: P1-P16 | F24: =IF(B24="Yes",5,IF(B24="Partial",2.5,0)) -> 2.5
A26: GOVERNANCE TOTAL SCORE (out of 100) | F26: =SUM(F5:F24) -> 66.071429

Sheet EE_Scorecard
A1: EE SCORECARD — Employment Equity Act | EEA2 Reporting | GRI 405 [Links: S_Data headcount]
A3: EE SCORE CARD — Weighted scoring aligned to EEA & B-BBEE Management Control
A4: EE Indicator | B4: Actual | C4: Target | D4: Weight | E4: Score | F4: Max | G4: Status | H4: Standard Ref
A5: % Black (all levels combined) | B5: =IFERROR((S_Data!B5+S_Data!C5+S_Data!D5+S_Data!F5+S_Data!G5+S_Data!H5)/(S_Data!L5)*1,0) -> 0 | C5: 60% | D5: 20 | E5: =IFERROR(MIN(20,ROUND(B5/0.6*20,2)),0) -> 0 | F5: 20 | G5: =IF(E5>=F5*0.9,"✓ Met",IF(E5>=F5*0.5,"⚠ Partial","✗ Gap")) -> ✗ Gap | H5: EEA s27 / GRI 405
A6: % Black female (all levels) | B6: =0 -> 0 | C6: 30% | D6: 15 | E6: =IFERROR(MIN(15,ROUND(B6/0.3*15,2)),0) -> 0 | F6: 15 | G6: =IF(E6>=F6*0.9,"✓ Met",IF(E6>=F6*0.5,"⚠ Partial","✗ Gap")) -> ✗ Gap | H6: EEA s27 / GRI 405
A7: % Black Top/Senior Mgmt (L1+L2) | B7: =IFERROR((S_Data!B5+ S_Data!B6)/S_Data!L12,0) -> 0 | C7: 50% | D7: 20 | E7: =IFERROR(MIN(20,ROUND(B7/0.5*20,2)),0) -> 0 | F7: 20 | G7: =IF(E7>=F7*0.9,"✓ Met",IF(E7>=F7*0.5,"⚠ Partial","✗ Gap")) -> ✗ Gap | H7: EEA s27 / King V P4
A8: % Persons with Disabilities | B8: =0 -> 0 | C8: 2% | D8: 10 | E8: =IFERROR(MIN(10,ROUND(B8/0.02*10,2)),0) -> 0 | F8: 10 | G8: =IF(E8>=F8*0.9,"✓ Met",IF(E8>=F8*0.5,"⚠ Partial","✗ Gap")) -> ✗ Gap | H8: EEA s6 / GRI 405
A9: EE Plan submitted to DoEL (Y/N) | B9: Yes | C9: Yes | D9: 10 | E9: =IF(B9="Yes",10,IF(B9="Partial",5,0)) -> 10 | F9: 10 | G9: =IF(E9>=F9*0.9,"✓ Met",IF(E9>=F9*0.5,"⚠ Partial","✗ Gap")) -> ✓ Met | H9: EEA s20/21
A10: EE forum/TDs consulted (Y/N) | B10: Yes | C10: Yes | D10: 5 | E10: =IF(B10="Yes",5,IF(B10="Partial",2,0)) -> 5 | F10: 5 | G10: =IF(E10>=F10*0.9,"✓ Met",IF(E10>=F10*0.5,"⚠ Partial","✗ Gap")) -> ✓ Met | H10: EEA s16
A11: EE monitoring & reporting (Y/N) | B11: Yes | C11: Yes | D11: 5 | E11: =IF(B11="Yes",5,IF(B11="Partial",2,0)) -> 5 | F11: 5 | G11: =IF(E11>=F11*0.9,"✓ Met",IF(E11>=F11*0.5,"⚠ Partial","✗ Gap")) -> ✓ Met | H11: EEA s19
A12: Numerical targets set (Y/N) | B12: Yes | C12: Yes | D12: 5 | E12: =IF(B12="Yes",5,IF(B12="Partial",2,0)) -> 5 | F12: 5 | G12: =IF(E12>=F12*0.9,"✓ Met",IF(E12>=F12*0.5,"⚠ Partial","✗ Gap")) -> ✓ Met | H12: EEA s20(2)(b)
A13: Barriers to EE removed (Y/N) | B13: Yes | C13: Yes | D13: 5 | E13: =IF(B13="Yes",5,IF(B13="Partial",2,0)) -> 5 | F13: 5 | G13: =IF(E13>=F13*0.9,"✓ Met",IF(E13>=F13*0.5,"⚠ Partial","✗ Gap")) -> ✓ Met | H13: EEA s20(2)(c)
A14: Affirmative measures implemented | B14: Yes | C14: Yes | D14: 5 | E14: =IF(B14="Yes",5,IF(B14="Partial",2,0)) -> 5 | F14: 5 | G14: =IF(E14>=F14*0.9,"✓ Met",IF(E14>=F14*0.5,"⚠ Partial","✗ Gap")) -> ✓ Met | H14: EEA s15
A15: EE TOTAL SCORE (out of 100) | E15: =SUM(E5,E6,E7,E8,E9,E10,E11,E12,E13,E14) -> 35 | F15: 100 | G15: =IF(E15>=85,"Excellent",IF(E15>=70,"Good",IF(E15>=50,"Adequate","Needs Attention"))) -> Needs Attention
A17: EE HEADCOUNT SUMMARY (from S_Data — update headcount there)
A18: Level | B18: Af M | C18: Col M | D18: Ind M | E18: Wht M | F18: Af F | G18: Col F | H18: Ind F | I18: Wht F
A19: Top Mgmt | B19: =S_Data!B5 -> 0 | C19: =S_Data!C5 -> 0 | D19: =S_Data!D5 -> 0 | E19: =S_Data!E5 -> 0 | F19: =S_Data!F5 -> 0 | G19: =S_Data!G5 -> 0 | H19: =S_Data!H5 -> 0 | I19: =S_Data!I5 -> 0
A20: Senior Mgmt | B20: =S_Data!B6 -> 0 | C20: =S_Data!C6 -> 0 | D20: =S_Data!D6 -> 0 | E20: =S_Data!E6 -> 0 | F20: =S_Data!F6 -> 0 | G20: =S_Data!G6 -> 0 | H20: =S_Data!H6 -> 0 | I20: =S_Data!I6 -> 0
A21: Prof Qualified | B21: =S_Data!B7 -> 0 | C21: =S_Data!C7 -> 0 | D21: =S_Data!D7 -> 0 | E21: =S_Data!E7 -> 0 | F21: =S_Data!F7 -> 0 | G21: =S_Data!G7 -> 0 | H21: =S_Data!H7 -> 0 | I21: =S_Data!I7 -> 0
A22: Skilled Tech | B22: =S_Data!B8 -> 0 | C22: =S_Data!C8 -> 0 | D22: =S_Data!D8 -> 0 | E22: =S_Data!E8 -> 0 | F22: =S_Data!F8 -> 0 | G22: =S_Data!G8 -> 0 | H22: =S_Data!H8 -> 0 | I22: =S_Data!I8 -> 0
A23: Semi-Skilled | B23: =S_Data!B9 -> 0 | C23: =S_Data!C9 -> 0 | D23: =S_Data!D9 -> 0 | E23: =S_Data!E9 -> 0 | F23: =S_Data!F9 -> 0 | G23: =S_Data!G9 -> 0 | H23: =S_Data!H9 -> 0 | I23: =S_Data!I9 -> 0
A24: Unskilled | B24: =S_Data!B10 -> 0 | C24: =S_Data!C10 -> 0 | D24: =S_Data!D10 -> 0 | E24: =S_Data!E10 -> 0 | F24: =S_Data!F10 -> 0 | G24: =S_Data!G10 -> 0 | H24: =S_Data!H10 -> 0 | I24: =S_Data!I10 -> 0
A25: TOTAL | B25: =S_Data!B12 -> 0 | C25: =S_Data!C12 -> 0 | D25: =S_Data!D12 -> 0 | E25: =S_Data!E12 -> 0 | F25: =S_Data!F12 -> 0 | G25: =S_Data!G12 -> 0 | H25: =S_Data!H12 -> 0 | I25: =S_Data!I12 -> 0

Sheet E_Scorecard
A1: E SCORECARD — Environmental Performance vs 100 pts | Net-Zero Lens | Links: E_Data
A3: Indicator | B3: Max Pts | C3: Actual (auto) | D3: Score | E3: Data Source | F3: Status | G3: Standard Ref | H3: Net-Zero Action | I3: Audit / Calculation
A4: ── GHG ──
A5: GHG: Scope 1 baseline established & tracked | B5: 5 | C5: =IF(E_Data!L19>0,5,0) -> 5 | D5: =MIN(C5,B5) -> 5 | E5: E_Data Fleet | F5: =IF(D5>=B5,"✓ Met",IF(D5>=B5*0.5,"⚠ Partial","✗ Gap")) -> ⚠ Partial | G5: IFRS S2 / GHG Protocol | H5: Baseline year: FY2025/26 | I5: Existence: E_Data!L19 (Fleet diesel YTD) > 0 → full 5 pts
A6: GHG: Scope 1 reduction vs prior year | B6: 10 | C6: =IFERROR(IF(E_Data!$B$90=0,0,IF((E_Data!$B$90-E_Data!$F$90)/E_Data!$B$90>=Assumptions!$B$43,10,IF((E_Data!$B$90-E_Data!$F$90)/E_Data!$B$90>=Assumptions!$B$43*Assumptions!$B$9,10*((E_Data!$B$90-E_Data!$F$90)/E_Data!$B$90)/Assumptions!$B$43,0))),0) -> 0 | D6: =MIN(C6,B6) -> 0 | E6: E_Data GHG | F6: =IF(D6>=B6,"✓ Met",IF(D6>=B6*0.5,"⚠ Partial","✗ Gap")) -> ✗ Gap | G6: SBTi near-term / IFRS S2 | H6: Target: -10% YoY → -50% by 2030 | I6: YoY reduction = (baseline-current)/baseline. Target = THR_GHG_YOY (Assumptions B36). Banded × stance floor.
A7: GHG: Scope 2 net reduction (solar offset) | B7: 8 | C7: =IFERROR(IF(E_Data!$M$80=0,0,IF(-E_Data!$M$81/E_Data!$M$80>=Assumptions!$B$44,8,IF(-E_Data!$M$81/E_Data!$M$80>=Assumptions!$B$44*Assumptions!$B$9,8*(-E_Data!$M$81/E_Data!$M$80)/Assumptions!$B$44,0))),0) -> 0 | D7: =MIN(C7,B7) -> 0 | E7: E_Data Solar | F7: =IF(D7>=B7,"✓ Met",IF(D7>=B7*0.5,"⚠ Partial","✗ Gap")) -> ✗ Gap | G7: RE100 / GRI 305-2 | H7: Expand solar all depots by 2027 | I7: Solar % of gross Scope 2 = -E_Data!M81/M80. Target = THR_RE (20%). Banded.
A8: GHG: Scope 3 tracking initiated | B8: 5 | C8: =IF(E_Data!$L$63>0,5,0) -> 5 | D8: =MIN(C8,B8) -> 5 | E8: E_Data Scope3 | F8: =IF(D8>=B8,"✓ Met",IF(D8>=B8*0.5,"⚠ Partial","✗ Gap")) -> ⚠ Partial | G8: GHG Protocol S3 / IFRS S2 | H8: Water, value chain, business travel | I8: Existence: E_Data!L63 (Water kL YTD) > 0 → full 5 pts (Scope 3 tracking initiated)
A9: GHG: Net-zero target formally set (SBTi) | B9: 5 | C9: =IF(AND(Assumptions!$B$107>=2030,Assumptions!$B$107<=2060),5,IF(Assumptions!$B$107>0,2.5,0)) -> 5 | D9: =MIN(C9,B9) -> 5 | E9: IFRS_S1_S2 | F9: =IF(D9>=B9,"✓ Met",IF(D9>=B9*0.5,"⚠ Partial","✗ Gap")) -> ⚠ Partial | G9: SBTi CNZS 2.0 | H9: Submit commitment letter FY2026 | I9: Net-zero target year set in Assumptions ENT_NZ (B105). 2030-2060 = full; other = half; blank = 0
A10: ── Energy ──
A11: Energy: kWh data tracked monthly (all 5 depots) | B11: 5 | C11: =IF(E_Data!L46>0,5,0) -> 5 | D11: =MIN(C11,B11) -> 5 | E11: E_Data Elec | F11: =IF(D11>=B11,"✓ Met",IF(D11>=B11*0.5,"⚠ Partial","✗ Gap")) -> ⚠ Partial | G11: GRI 302-1 | H11: Monthly utility bill reconciliation | I11: Existence: E_Data!L46 (Electricity kWh YTD) > 0 → full 5 pts
A12: Energy: Energy efficiency improvement YoY | B12: 5 | C12: 0 | D12: =MIN(C12,B12) -> 0 | E12: E_Data Elec | F12: =IF(D12>=B12,"✓ Met",IF(D12>=B12*0.5,"⚠ Partial","✗ Gap")) -> ✗ Gap | G12: GRI 302-4 / ISO 14001 | H12: LED retrofit; efficient cold chain | I12: Pending: requires prior-year kWh baseline. Add to E_Data and reformulate. Currently 0.
A13: Energy: % renewable electricity ≥20% | B13: 8 | C13: =IFERROR(IF(E_Data!$L$46=0,0,IF((E_Data!$L$50+E_Data!$L$51+E_Data!$L$52+E_Data!$L$53+E_Data!$L$54)/E_Data!$L$46>=Assumptions!$B$44,8,IF((E_Data!$L$50+E_Data!$L$51+E_Data!$L$52+E_Data!$L$53+E_Data!$L$54)/E_Data!$L$46>=Assumptions!$B$44*Assumptions!$B$9,8*((E_Data!$L$50+E_Data!$L$51+E_Data!$L$52+E_Data!$L$53+E_Data!$L$54)/E_Data!$L$46)/Assumptions!$B$44,0))),0) -> 0 | D13: =MIN(C13,B13) -> 0 | E13: E_Data Solar | F13: =IF(D13>=B13,"✓ Met",IF(D13>=B13*0.5,"⚠ Partial","✗ Gap")) -> ✗ Gap | G13: RE100 / IFRS S2 | H13: Solar at all 5 depots by 2028 | I13: Solar kWh ÷ Total grid kWh. Target = THR_RE (20%). Banded × stance.
A14: ── Fleet ──
A15: Fleet: L/100km within norm (all vehicles) | B15: 8 | C15: =IFERROR(IF(COUNTA(Fleet_Register!$A$4:$A$19)=0,0,8*SUMPRODUCT((Fleet_Register!$K$4:$K$19>0)*(Fleet_Register!$K$4:$K$19<=Fleet_Register!$L$4:$L$19*Assumptions!$B$45))/MAX(1,COUNTIF(Fleet_Register!$K$4:$K$19,">0"))),0) -> 0 | D15: =MIN(C15,B15) -> 0 | E15: Fleet_Register | F15: =IF(D15>=B15,"✓ Met",IF(D15>=B15*0.5,"⚠ Partial","✗ Gap")) -> ✗ Gap | G15: SASB TR-AU / GRI 302 | H15: Eco-driving training: -10% L/100km | I15: % of vehicles with K (L/100km actual) ≤ L (norm) × tolerance (THR_FUEL_TOL=1.05). Currently low because monthly km/litres not yet logged per vehicle.
A16: Fleet: Fleet CO₂ per tonne-km tracked | B16: 5 | C16: =IF(SUMPRODUCT((Fleet_Register!$F$4:$F$19>0)*(Fleet_Register!$I$4:$I$19>0))>0,5,0) -> 0 | D16: =MIN(C16,B16) -> 0 | E16: Fleet_Register + tonnage | F16: =IF(D16>=B16,"✓ Met",IF(D16>=B16*0.5,"⚠ Partial","✗ Gap")) -> ✗ Gap | G16: IFRS S2 / GRI 305 | H16: Monthly intensity reporting | I16: Existence: any vehicle with both carry capacity (F) and km logged (I) → full 5 pts
A17: Fleet: EV vehicles as % of fleet | B17: 5 | C17: =IFERROR(IF(Fleet_Register!$B$28=0,0,IF(Fleet_Register!$H$28/Fleet_Register!$B$28>=Assumptions!$B$46,5,IF(Fleet_Register!$H$28/Fleet_Register!$B$28>=Assumptions!$B$46*Assumptions!$B$9,5*(Fleet_Register!$H$28/Fleet_Register!$B$28)/Assumptions!$B$46,0))),0) -> 0 | D17: =MIN(C17,B17) -> 0 | E17: Fleet_Register | F17: =IF(D17>=B17,"✓ Met",IF(D17>=B17*0.5,"⚠ Partial","✗ Gap")) -> ✗ Gap | G17: SBTi Scope 3 / IFRS S2 | H17: 20% EV target by 2030 | I17: EV count ÷ total fleet (Fleet_Register row 28). Target = THR_EV_MIN (5% current). Banded.
A18: ── Waste ──
A19: Waste: Diversion rate ≥75% (target 91%+) | B19: 5 | C19: =IFERROR(IF(Waste_Register!$B$16>=Assumptions!$B$48,5,IF(Waste_Register!$B$16>=Assumptions!$B$48*Assumptions!$B$9,5*Waste_Register!$B$16/Assumptions!$B$48,0)),0) -> 5 | D19: =MIN(C19,B19) -> 5 | E19: Waste_Register | F19: =IF(D19>=B19,"✓ Met",IF(D19>=B19*0.5,"⚠ Partial","✗ Gap")) -> ⚠ Partial | G19: GRI 306 / ISO 14001 | H19: Extend Oricol CPT to all depots | I19: Waste_Register!B16 (Oricol CPT diversion %). Target = THR_WASTE (75%). Banded.
A20: Waste: Cardboard recycling tracked (Cority) | B20: 4 | C20: =IF(Waste_Register!$B$17>0,4,0) -> 4 | D20: =MIN(C20,B20) -> 4 | E20: E_Data Waste | F20: =IF(D20>=B20,"✓ Met",IF(D20>=B20*0.5,"⚠ Partial","✗ Gap")) -> ⚠ Partial | G20: GRI 306 / ISO 14001 | H20: Monthly depot reporting | I20: Existence: Cority average % recycled (Waste_Register B17) > 0 → full 4 pts
A21: Waste: Landfill tCO₂e tracked | B21: 3 | C21: =IF(Waste_Register!$B$18>0,3,0) -> 3 | D21: =MIN(C21,B21) -> 3 | E21: Waste_Register | F21: =IF(D21>=B21,"✓ Met",IF(D21>=B21*0.5,"⚠ Partial","✗ Gap")) -> ⚠ Partial | G21: GRI 306-3 | H21: Minimise landfill send | I21: Existence: Waste_Register B18 (Landfill tCO₂e YTD) > 0 → full 3 pts
A22: ── Water ──
A23: Water: Monthly consumption tracked (all depots) | B23: 4 | C23: =IF(E_Data!L63>0,4,0) -> 4 | D23: =MIN(C23,B23) -> 4 | E23: E_Data Water | F23: =IF(D23>=B23,"✓ Met",IF(D23>=B23*0.5,"⚠ Partial","✗ Gap")) -> ⚠ Partial | G23: GRI 303-1 | H23: CT dam project; DBN monitoring | I23: Existence: E_Data!L63 (Water kL YTD) > 0 → full 4 pts
A24: Water: Water efficiency initiative active | B24: 3 | C24: 0 | D24: =MIN(C24,B24) -> 0 | E24: E_Data | F24: =IF(D24>=B24,"✓ Met",IF(D24>=B24*0.5,"⚠ Partial","✗ Gap")) -> ✗ Gap | G24: GRI 303-3 | H24: CT dam, DBN 20kL project | I24: Pending: requires water efficiency initiative Y/N flag in G_Data. Currently 0.
A25: ── ISO ──
A26: ISO 14001: Certification achieved/in progress | B26: 8 | C26: 0 | D26: =MIN(C26,B26) -> 0 | E26: ISO_Tracker | F26: =IF(D26>=B26,"✓ Met",IF(D26>=B26*0.5,"⚠ Partial","✗ Gap")) -> ✗ Gap | G26: ISO 14001 | H26: Target date confirm with Maria | I26: Pending: requires ISO 14001 cert status (Y/N) from ISO_Tracker. Currently 0.
A27: ISO 14001: Aspects register maintained | B27: 4 | C27: 0 | D27: =MIN(C27,B27) -> 0 | E27: ISO_Tracker | F27: =IF(D27>=B27,"✓ Met",IF(D27>=B27*0.5,"⚠ Partial","✗ Gap")) -> ✗ Gap | G27: ISO 14001 cl 6.1.2 | H27: Fleet diesel dominant aspect | I27: Pending: aspects register Y/N from ISO_Tracker. Currently 0.
A28: Environmental policy — board approved | B28: 4 | C28: 0 | D28: =MIN(C28,B28) -> 0 | E28: G_Data | F28: =IF(D28>=B28,"✓ Met",IF(D28>=B28*0.5,"⚠ Partial","✗ Gap")) -> ✗ Gap | G28: King V P1 / ISO 14001 | H28: Include net-zero commitment | I28: Pending: env policy approval Y/N from G_Data row 23. Currently 0.
A29: NEMA/NWA/NEMWA legal compliance | B29: 4 | C29: 0 | D29: =MIN(C29,B29) -> 0 | E29: ISO_Tracker | F29: =IF(D29>=B29,"✓ Met",IF(D29>=B29*0.5,"⚠ Partial","✗ Gap")) -> ✗ Gap | G29: NEMA / NWA | H29: Legal register quarterly | I29: Pending: legal compliance status from ISO_Tracker. Currently 0.
A30: E SCORECARD TOTAL | D30: =SUM(D5,D6,D7,D8,D9,D11,D12,D13,D15,D16,D17,D19,D20,D21,D23,D24,D26,D27,D28,D29) -> 36 | E30: 108 pts max

Sheet S_Scorecard
A1: S SCORECARD — Social Performance vs 100 pts | EE · WSP/ATR · H&S · Community | Links: S_Data
A3: Indicator | B3: Max Pts | C3: Actual | D3: Score | E3: Data Source | F3: Status | G3: Standard Ref | H3: EE/WSP Action | I3: Audit / Calculation
A4: ── EE ──
A5: EE: % Black employees (all levels) vs 60% target | B5: 8 | C5: =IFERROR(IF(EE_Scorecard!$B$5>=Assumptions!$B$50,8,IF(EE_Scorecard!$B$5>=Assumptions!$B$50*Assumptions!$B$9,8*EE_Scorecard!$B$5/Assumptions!$B$50,0)),0) -> 0 | D5: =MIN(C5,B5) -> 0 | E5: EE_Scorecard | F5: =IF(D5>=B5,"✓ Met",IF(D5>=B5*0.5,"⚠ Partial","✗ Gap")) -> ✗ Gap | G5: EEA s27 / GRI 405-1 | H5: EE act compliance | I5: % Black (EE_Scorecard B5) ÷ THR_BLACK (60%). Banded × stance.
A6: EE: % Black female management (L1-L3) vs 30% | B6: 6 | C6: =IFERROR(IF((S_Data!$L$5+S_Data!$L$6)=0,0,IF((S_Data!$F$5+S_Data!$F$6+S_Data!$G$5+S_Data!$G$6+S_Data!$H$5+S_Data!$H$6)/(S_Data!$L$5+S_Data!$L$6)>=Assumptions!$B$51,6,IF((S_Data!$F$5+S_Data!$F$6+S_Data!$G$5+S_Data!$G$6+S_Data!$H$5+S_Data!$H$6)/(S_Data!$L$5+S_Data!$L$6)>=Assumptions!$B$51*Assumptions!$B$9,6*((S_Data!$F$5+S_Data!$F$6+S_Data!$G$5+S_Data!$G$6+S_Data!$H$5+S_Data!$H$6)/(S_Data!$L$5+S_Data!$L$6))/Assumptions!$B$51,0))),0) -> 0 | D6: =MIN(C6,B6) -> 0 | E6: S_Data EE | F6: =IF(D6>=B6,"✓ Met",IF(D6>=B6*0.5,"⚠ Partial","✗ Gap")) -> ✗ Gap | G6: EEA s27 / B-BBEE Mgt Control | H6: Pipeline — promote Black females | I6: % Black female at L1+L2 (S_Data) ÷ THR_BFM (30%). Banded × stance.
A7: EE: EE Plan submitted & compliant | B7: 5 | C7: =IF(EE_Scorecard!$B$9="Yes",5,IF(EE_Scorecard!$B$9="Partial",2.5,0)) -> 5 | D7: =MIN(C7,B7) -> 5 | E7: S_Data WSP | F7: =IF(D7>=B7,"✓ Met",IF(D7>=B7*0.5,"⚠ Partial","✗ Gap")) -> ⚠ Partial | G7: EEA s20/21 | H7: Annual DoEL submission | I7: EE Plan submitted (EE_Scorecard B9). Yes=5, Partial=2.5, No=0
A8: EE: % Persons with Disabilities vs 2% | B8: 5 | C8: =IFERROR(IF(EE_Scorecard!$B$8>=Assumptions!$B$52,5,IF(EE_Scorecard!$B$8>=Assumptions!$B$52*Assumptions!$B$9,5*EE_Scorecard!$B$8/Assumptions!$B$52,0)),0) -> 0 | D8: =MIN(C8,B8) -> 0 | E8: S_Data EE | F8: =IF(D8>=B8,"✓ Met",IF(D8>=B8*0.5,"⚠ Partial","✗ Gap")) -> ✗ Gap | G8: EEA s6 | H8: PWD target per level | I8: % PWD (EE_Scorecard B8) ÷ THR_PWD (2%). Banded.
A9: EE: EE forum/TD consultation active | B9: 3 | C9: =IF(EE_Scorecard!$B$10="Yes",3,IF(EE_Scorecard!$B$10="Partial",1.5,0)) -> 3 | D9: =MIN(C9,B9) -> 3 | E9: S_Data | F9: =IF(D9>=B9,"✓ Met",IF(D9>=B9*0.5,"⚠ Partial","✗ Gap")) -> ⚠ Partial | G9: EEA s16 | H9: Monthly TDs meeting | I9: EE forum active (EE_Scorecard B10). Y/N.
A10: EE: EE numerical targets set and tracked | B10: 3 | C10: =IF(EE_Scorecard!$B$12="Yes",3,IF(EE_Scorecard!$B$12="Partial",1.5,0)) -> 3 | D10: =MIN(C10,B10) -> 3 | E10: S_Data | F10: =IF(D10>=B10,"✓ Met",IF(D10>=B10*0.5,"⚠ Partial","✗ Gap")) -> ⚠ Partial | G10: EEA s20(2)(b) | H10: Targets per level/race/gender | I10: EE numerical targets set (EE_Scorecard B12). Y/N.
A11: ── WSP ──
A12: WSP: WSP submitted to SETA on time | B12: 5 | C12: =IF(S_Data!B45="Yes",5,0) -> 0 | D12: =MIN(C12,B12) -> 0 | E12: S_Data WSP | F12: =IF(D12>=B12,"✓ Met",IF(D12>=B12*0.5,"⚠ Partial","✗ Gap")) -> ✗ Gap | G12: SDL Act s10 / GRI 404 | H12: Deadline: 30 April annually | I12: WSP submitted Y/N (S_Data B45). Yes=5, No=0
A13: WSP: ATR submitted on time | B13: 5 | C13: =IF(S_Data!B46="Yes",5,0) -> 0 | D13: =MIN(C13,B13) -> 0 | E13: S_Data WSP | F13: =IF(D13>=B13,"✓ Met",IF(D13>=B13*0.5,"⚠ Partial","✗ Gap")) -> ✗ Gap | G13: SDL Act s10 / GRI 404 | H13: Annual training report | I13: ATR submitted Y/N (S_Data B46). Yes=5, No=0
A14: WSP: Training hours per employee ≥40 hours | B14: 5 | C14: =IFERROR(IF(S_Data!$L$12=0,0,IF(S_Data!$B$49/S_Data!$L$12>=Assumptions!$B$53,5,IF(S_Data!$B$49/S_Data!$L$12>=Assumptions!$B$53*Assumptions!$B$9,5*(S_Data!$B$49/S_Data!$L$12)/Assumptions!$B$53,0))),0) -> 0 | D14: =MIN(C14,B14) -> 0 | E14: S_Data WSP | F14: =IF(D14>=B14,"✓ Met",IF(D14>=B14*0.5,"⚠ Partial","✗ Gap")) -> ✗ Gap | G14: GRI 404-1 | H14: Net-zero + EE-aligned programmes | I14: Total training hrs (S_Data B49) ÷ total employees (L12). Target = THR_TRAIN_HR (40). Banded.
A15: WSP: Mandatory grant recovery ≥80% | B15: 5 | C15: =IFERROR(IF(S_Data!$B$44=0,0,IF(S_Data!$B$47/S_Data!$B$44>=Assumptions!$B$54,5,IF(S_Data!$B$47/S_Data!$B$44>=Assumptions!$B$54*Assumptions!$B$9,5*(S_Data!$B$47/S_Data!$B$44)/Assumptions!$B$54,0))),0) -> 0 | D15: =MIN(C15,B15) -> 0 | E15: S_Data WSP | F15: =IF(D15>=B15,"✓ Met",IF(D15>=B15*0.5,"⚠ Partial","✗ Gap")) -> ✗ Gap | G15: SDL Act s11 | H15: Mandatory grant claim deadline | I15: Grant claimed (S_Data B47) ÷ SDL levy (B44). Target = THR_GRANT (80%). Banded.
A16: ── H&S ──
A17: H&S: LTIFR ≤ 2.0 | B17: 8 | C17: =IFERROR(IF(S_Data!$G$35=0,0,IF(S_Data!$G$35<=Assumptions!$B$55,8,IF(S_Data!$G$35<=Assumptions!$B$55/Assumptions!$B$9,MAX(0,8*(1+Assumptions!$B$9-S_Data!$G$35/Assumptions!$B$55)),0))),0) -> 0 | D17: =MIN(C17,B17) -> 0 | E17: S_Data H&S | F17: =IF(D17>=B17,"✓ Met",IF(D17>=B17*0.5,"⚠ Partial","✗ Gap")) -> ✗ Gap | G17: ISO 45001 / GRI 403-9 | H17: Fatigue management key lever | I17: LTIFR (S_Data G35). Target ≤ THR_LTIFR (2.0). Inverse banded × stance.
A18: H&S: Zero fatalities | B18: 8 | C18: =IFERROR(IF(OR(S_Data!$G$28=0,S_Data!$G$28="—",S_Data!$G$28=""),8,0),0) -> 8 | D18: =MIN(C18,B18) -> 8 | E18: S_Data H&S | F18: =IF(D18>=B18,"✓ Met",IF(D18>=B18*0.5,"⚠ Partial","✗ Gap")) -> ⚠ Partial | G18: GRI 403-9 / OHS Act | H18: Absolute priority | I18: Fatalities YTD (S_Data G28). Zero = full 8 pts; any fatality = 0 (absolute priority).
A19: H&S: Driver fatigue programme active | B19: 5 | C19: =IF(S_Data!$C$59>0,5,0) -> 5 | D19: =MIN(C19,B19) -> 5 | E19: Driver_Debrief | F19: =IF(D19>=B19,"✓ Met",IF(D19>=B19*0.5,"⚠ Partial","✗ Gap")) -> ⚠ Partial | G19: ISO 45001 / TETA | H19: All 77 drivers trained annually | I19: Driver fatigue training learners count (S_Data C59) > 0 → full 5 pts
A20: H&S: Incident investigation rate 100% | B20: 4 | C20: =IF(SUM(S_Data!$G$29:$G$33)>0,4,0) -> 4 | D20: =MIN(C20,B20) -> 4 | E20: S_Data H&S | F20: =IF(D20>=B20,"✓ Met",IF(D20>=B20*0.5,"⚠ Partial","✗ Gap")) -> ⚠ Partial | G20: ISO 45001 / OHS Act | H20: Accidently system all depots | I20: Incidents being logged (S_Data G29:G33 sum > 0) → full 4 pts. Refinement: link to G_Data investigation Y/N.
A21: ── Community ──
A22: Community: CSI/SED spend ≥1% NPAT | B22: 5 | C22: 0 | D22: =MIN(C22,B22) -> 0 | E22: S_Data Community | F22: =IF(D22>=B22,"✓ Met",IF(D22>=B22*0.5,"⚠ Partial","✗ Gap")) -> ✗ Gap | G22: GRI 413-1 / B-BBEE SED | H22: Align to social calendar | I22: Pending: requires NPAT input in G_Data + sum of S_Data D72:D79 (CSI spend). Currently 0.
A23: Community: Social calendar initiatives ≥6 pa | B23: 5 | C23: =IFERROR(IF(COUNTA(S_Data!$A$72:$A$79)>=6,5,IF(COUNTA(S_Data!$A$72:$A$79)>=6*Assumptions!$B$9,5*COUNTA(S_Data!$A$72:$A$79)/6,0)),0) -> 5 | D23: =MIN(C23,B23) -> 5 | E23: S_Data Community | F23: =IF(D23>=B23,"✓ Met",IF(D23>=B23*0.5,"⚠ Partial","✗ Gap")) -> ⚠ Partial | G23: ISO 26000 / King V P2 | H23: 2026 calendar active | I23: Count of CSI initiatives (S_Data A72:A79). Target = 6 pa. Banded.
A24: Community: Local labour procurement ≥40% | B24: 5 | C24: 0 | D24: =MIN(C24,B24) -> 0 | E24: S_Data | F24: =IF(D24>=B24,"✓ Met",IF(D24>=B24*0.5,"⚠ Partial","✗ Gap")) -> ✗ Gap | G24: B-BBEE ESD / GRI 204 | H24: Preferential procurement | I24: Pending: requires local procurement % input in S_Data. Currently 0.
A25: ── Supplier ──
A26: Supplier: IMS-T-149 H&S compliance ≥80% | B26: 5 | C26: 0 | D26: =MIN(C26,B26) -> 0 | E26: SAQ_Supplier | F26: =IF(D26>=B26,"✓ Met",IF(D26>=B26*0.5,"⚠ Partial","✗ Gap")) -> ✗ Gap | G26: GRI 308 / ISO 26000 | H26: Safety file check each supplier | I26: Pending: SAQ_Supplier aggregate score required. Currently 0.
A27: Supplier: Supplier food safety rating | B27: 5 | C27: 0 | D27: =MIN(C27,B27) -> 0 | E27: SAQ_Supplier | F27: =IF(D27>=B27,"✓ Met",IF(D27>=B27*0.5,"⚠ Partial","✗ Gap")) -> ✗ Gap | G27: ISO 22000 / GRI 416 | H27: Cold chain quality standards | I27: Pending: SAQ_Supplier food safety aggregate required. Currently 0.
A28: S SCORECARD TOTAL | D28: =SUM(D5,D6,D7,D8,D9,D10,D12,D13,D14,D15,D17,D18,D19,D20,D22,D23,D24,D26,D27) -> 33

Sheet G_Scorecard
A1: G SCORECARD — Governance vs 100 pts | King V · IFRS S1/S2 · GARP/GRAP · POPIA · ISO 27001
A3: Indicator | B3: Max Pts | C3: Actual | D3: Score | E3: Data Source | F3: Status | G3: Standard Ref | H3: Action | I3: Audit / Calculation
A4: ── King V ──
A5: King V: Score ≥70% (Apply & Explain) | B5: 25 | C5: =King5_Scorecard!E21/170*25 -> 19.852941 | D5: =MIN(C5,B5) -> 19.852941 | E5: King5_Scorecard | F5: =IF(D5>=B5,"✓ Met",IF(D5>=B5*0.5,"⚠ Partial","✗ Gap")) -> ⚠ Partial | G5: King V all 17 principles | H5: Board apply & explain all principles | I5: King V total (King5_Scorecard E21) ÷ 170 × 25. THR_KING (70%) is the rating threshold.
A6: King V: Social & Ethics Committee established | B6: 5 | C6: =G_Data!F13 -> 5 | D6: =MIN(C6,B6) -> 5 | E6: G_Data | F6: =IF(D6>=B6,"✓ Met",IF(D6>=B6*0.5,"⚠ Partial","✗ Gap")) -> ⚠ Partial | G6: King V P5 / Companies Act s72 | H6: S&EC ToR and meetings minutes | I6: S&E Committee active (G_Data F13). Scaled to max 5 pts.
A7: King V: ESG-linked executive remuneration | B7: 5 | C7: =G_Data!F14 -> 0 | D7: =MIN(C7,B7) -> 0 | E7: G_Data | F7: =IF(D7>=B7,"✓ Met",IF(D7>=B7*0.5,"⚠ Partial","✗ Gap")) -> ✗ Gap | G7: King V P6 / GRI 201 | H7: ESG KPIs in exec contracts | I7: ESG-linked remuneration (G_Data F14). Scaled to max 5 pts.
A8: ── IFRS ──
A9: IFRS: S1/S2 disclosures prepared | B9: 10 | C9: =IFERROR(10*COUNTIF(IFRS_S1_S2!D4:D40,"Yes")/MAX(1,COUNTA(IFRS_S1_S2!A4:A40)-COUNTBLANK(IFRS_S1_S2!A4:A40)),0) -> 0 | D9: =MIN(C9,B9) -> 0 | E9: IFRS_S1_S2 | F9: =IF(D9>=B9,"✓ Met",IF(D9>=B9*0.5,"⚠ Partial","✗ Gap")) -> ✗ Gap | G9: IFRS S1/S2 / TCFD | H9: Annual ESG/integrated report | I9: Count of "Yes" disclosures (IFRS_S1_S2 D4:D40) ÷ total rows × max 10 pts
A10: IFRS: Climate risk in board agenda | B10: 5 | C10: =G_Data!F23 -> 2.5 | D10: =MIN(C10,B10) -> 2.5 | E10: IFRS_S1_S2 | F10: =IF(D10>=B10,"✓ Met",IF(D10>=B10*0.5,"⚠ Partial","✗ Gap")) -> ⚠ Partial | G10: IFRS S2 / King V P10 | H10: Quarterly risk review | I10: Climate risk in register (G_Data F23). Scaled to max 5 pts.
A11: ── GARP ──
A12: GARP: ERM framework includes ESG/climate risks | B12: 8 | C12: =IF(G_Data!F21>0,IF(G_Data!F23>0,8,4),0) -> 8 | D12: =MIN(C12,B12) -> 8 | E12: GARP_GRAP | F12: =IF(D12>=B12,"✓ Met",IF(D12>=B12*0.5,"⚠ Partial","✗ Gap")) -> ⚠ Partial | G12: GARP ERM / IFRS S1 | H12: 10 material ESG risks identified | I12: Risk register updated (G_Data F21) AND climate risk included (F23) → full 8; only one → 4; neither → 0
A13: ── GRAP ──
A14: GARP: GRAP public interest compliance | B14: 5 | C14: =IF(G_Data!F5>0,5,0) -> 5 | D14: =MIN(C14,B14) -> 5 | E14: GARP_GRAP | F14: =IF(D14>=B14,"✓ Met",IF(D14>=B14*0.5,"⚠ Partial","✗ Gap")) -> ⚠ Partial | G14: Companies Act s93 | H14: PI score ≥500 monitored | I14: Board structure exists (G_Data F5 board count). 5 pts if board > 0.
A15: ── ISO 27001 ──
A16: ISO 27001: POPIA Information Officer appointed | B16: 5 | C16: =G_Data!F17 -> 2.5 | D16: =MIN(C16,B16) -> 2.5 | E16: ISO_Tracker | F16: =IF(D16>=B16,"✓ Met",IF(D16>=B16*0.5,"⚠ Partial","✗ Gap")) -> ⚠ Partial | G16: POPIA Act / ISO 27001 | H16: s55 appointment letter | I16: POPIA Info Officer appointed (G_Data F17). Scaled to max 5 pts.
A17: ISO 27001: Cyber/data risk assessed | B17: 5 | C17: =G_Data!F18 -> 2.5 | D17: =MIN(C17,B17) -> 2.5 | E17: ISO_Tracker | F17: =IF(D17>=B17,"✓ Met",IF(D17>=B17*0.5,"⚠ Partial","✗ Gap")) -> ⚠ Partial | G17: ISO 27001 / King V P9 | H17: Annual cyber risk assessment | I17: POPIA impact assessment done (G_Data F18). Scaled to max 5 pts.
A18: ── Reporting ──
A19: Transparency: ESG/Integrated report published | B19: 8 | C19: =G_Data!F20*8/5 -> 8 | D19: =MIN(C19,B19) -> 8 | E19: G_Data | F19: =IF(D19>=B19,"✓ Met",IF(D19>=B19*0.5,"⚠ Partial","✗ Gap")) -> ⚠ Partial | G19: King V P8/P15 / GRI 2-3 | H19: Annual publication commitment | I19: Integrated report published (G_Data F20). Rescaled from /5 to /8.
A20: Transparency: External assurance of ESG report | B20: 5 | C20: =G_Data!F19 -> 0 | D20: =MIN(C20,B20) -> 0 | E20: G_Data | F20: =IF(D20>=B20,"✓ Met",IF(D20>=B20*0.5,"⚠ Partial","✗ Gap")) -> ✗ Gap | G20: ISAE 3000 / King V P11 | H20: Assurance provider engaged | I20: External assurance of ESG report (G_Data F19). Scaled to max 5 pts.
A21: ── Ethics ──
A22: Ethics: Code of ethics + hotline active | B22: 4 | C22: =(G_Data!F15+G_Data!F16)/2*4/5 -> 4 | D22: =MIN(C22,B22) -> 4 | E22: G_Data | F22: =IF(D22>=B22,"✓ Met",IF(D22>=B22*0.5,"⚠ Partial","✗ Gap")) -> ⚠ Partial | G22: King V P1 / GRI 205 | H22: Confidential hotline operational | I22: Avg of code of ethics (G_Data F15) + whistleblower hotline (F16). Rescaled to /4.
A23: ── Compliance ──
A24: Compliance: Legal register maintained | B24: 5 | C24: =G_Data!F21 -> 2.5 | D24: =MIN(C24,B24) -> 2.5 | E24: ISO_Tracker | F24: =IF(D24>=B24,"✓ Met",IF(D24>=B24*0.5,"⚠ Partial","✗ Gap")) -> ⚠ Partial | G24: ISO 14001/45001 / King V P12 | H24: Quarterly compliance review | I24: Legal/risk register maintained (G_Data F21). Scaled to max 5 pts. Refinement: link directly to ISO_Tracker.
A25: Compliance: No material regulatory penalties | B25: 5 | C25: =IF(G_Data!B25="",5,IF(G_Data!B25=0,5,0)) -> 5 | D25: =MIN(C25,B25) -> 5 | E25: G_Data | F25: =IF(D25>=B25,"✓ Met",IF(D25>=B25*0.5,"⚠ Partial","✗ Gap")) -> ⚠ Partial | G25: Companies Act / NEMA | H25: Zero-tolerance compliance | I25: Material penalties counter (G_Data B25). Blank or 0 = full 5 pts; any penalties = 0
A26: G SCORECARD TOTAL | D26: =SUM(D5,D6,D7,D9,D10,D12,D14,D16,D17,D19,D20,D22,D24,D25) -> 64.852941

Sheet King5_Scorecard
A1: KING V GOVERNANCE SCORECARD — Apply & Explain Methodology | All 17 Principles
A3: # | B3: Principle | C3: Status (Apply/Explain/Not) | D3: Weight | E3: Score /10 | F3: Weighted Score | G3: Evidence Required | H3: Current Status / Evidence | I3: Action Required
A4: 1 | B4: [Chapter 1] Ethical leadership and organisational ethics | C4: Applied | D4: 8 | E4: =IF(C4="Applied",10,IF(C4="Explained",7,IF(C4="Partially Applied",5,0))) -> 10 | F4: =E4*D4/10 -> 8 | G4: Ethics policy, code of conduct, ethics hotline | H4: Super Group Code of Business Standards and Ethics (Rev 2, 30 Jan 2023) approved by Executive Committee; Be Heard whistleblower hotline 0800-007-117 (24/365); zero-tolerance anti-bribery framework | I4: Annual ethics training programme to be evidenced; ethics committee minutes
A5: 2 | B5: [Chapter 2] Responsible corporate citizenship | C5: Applied | D5: 6 | E5: =IF(C5="Applied",10,IF(C5="Explained",7,IF(C5="Partially Applied",5,0))) -> 10 | F5: =E5*D5/10 -> 6 | G5: CSI report, community engagement log, B-BBEE | H5: Super Group CSI and SED Policy (Rev 2, 30 Jan 2023) — SED budget 1% NPAT, CSI ≤0.25% NPAT; three-pronged approach (Central/Decentralised/Volunteerism); approval & monitoring by Group Social and Ethics Committee | I5: Publish FY25/26 CSI spend and beneficiary report
A6: 3 | B6: [Chapter 3] Board composition — skills, diversity, independence | C6: Explained | D6: 6 | E6: =IF(C6="Applied",10,IF(C6="Explained",7,IF(C6="Partially Applied",5,0))) -> 7 | F6: =E6*D6/10 -> 4.2 | G6: Board skills matrix, diversity stats, appointments | H6: Board composition not disclosed in supplied policy stack — listed SG Trading directors (6) and SG Consumer divisional executives (5) per POPI consent block | I6: Provide board skills matrix, diversity stats, independence declarations
A7: 4 | B7: [Chapter 4] Board roles, function and performance | C7: Explained | D7: 6 | E7: =IF(C7="Applied",10,IF(C7="Explained",7,IF(C7="Partially Applied",5,0))) -> 7 | F7: =E7*D7/10 -> 4.2 | G7: Board charter, director induction, evaluations | H7: Board charter not provided in supplied policies | I7: Provide board charter, director induction records, performance evaluations
A8: 5 | B8: [Chapter 5] Committees — Audit, Risk, Remco, S&E Committee | C8: Partially Applied | D8: 8 | E8: =IF(C8="Applied",10,IF(C8="Explained",7,IF(C8="Partially Applied",5,0))) -> 5 | F8: =E8*D8/10 -> 4 | G8: Committee ToRs, meeting minutes, composition | H8: Group Social and Ethics Committee confirmed (CSI/SED Policy §7); Audit/Risk/Remco committee ToRs and composition not provided | I8: Provide ToRs and minutes for Audit, Risk, Remco committees
A9: 6 | B9: [Chapter 6] Remuneration policy — ESG-linked KPIs | C9: Explained | D9: 6 | E9: =IF(C9="Applied",10,IF(C9="Explained",7,IF(C9="Partially Applied",5,0))) -> 7 | F9: =E9*D9/10 -> 4.2 | G9: Remco report, ESG KPIs in exec contracts | H9: Remco report and ESG-linked exec remuneration not disclosed in supplied policies | I9: Provide Remco report; embed ESG KPIs in executive contracts
A10: 7 | B10: [Chapter 7] Stakeholder engagement and inclusivity | C10: Applied | D10: 6 | E10: =IF(C10="Applied",10,IF(C10="Explained",7,IF(C10="Partially Applied",5,0))) -> 10 | F10: =E10*D10/10 -> 6 | G10: Stakeholder register, material issues, IAR | H10: CSI/SED Policy §15 details internal (intranet, Exco, MCFs, newsletters) and external (website, Integrated Report, PR, tender docs) communication plan; Supplier Code engages full supply chain | I10: Maintain stakeholder register; document material issues per IAR
A11: 8 | B11: [Chapter 8] Reporting — integrated reporting, materiality | C11: Applied | D11: 8 | E11: =IF(C11="Applied",10,IF(C11="Explained",7,IF(C11="Partially Applied",5,0))) -> 10 | F11: =E11*D11/10 -> 8 | G11: Integrated/ESG report, GRI index, materiality matrix | H11: CSI/SED Policy §15(b)(v) confirms Group Integrated Report including ESG Report as external communication channel | I11: Provide latest Integrated Report; complete materiality matrix in toolkit
A12: 9 | B12: [Chapter 9] Technology and information governance | C12: Applied | D12: 6 | E12: =IF(C12="Applied",10,IF(C12="Explained",7,IF(C12="Partially Applied",5,0))) -> 10 | F12: =E12*D12/10 -> 6 | G12: IT governance policy, POPIA compliance, cyber risk | H12: Code of Ethics §6 (Protection of Company Property — IP, confidential information, POPI Act compliance); active SG Consumer POPI consent process (Jan 2026) | I12: ISO 27001 certification path; formal POPIA Info Officer appointment letter; annual cyber risk assessment
A13: 10 | B13: [Chapter 10] Risk governance — ERM including climate risk | C13: Partially Applied | D13: 8 | E13: =IF(C13="Applied",10,IF(C13="Explained",7,IF(C13="Partially Applied",5,0))) -> 5 | F13: =E13*D13/10 -> 4 | G13: Risk register with climate risks, ERM policy | H13: Code of Ethics §11 commits to "pragmatic, risk-based approach" for environmental performance with GHG/waste/water targets; explicit climate risk integration into ERM register requires confirmation | I13: Formal climate risk integration into ERM register; quarterly board review of climate risks
A14: 11 | B14: [Chapter 11] Internal audit and combined assurance | C14: Partially Applied | D14: 6 | E14: =IF(C14="Applied",10,IF(C14="Explained",7,IF(C14="Partially Applied",5,0))) -> 5 | F14: =E14*D14/10 -> 3 | G14: Internal audit plan, combined assurance model | H14: Code of Ethics §8 confirms active Internal Audit Department (reactive + proactive); combined assurance model details not provided | I14: Document combined assurance model; provide internal audit annual plan
A15: 12 | B15: [Chapter 12] Governing compliance — legal, regulatory, ESG | C15: Applied | D15: 8 | E15: =IF(C15="Applied",10,IF(C15="Explained",7,IF(C15="Partially Applied",5,0))) -> 10 | F15: =E15*D15/10 -> 8 | G15: Legal compliance register, ESG compliance tracker | H15: Code of Ethics §3-4 commits to ethical compliance with all applicable laws; Supplier Code §5 enforces legislative compliance across supply chain; EE Policy aligns to EEA Chapter 3; multi-statute framework evidenced (Companies Act, POPI, EEA, OHS, NEMA, PRECCA, FICA) | I15: Maintain quarterly legal compliance register
... A20: 17 | B20: [King III] Residual — specific SA context requirements | C20: Applied | D20: 4 | E20: =IF(C20="Applied",10,IF(C20="Explained",7,IF(C20="Partially Applied",5,0))) -> 10 | F20: =E20*D20/10 -> 4 | G20: Companies Act compliance, MOI, AGM | H20: Companies Act compliance evidenced (Social & Ethics Committee per s72; Code of Ethics aligns to Companies Act principles); SA regulatory framework throughout (EEA, BCEA, SDL, POPIA, NEMA, OHS Act, PRECCA, FICA) | I20: Confirm MOI alignment; AGM evidence
A21: KING V TOTAL SCORE | E21: =SUM(E4,E5,E6,E7,E8,E9,E10,E11,E12,E13,E14,E15,E16,E17,E18,E19,E20) -> 135 | F21: =SUM(F4,F5,F6,F7,F8,F9,F10,F11,F12,F13,F14,F15,F16,F17,F18,F19,F20) -> 87 | G21: Max theoretical: 1100
E22: =IFERROR(E21/170,0) -> 0.79411765 | F22: =IF(F21>=120,"Excellent",IF(F21>=90,"Good",IF(F21>=60,"Adequate","Needs Attention"))) -> Adequate

Sheet IFRS_S1_S2
A1: IFRS S1 + S2 CLIMATE DISCLOSURE TRACKER | TCFD Framework | GHG Protocol [Links: E_Data GHG, NetZero_Roadmap]
A3: IFRS S1 — General Sustainability-Related Financial Information
B4: Disclosure Requirement | C4: Pillar | D4: Status | E4: Score /5 | F4: Data Source | G4: Current Status / Evidence | H4: Action Required
B5: Board oversight of climate risks | C5: Governance | D5: Partially Disclosed | E5: =IF(D5="Disclosed",5,IF(D5="Partially Disclosed",3,IF(D5="N/A",5,0))) -> 3 | F5: G_Data / King V P10 | G5: Group Social and Ethics Committee mandate covers environment (CSI/SED Policy); explicit climate mandate to be confirmed | H5: Embed explicit climate-risk oversight into S&EC charter
B6: Management role in climate risk | C6: Governance | D6: Not Disclosed | E6: =IF(D6="Disclosed",5,IF(D6="Partially Disclosed",3,IF(D6="N/A",5,0))) -> 0 | F6: G_Data | G6: Management climate KPIs not disclosed in supplied policies | H6: Assign exec climate risk owner with KPIs
B7: Climate risks to business model | C7: Strategy | D7: Partially Disclosed | E7: =IF(D7="Disclosed",5,IF(D7="Partially Disclosed",3,IF(D7="N/A",5,0))) -> 3 | F7: E_Data / Risk Register | G7: Code of Ethics §11 acknowledges vehicle emissions; physical/transition risk assessment to be formalised | H7: Document physical and transition climate risk assessment
B8: Climate opportunities identified | C8: Strategy | D8: Partially Disclosed | E8: =IF(D8="Disclosed",5,IF(D8="Partially Disclosed",3,IF(D8="N/A",5,0))) -> 3 | F8: Fleet_Register / E_Data | G8: Code of Ethics §11 commits to energy efficiency and cleaner fuel partnerships; explicit opportunity register required | H8: Build opportunity register; EV fleet, solar expansion business case
B9: Scenario analysis (1.5°C/2°C/4°C) | C9: Strategy | D9: Not Disclosed | E9: =IF(D9="Disclosed",5,IF(D9="Partially Disclosed",3,IF(D9="N/A",5,0))) -> 0 | F9: NetZero_Roadmap | G9: Climate scenario analysis not evidenced in supplied policies | H9: Commission 1.5°C/2°C/4°C scenario analysis
B10: Climate risk identification process | C10: Risk Management | D10: Partially Disclosed | E10: =IF(D10="Disclosed",5,IF(D10="Partially Disclosed",3,IF(D10="N/A",5,0))) -> 3 | F10: G_Data | G10: Code of Ethics §11 "pragmatic, risk-based approach" — formal identification process to be documented | H10: Document climate risk identification methodology
B11: Climate risk integration into ERM | C11: Risk Management | D11: Partially Disclosed | E11: =IF(D11="Disclosed",5,IF(D11="Partially Disclosed",3,IF(D11="N/A",5,0))) -> 3 | F11: G_Data | G11: ERM integration of climate risks requires confirmation | H11: Update risk register to include climate physical & transition risks
B12: Absolute Scope 1 GHG tCO₂e | C12: Metrics & Targets | E12: =IF(D12="Disclosed",5,IF(D12="Partially Disclosed",3,IF(D12="N/A",5,0))) -> 0 | F12: E_Data GHG_GRAND_ROW | G12: Fleet diesel + generator + LPG
B13: Absolute Scope 2 GHG tCO₂e | C13: Metrics & Targets | E13: =IF(D13="Disclosed",5,IF(D13="Partially Disclosed",3,IF(D13="N/A",5,0))) -> 0 | F13: E_Data ELEC_TOTAL | G13: Grid electricity per depot
B14: Scope 3 GHG material categories | C14: Metrics & Targets | E14: =IF(D14="Disclosed",5,IF(D14="Partially Disclosed",3,IF(D14="N/A",5,0))) -> 0 | F14: E_Data Scope3 | G14: Water, value chain transport
B15: GHG reduction targets | C15: Metrics & Targets | D15: Partially Disclosed | E15: =IF(D15="Disclosed",5,IF(D15="Partially Disclosed",3,IF(D15="N/A",5,0))) -> 3 | F15: NetZero_Roadmap | G15: Code of Ethics §11 commits to GHG quantification and target-setting; numerical SBTi-aligned targets to be confirmed (SBTi CNZS 2.0 net-zero by 2050 — toolkit Assumptions) | H15: Submit SBTi commitment letter; publish FY25/26 baseline and near-term targets
B16: Transition plan (net-zero pathway) | C16: Metrics & Targets | E16: =IF(D16="Disclosed",5,IF(D16="Partially Disclosed",3,IF(D16="N/A",5,0))) -> 0 | F16: NetZero_Roadmap | G16: OER tiers, EV fleet, solar expansion
A17: IFRS S2 — Climate-Related Disclosures
B18: Disclosure Requirement | C18: Pillar | D18: Status | E18: Score /5 | F18: Data Source | G18: Current Status / Evidence | H18: Action Required
B19: Physical climate risks in board agenda | C19: Governance | D19: Not Disclosed | E19: =IF(D19="Disclosed",5,IF(D19="Partially Disclosed",3,IF(D19="N/A",5,0))) -> 0 | F19: G_Data | G19: Board agenda climate physical risk integration not evidenced | H19: Add quarterly climate physical risk to board agenda
B20: Transition climate risks in board agenda | C20: Governance | D20: Not Disclosed | E20: =IF(D20="Disclosed",5,IF(D20="Partially Disclosed",3,IF(D20="N/A",5,0))) -> 0 | F20: G_Data | G20: Board agenda climate transition risk integration not evidenced | H20: Add carbon tax / EV transition risk to board agenda
B21: Financial effect of climate risks (R) | C21: Strategy | E21: =IF(D21="Disclosed",5,IF(D21="Partially Disclosed",3,IF(D21="N/A",5,0))) -> 0 | F21: E_Data cost data | G21: Fuel cost sensitivity, stranded fleet risk
B22: Resilience of strategy to climate scenarios | C22: Strategy | E22: =IF(D22="Disclosed",5,IF(D22="Partially Disclosed",3,IF(D22="N/A",5,0))) -> 0 | F22: NetZero_Roadmap | G22: Net-zero pathway documented
B23: Energy intensity (kWh/tonne-km) | C23: Metrics | E23: =IF(D23="Disclosed",5,IF(D23="Partially Disclosed",3,IF(D23="N/A",5,0))) -> 0 | F23: E_Data / tonnage data | G23: Electricity and fuel per tonne delivered
B24: Fleet CO₂ intensity (tCO₂e/tonne-km) | C24: Metrics | E24: =IF(D24="Disclosed",5,IF(D24="Partially Disclosed",3,IF(D24="N/A",5,0))) -> 0 | F24: E_Data + tonnage | G24: Scope 1 fleet per tonne-km
B25: % renewable energy | C25: Metrics | E25: =IF(D25="Disclosed",5,IF(D25="Partially Disclosed",3,IF(D25="N/A",5,0))) -> 0 | F25: E_Data solar rows | G25: Solar kWh / total electricity kWh
B26: Carbon credits/offsets used | C26: Metrics | E26: =IF(D26="Disclosed",5,IF(D26="Partially Disclosed",3,IF(D26="N/A",5,0))) -> 0 | F26: Carbon_Credits_Register | G26: OER tier — credits register
B27: Internal carbon price (R/tCO₂e) | C27: Metrics | E27: =IF(D27="Disclosed",5,IF(D27="Partially Disclosed",3,IF(D27="N/A",5,0))) -> 0 | F27: Management decision | G27: Used for investment decisions?
B28: Climate-related capex planned (R) | C28: Metrics | E28: =IF(D28="Disclosed",5,IF(D28="Partially Disclosed",3,IF(D28="N/A",5,0))) -> 0 | F28: NetZero_Roadmap | G28: EV fleet, solar, insulation investments
A29: IFRS S1+S2 TOTAL SCORE | E29: =SUMIF(E5:E28,"<>0",E5:E28) -> 18
E30: =IFERROR(E29/110,0) -> 0.16363636

Sheet GARP_GRAP
A1: GARP / GRAP RISK & COMPLIANCE FRAMEWORK | ERM | Public Interest Alignment | IFRS S1 Risk
A3: GARP — Enterprise Risk Management (ERM)
B4: Risk / Requirement | C4: Description | D4: Data Source | E4: Severity | F4: Control Status | G4: Current Control / Evidence | H4: Improvement Action | I4: Likelihood (1-5) | J4: Risk Score | K4: Material?
B5: Climate Physical Risk | C5: Flooding (DBN 2022), extreme heat, supply disruption | D5: E_Data | E5: High | G5: Code of Ethics §11 commits to environmental risk management; SG Consumer flood-exposed depots (DBN/PE) | I5: 4 | J5: =IF(E5="High",5,IF(E5="Medium",3,IF(E5="Low",1,IF(E5="Req",4,0))))*I5 -> 20 | K5: =IF(J5>=12,"✓ Material",IF(J5>=6,"⚠ Monitor","○ Low")) -> ✓ Material
B6: Climate Transition Risk | C6: Carbon tax, fuel cost escalation, EV mandate | D6: E_Data | E6: High | G6: Code of Ethics §11 commits to GHG reduction, fuel efficiency, partnerships with cleaner fuel suppliers | I6: 5 | J6: =IF(E6="High",5,IF(E6="Medium",3,IF(E6="Low",1,IF(E6="Req",4,0))))*I6 -> 25 | K6: =IF(J6>=12,"✓ Material",IF(J6>=6,"⚠ Monitor","○ Low")) -> ✓ Material
B7: Operational Risk — Fleet | C7: Vehicle breakdowns, driver fatigue, accidents | D7: Fleet/S_Data | E7: High | G7: Code of Ethics §11 commits to vehicle maintenance per manufacturer spec; Driver Debrief operational | I7: 5 | J7: =IF(E7="High",5,IF(E7="Medium",3,IF(E7="Low",1,IF(E7="Req",4,0))))*I7 -> 25 | K7: =IF(J7>=12,"✓ Material",IF(J7>=6,"⚠ Monitor","○ Low")) -> ✓ Material
B8: Regulatory Risk — EE Act | C8: Non-compliance with EEA reporting deadlines | D8: S_Data EE | E8: Medium | G8: Super Group EE Policy (Rev 2, 30 Jan 2023) — formal EE Plan, designated employer, Chapter 3 EEA compliance; EE Committees established per s16 | I8: 3 | J8: =IF(E8="High",5,IF(E8="Medium",3,IF(E8="Low",1,IF(E8="Req",4,0))))*I8 -> 9 | K8: =IF(J8>=12,"✓ Material",IF(J8>=6,"⚠ Monitor","○ Low")) -> ⚠ Monitor
B9: Regulatory Risk — POPIA | C9: Data breach, non-appointment of Info Officer | D9: G_Data | E9: Medium | G9: Code of Ethics §6 (POPI Act compliance); SG Consumer POPI Consent process active (Jan 2026); Information Officer appointment to be confirmed | I9: 3 | J9: =IF(E9="High",5,IF(E9="Medium",3,IF(E9="Low",1,IF(E9="Req",4,0))))*I9 -> 9 | K9: =IF(J9>=12,"✓ Material",IF(J9>=6,"⚠ Monitor","○ Low")) -> ⚠ Monitor
B10: Financial Risk — SDL/WSP | C10: Non-submission of WSP/ATR, loss of grant | D10: S_Data WSP | E10: Medium | G10: Group Skills Development pipeline (CSI/SED + EE training commitments) — WSP submission status in S_Data | I10: 3 | J10: =IF(E10="High",5,IF(E10="Medium",3,IF(E10="Low",1,IF(E10="Req",4,0))))*I10 -> 9 | K10: =IF(J10>=12,"✓ Material",IF(J10>=6,"⚠ Monitor","○ Low")) -> ⚠ Monitor
B11: Reputational Risk — ESG | C11: Failure to publish ESG report, poor scores | D11: ESG_Dashboard | E11: Medium | G11: CSI/SED Policy §15(b)(v) confirms Integrated Report including ESG Report | I11: 3 | J11: =IF(E11="High",5,IF(E11="Medium",3,IF(E11="Low",1,IF(E11="Req",4,0))))*I11 -> 9 | K11: =IF(J11>=12,"✓ Material",IF(J11>=6,"⚠ Monitor","○ Low")) -> ⚠ Monitor
B12: Environmental Risk — Waste | C12: Landfill non-compliance, NEMA penalties | D12: E_Data Waste | E12: Low | G12: Code of Ethics §11 commits to systematic waste identification, management, reduction and recycling (hazardous + non-hazardous) | I12: 2 | J12: =IF(E12="High",5,IF(E12="Medium",3,IF(E12="Low",1,IF(E12="Req",4,0))))*I12 -> 2 | K12: =IF(J12>=12,"✓ Material",IF(J12>=6,"⚠ Monitor","○ Low")) -> ○ Low
B13: Supply Chain Risk | C13: Supplier ESG non-compliance (SAQ gaps) | D13: SAQ_Supplier | E13: Medium | G13: Super Group Supplier Code of Conduct (Rev 2, 30 Jan 2023) — full supplier ESG framework: labour, ethics, H&S, environment & sustainability | I13: 4 | J13: =IF(E13="High",5,IF(E13="Medium",3,IF(E13="Low",1,IF(E13="Req",4,0))))*I13 -> 12 | K13: =IF(J13>=12,"✓ Material",IF(J13>=6,"⚠ Monitor","○ Low")) -> ✓ Material
B14: Technology Risk | C14: System failure in Cority/fleet telematics | D14: G_Data | E14: Low | G14: Code of Ethics §6 (IT/IP controls); ISO 27001 certification path | I14: 2 | J14: =IF(E14="High",5,IF(E14="Medium",3,IF(E14="Low",1,IF(E14="Req",4,0))))*I14 -> 2 | K14: =IF(J14>=12,"✓ Material",IF(J14>=6,"⚠ Monitor","○ Low")) -> ○ Low
A15: GRAP — Public Interest Score & Accountability
B16: Risk / Requirement | C16: Description | D16: Data Source | E16: Severity | F16: Control Status | G16: Current Control / Evidence | H16: Improvement Action
B17: Public interest score ≥500 points | C17: Mandatory audit + Social & Ethics Committee | D17: G_Data | E17: Req | G17: Group Social and Ethics Committee operates per Companies Act s72 (CSI/SED Policy §7) | I17: 3 | J17: =IF(E17="High",5,IF(E17="Medium",3,IF(E17="Low",1,IF(E17="Req",4,0))))*I17 -> 12 | K17: =IF(J17>=12,"✓ Material",IF(J17>=6,"⚠ Monitor","○ Low")) -> ✓ Material
B18: Social & Ethics Committee (S&EC) | C18: Required if PI score ≥500 or listed | D18: G_Data | E18: Req | G18: Group Social and Ethics Committee — identifies/approves/monitors CSI & SED initiatives; budgets and expenditure (CSI/SED Policy §7) | I18: 3 | J18: =IF(E18="High",5,IF(E18="Medium",3,IF(E18="Low",1,IF(E18="Req",4,0))))*I18 -> 12 | K18: =IF(J18>=12,"✓ Material",IF(J18>=6,"⚠ Monitor","○ Low")) -> ✓ Material
B19: S&EC — Labour & Employment (EE, BCEA) | C19: S&EC must monitor EE, BBBEE, training | D19: S_Data | E19: Req | G19: EE Policy §6.10 — Group CEO + Reporting Entity Exec Officer jointly accountable for EE/AA implementation; EE KPA in Line Mgr performance agreements | I19: 3 | J19: =IF(E19="High",5,IF(E19="Medium",3,IF(E19="Low",1,IF(E19="Req",4,0))))*I19 -> 12 | K19: =IF(J19>=12,"✓ Material",IF(J19>=6,"⚠ Monitor","○ Low")) -> ✓ Material
B20: S&EC — Environment | C20: S&EC monitors environmental performance | D20: E_Data | E20: Req | G20: Code of Ethics §11 — environmental performance, GHG, waste, water, biodiversity, noise commitments; Supplier Code §8 cascades to supply chain | I20: 3 | J20: =IF(E20="High",5,IF(E20="Medium",3,IF(E20="Low",1,IF(E20="Req",4,0))))*I20 -> 12 | K20: =IF(J20>=12,"✓ Material",IF(J20>=6,"⚠ Monitor","○ Low")) -> ✓ Material
B21: S&EC — Anti-corruption | C21: S&EC monitors FICA, anti-bribery, ethics | D21: G_Data | E21: Req | G21: Code of Ethics §8 — zero-tolerance anti-bribery/corruption; Be Heard hotline 0800-007-117; Internal Audit Department active | I21: 3 | J21: =IF(E21="High",5,IF(E21="Medium",3,IF(E21="Low",1,IF(E21="Req",4,0))))*I21 -> 12 | K21: =IF(J21>=12,"✓ Material",IF(J21>=6,"⚠ Monitor","○ Low")) -> ✓ Material
B22: S&EC — Consumer relations | C22: Customer satisfaction, product quality | D22: Customer_Report_Data | E22: Req | G22: Code of Ethics §3 commitments to quality and product specifications; Supplier Code §6 enforces quality + food safety standards | I22: 3 | J22: =IF(E22="High",5,IF(E22="Medium",3,IF(E22="Low",1,IF(E22="Req",4,0))))*I22 -> 12 | K22: =IF(J22>=12,"✓ Material",IF(J22>=6,"⚠ Monitor","○ Low")) -> ✓ Material
B23: S&EC — Community development | C23: CSI, SED, skills development | D23: S_Data | E23: Req | G23: CSI/SED Policy — 1% NPAT SED target; three-pronged approach (Central/Decentralised/Volunteerism); 75% Black beneficiary requirement aligned to B-BBEE | I23: 3 | J23: =IF(E23="High",5,IF(E23="Medium",3,IF(E23="Low",1,IF(E23="Req",4,0))))*I23 -> 12 | K23: =IF(J23>=12,"✓ Material",IF(J23>=6,"⚠ Monitor","○ Low")) -> ✓ Material
B24: External audit coverage | C24: External auditors cover ESG risks | D24: G_Data | E24: Req | G24: Code of Ethics §8 — Internal Audit Department active in fraud/corruption detection; external assurance evidence to be provided | I24: 3 | J24: =IF(E24="High",5,IF(E24="Medium",3,IF(E24="Low",1,IF(E24="Req",4,0))))*I24 -> 12 | K24: =IF(J24>=12,"✓ Material",IF(J24>=6,"⚠ Monitor","○ Low")) -> ✓ Material
B26: RISK SUMMARY
B27: Total risks logged | C27: =COUNTA(B5:B14)+COUNTA(B17:B24) -> 18
B28: Material risks (score ≥12) | C28: =COUNTIF(K5:K14,"✓ Material")+COUNTIF(K17:K24,"✓ Material") -> 12
B29: Monitor risks (6-11) | C29: =COUNTIF(K5:K14,"⚠ Monitor")+COUNTIF(K17:K24,"⚠ Monitor") -> 4
B30: Maximum severity score | C30: =MAX(J5:J14,J17:J24) -> 25

Sheet ISO_Tracker
A1: ISO STANDARDS GAP TRACKER | ISO 14001 | 45001 | 27001 | 26000 | 22000 [Net-Zero lens on all]
A3: ISO 14001:2015 — Environmental Management System
B4: Requirement | C4: Clause | D4: Status | E4: Score /5 | F4: Weight | G4: Evidence Needed | H4: Current Evidence / Status | I4: Net-Zero / ESG Link
B5: Context of the organisation — internal/external issues | C5: 4.1 | E5: =IF(D5="Fully Compliant",5,IF(D5="Partially Compliant",3,IF(D5="Not Applicable",5,0))) -> 0 | F5: 1 | G5: Env issues register | I5: Net-zero context essential
B6: Interested parties — needs/expectations | C6: 4.2 | E6: =IF(D6="Fully Compliant",5,IF(D6="Partially Compliant",3,IF(D6="Not Applicable",5,0))) -> 0 | F6: 1 | G6: Stakeholder register | I6: Customers, SETA, DoEL
B7: Scope of EMS | C7: 4.3 | E7: =IF(D7="Fully Compliant",5,IF(D7="Partially Compliant",3,IF(D7="Not Applicable",5,0))) -> 0 | F7: 1 | G7: EMS scope document | I7: All 5 depots covered
B8: Environmental policy — net-zero commitment | C8: 5.2 | D8: Partially Compliant | E8: =IF(D8="Fully Compliant",5,IF(D8="Partially Compliant",3,IF(D8="Not Applicable",5,0))) -> 3 | F8: 1 | G8: Board-approved env policy | H8: Code of Ethics §11 — board-approved environmental policy with GHG, energy, water, waste, biodiversity, noise commitments. Explicit net-zero / SBTi commitment to be added. | I8: Include net-zero target
B9: Environmental objectives — GHG, energy, water, waste | C9: 6.2 | D9: Partially Compliant | E9: =IF(D9="Fully Compliant",5,IF(D9="Partially Compliant",3,IF(D9="Not Applicable",5,0))) -> 3 | F9: 1 | G9: KPIs in E_Scorecard | H9: Code of Ethics §11 commits to GHG quantification + target-setting; energy efficiency, water reduction, waste minimisation. Numerical SBTi targets pending formal commitment letter. | I9: Link to SBTi targets
B10: Environmental aspects — fleet emissions dominant | C10: 6.1.2 | D10: Partially Compliant | E10: =IF(D10="Fully Compliant",5,IF(D10="Partially Compliant",3,IF(D10="Not Applicable",5,0))) -> 3 | F10: 1 | G10: Aspects register | H10: Code of Ethics §11 identifies vehicle emissions as material aspect; full aspects register to be formalised. | I10: Fleet = >80% Scope 1
B11: Legal requirements register (NEMA, NWA, NEMWA) | C11: 6.1.3 | D11: Partially Compliant | E11: =IF(D11="Fully Compliant",5,IF(D11="Partially Compliant",3,IF(D11="Not Applicable",5,0))) -> 3 | F11: 1 | G11: Legal compliance register | H11: Code of Ethics §11 commits to compliance with all applicable laws and maintenance of environmental permits, licenses, approvals. | I11: Quarterly update
B12: Emergency preparedness — fuel spill, fire | C12: 8.2 | D12: Partially Compliant | E12: =IF(D12="Fully Compliant",5,IF(D12="Partially Compliant",3,IF(D12="Not Applicable",5,0))) -> 3 | F12: 1 | G12: Emergency response plan | H12: Supplier Code §8 references spill/incident response procedures (cascaded to suppliers); depot-level plans to be confirmed. | I12: All depot plans
B13: Monitoring & measurement — monthly GHG data | C13: 9.1 | E13: =IF(D13="Fully Compliant",5,IF(D13="Partially Compliant",3,IF(D13="Not Applicable",5,0))) -> 0 | F13: 1 | G13: E_Data sheet | I13: Monthly Mariette submission
B14: Internal audit — all depots | C14: 9.2 | E14: =IF(D14="Fully Compliant",5,IF(D14="Partially Compliant",3,IF(D14="Not Applicable",5,0))) -> 0 | F14: 1 | G14: Audit schedule | I14: Annual minimum
B15: Management review — ESG integration | C15: 9.3 | E15: =IF(D15="Fully Compliant",5,IF(D15="Partially Compliant",3,IF(D15="Not Applicable",5,0))) -> 0 | F15: 1 | G15: Board/management review | I15: Quarterly ESG review
B16: ISO 14001 certification achieved | C16: 10 | E16: =IF(D16="Fully Compliant",5,IF(D16="Partially Compliant",3,IF(D16="Not Applicable",5,0))) -> 0 | F16: 1 | G16: Certificate | I16: Target: confirm with Maria
B17: ISO 14001:2015 Score | E17: =SUM(E5,E6,E7,E8,E9,E10,E11,E12,E13,E14,E15,E16) -> 15
A19: ISO 45001:2018 — Occupational H&S Management System
B20: Requirement | C20: Clause | D20: Status | E20: Score /5 | F20: Weight | G20: Evidence Needed | H20: Current Evidence / Status | I20: Net-Zero / ESG Link
B21: H&S policy — zero harm commitment | C21: 5.2 | D21: Partially Compliant | E21: =IF(D21="Fully Compliant",5,IF(D21="Partially Compliant",3,IF(D21="Not Applicable",5,0))) -> 3 | F21: 1 | G21: Board H&S policy | H21: Code of Ethics §7 (Labour Standards & Human Rights) commits to safe workplace; Supplier Code §7 requires OHS Act compliance and OHS management system from suppliers. | I21: Include fatigue policy
B22: Hazard identification (HIRA) — driver fatigue | C22: 6.1.2 | E22: =IF(D22="Fully Compliant",5,IF(D22="Partially Compliant",3,IF(D22="Not Applicable",5,0))) -> 0 | F22: 1 | G22: HIRA register | I22: Driver routes = key hazard
B23: Legal requirements — OHS Act, COID, Road Traffic | C23: 6.1.3 | D23: Partially Compliant | E23: =IF(D23="Fully Compliant",5,IF(D23="Partially Compliant",3,IF(D23="Not Applicable",5,0))) -> 3 | F23: 1 | G23: Legal register | H23: Supplier Code §7 enforces OHS Act compliance and incident notification; internal legal register to be confirmed. | I23: Quarterly update
B24: Operational controls — PPE, fatigue mgmt, vehicle checks | C24: 8.1 | E24: =IF(D24="Fully Compliant",5,IF(D24="Partially Compliant",3,IF(D24="Not Applicable",5,0))) -> 0 | F24: 1 | G24: SOPs per depot | I24: Driver debrief critical
B25: Emergency preparedness — road accidents | C25: 8.2 | E25: =IF(D25="Fully Compliant",5,IF(D25="Partially Compliant",3,IF(D25="Not Applicable",5,0))) -> 0 | F25: 1 | G25: Emergency plan | I25: All depots + fleet
B26: Monitoring — LTIFR, TRIFR, near-miss (Accidently) | C26: 9.1 | E26: =IF(D26="Fully Compliant",5,IF(D26="Partially Compliant",3,IF(D26="Not Applicable",5,0))) -> 0 | F26: 1 | G26: Accidently system | I26: Monthly reporting
B27: Incident investigation process | C27: 10.2 | E27: =IF(D27="Fully Compliant",5,IF(D27="Partially Compliant",3,IF(D27="Not Applicable",5,0))) -> 0 | F27: 1 | G27: Incident reports | I27: Within 24hrs of incident
B28: Worker participation and consultation | C28: 5.4 | E28: =IF(D28="Fully Compliant",5,IF(D28="Partially Compliant",3,IF(D28="Not Applicable",5,0))) -> 0 | F28: 1 | G28: Safety committee minutes | I28: Monthly meetings
B29: ISO 45001 certification achieved | C29: 10 | E29: =IF(D29="Fully Compliant",5,IF(D29="Partially Compliant",3,IF(D29="Not Applicable",5,0))) -> 0 | F29: 1 | G29: Certificate | I29: Target: confirm timeline
B30: ISO 45001:2018 Score | E30: =SUM(E21,E22,E23,E24,E25,E26,E27,E28,E29) -> 6
A32: ISO 27001:2022 — Information Security Management System
B33: Requirement | C33: Clause | D33: Status | E33: Score /5 | F33: Weight | G33: Evidence Needed | H33: Current Evidence / Status | I33: Net-Zero / ESG Link
B34: Information security policy | C34: 5.2 | D34: Partially Compliant | E34: =IF(D34="Fully Compliant",5,IF(D34="Partially Compliant",3,IF(D34="Not Applicable",5,0))) -> 3 | F34: 1 | G34: IS policy | H34: Code of Ethics §6 — Protection of Company Property: IP, confidential info, POPI Act compliance. Standalone Information Security policy to be confirmed. | I34: POPIA-aligned
B35: POPIA Information Officer appointed | C35: 6.1 | D35: Partially Compliant | E35: =IF(D35="Fully Compliant",5,IF(D35="Partially Compliant",3,IF(D35="Not Applicable",5,0))) -> 3 | F35: 1 | G35: Appointment letter | H35: POPI consent process active for SG Consumer (Jan 2026 letter); formal Information Officer appointment letter required. | I35: Companies Act s55
B36: Information asset register | C36: 8.1 | E36: =IF(D36="Fully Compliant",5,IF(D36="Partially Compliant",3,IF(D36="Not Applicable",5,0))) -> 0 | F36: 1 | G36: Asset register | I36: Include fleet telematics data
B37: Access controls — Cority, JDE, telematics systems | C37: 8.5.3 | E37: =IF(D37="Fully Compliant",5,IF(D37="Partially Compliant",3,IF(D37="Not Applicable",5,0))) -> 0 | F37: 1 | G37: Access policy | I37: Role-based access
B38: Incident response plan — data breach | C38: 8.6 | D38: Partially Compliant | E38: =IF(D38="Fully Compliant",5,IF(D38="Partially Compliant",3,IF(D38="Not Applicable",5,0))) -> 3 | F38: 1 | G38: Incident response plan | H38: POPI Act compliance referenced (Code of Ethics §6); 72hr breach notification protocol per POPIA to be formalised. | I38: 72hr notification POPIA
B39: Supplier agreements — data processing | C39: 8.7 | D39: Partially Compliant | E39: =IF(D39="Fully Compliant",5,IF(D39="Partially Compliant",3,IF(D39="Not Applicable",5,0))) -> 3 | F39: 1 | G39: DPA agreements | H39: Supplier Code §5 — supplier confidentiality and information protection obligations cascaded. | I39: All SaaS suppliers
B40: Risk assessment — cyber risks | C40: 6.1.2 | E40: =IF(D40="Fully Compliant",5,IF(D40="Partially Compliant",3,IF(D40="Not Applicable",5,0))) -> 0 | F40: 1 | G40: Cyber risk register | I40: Annual assessment
B41: ISO 27001 certification | C41: 10 | E41: =IF(D41="Fully Compliant",5,IF(D41="Partially Compliant",3,IF(D41="Not Applicable",5,0))) -> 0 | F41: 1 | G41: Certificate | I41: Target: confirm timeline
B42: ISO 27001:2022 Score | E42: =SUM(E34,E35,E36,E37,E38,E39,E40,E41) -> 12
A44: ISO 26000:2010 — Social Responsibility Guidance
B45: Requirement | C45: Clause | D45: Status | E45: Score /5 | F45: Weight | G45: Evidence Needed | H45: Current Evidence / Status | I45: Net-Zero / ESG Link
B46: Organisational governance — board accountability | C46: P1 | D46: Partially Compliant | E46: =IF(D46="Fully Compliant",5,IF(D46="Partially Compliant",3,IF(D46="Not Applicable",5,0))) -> 3 | F46: 1 | G46: Board charter | H46: Code of Ethics — board-approved code; Executive Committee approval; multiple committee structures (S&EC, Internal Audit). | I46: King V P1 aligned
B47: Human rights — due diligence | C47: P2 | D47: Partially Compliant | E47: =IF(D47="Fully Compliant",5,IF(D47="Partially Compliant",3,IF(D47="Not Applicable",5,0))) -> 3 | F47: 1 | G47: HR policy | H47: Code of Ethics §7 (Labour Standards & Human Rights): dignity, fair treatment, no harassment, forced labour & child labour prohibitions, freedom of association, anti-discrimination, fair employment, community land rights. | I47: Labour Relations Act
B48: Labour practices — fair wages, EE, training | C48: P3 | D48: Fully Compliant | E48: =IF(D48="Fully Compliant",5,IF(D48="Partially Compliant",3,IF(D48="Not Applicable",5,0))) -> 5 | F48: 1 | G48: HR policies, WSP | H48: EE Policy (Rev 2, 30 Jan 2023) — designated employer, EEA Chapter 3 compliance, EE Plan, EE Committees, reasonable accommodation, career advancement, learning & development; equal pay for equal value; workplace harassment policy. | I48: EEA + BCEA aligned
B49: Environment — net-zero, waste, water | C49: P4 | D49: Partially Compliant | E49: =IF(D49="Fully Compliant",5,IF(D49="Partially Compliant",3,IF(D49="Not Applicable",5,0))) -> 3 | F49: 1 | G49: E_Data, E_Scorecard | H49: Code of Ethics §11 — environmental commitments (GHG, energy, water, waste, biodiversity, noise); Supplier Code §8 cascades to supply chain. | I49: ISO 14001 aligned
B50: Fair operating practices — anti-corruption | C50: P5 | D50: Fully Compliant | E50: =IF(D50="Fully Compliant",5,IF(D50="Partially Compliant",3,IF(D50="Not Applicable",5,0))) -> 5 | F50: 1 | G50: Ethics policy | H50: Code of Ethics §8 — zero-tolerance bribery/corruption; Be Heard hotline 0800-007-117; Internal Audit active; PRECCA + FICA references; Supplier Code §5 cascades. | I50: PRECCA compliance
B51: Consumer issues — cold chain quality | C51: P6 | E51: =IF(D51="Fully Compliant",5,IF(D51="Partially Compliant",3,IF(D51="Not Applicable",5,0))) -> 0 | F51: 1 | G51: Quality procedures | I51: ISO 22000 aligned
B52: Community development — CSI, SED | C52: P7 | D52: Fully Compliant | E52: =IF(D52="Fully Compliant",5,IF(D52="Partially Compliant",3,IF(D52="Not Applicable",5,0))) -> 5 | F52: 1 | G52: Social calendar | H52: CSI/SED Policy (Rev 2, 30 Jan 2023) — formal three-pronged approach; SED 1% NPAT, CSI ≤0.25% NPAT; 75% Black beneficiary requirement (B-BBEE aligned); priority areas: income/jobs, infrastructure, training/mentoring. | I52: B-BBEE SED criteria
B53: ISO 26000:2010 Score | E53: =SUM(E46,E47,E48,E49,E50,E51,E52) -> 24
A55: ISO 22000:2018 — Food Safety Management (Cold Chain)
B56: Requirement | C56: Clause | D56: Status | E56: Score /5 | F56: Weight | G56: Evidence Needed | H56: Current Evidence / Status | I56: Net-Zero / ESG Link
B57: Food safety policy — cold chain integrity | C57: 5.2 | E57: =IF(D57="Fully Compliant",5,IF(D57="Partially Compliant",3,IF(D57="Not Applicable",5,0))) -> 0 | F57: 1 | G57: Food safety policy | I57: FSMS for chilled goods
B58: HACCP plan — temperature control | C58: 8.5 | E58: =IF(D58="Fully Compliant",5,IF(D58="Partially Compliant",3,IF(D58="Not Applicable",5,0))) -> 0 | F58: 1 | G58: HACCP document | I58: Fridge units — 500hr service
B59: Prerequisite programmes — hygiene, pest control | C59: 8.2 | E59: =IF(D59="Fully Compliant",5,IF(D59="Partially Compliant",3,IF(D59="Not Applicable",5,0))) -> 0 | F59: 1 | G59: PRP records | I59: All depot warehouses
B60: Fridge unit maintenance (Transfrig) | C60: 8.6 | E60: =IF(D60="Fully Compliant",5,IF(D60="Partially Compliant",3,IF(D60="Not Applicable",5,0))) -> 0 | F60: 1 | G60: Service records | I60: Service intervals Fleet_Register
B61: Food safety training — drivers and warehouse | C61: 7.2 | E61: =IF(D61="Fully Compliant",5,IF(D61="Partially Compliant",3,IF(D61="Not Applicable",5,0))) -> 0 | F61: 1 | G61: Training records | I61: Annual minimum
B62: Traceability system — batch/load tracking | C62: 8.9.2 | E62: =IF(D62="Fully Compliant",5,IF(D62="Partially Compliant",3,IF(D62="Not Applicable",5,0))) -> 0 | F62: 1 | G62: Tracking records | I62: I-CAM / Cellulant system
B63: Emergency preparedness — temperature exceedance | C63: 8.4 | E63: =IF(D63="Fully Compliant",5,IF(D63="Partially Compliant",3,IF(D63="Not Applicable",5,0))) -> 0 | F63: 1 | G63: Emergency plan | I63: Cold chain failure protocol
B64: ISO 22000:2018 Score | E64: =SUM(E57,E58,E59,E60,E61,E62,E63) -> 0

Sheet SAQ_Supplier
A1: SUPPLIER ESG ASSESSMENT | IMS-T-149-02 | JDE Environmental SAQ | Sanulac Sustainability [Source: MARIA + MAXINE]
A3: IMS-T-149-02 — EXTERNAL SERVICE PROVIDER EVALUATIONS (Score 1–5 per criterion; Rating A>90%, B>80%, C<80%)
A4: Supplier Name | B4: On-Time Del | C4: Quality | D4: H&S (Safety File) | E4: Environmental (EMS/Waste/Spill) | F4: Food Safety (COA/Policy) | G4: Correct Invoicing | H4: Backup Support | I4: % Score | J4: Rating | K4: ESG Net-Zero Link
A5: Fuel Supplier — ENGEN (BLOEM) | B5: 3 | C5: 3 | D5: 3 | E5: 3 | F5: 3 | G5: 3 | H5: 3 | I5: =IFERROR(SUM(B5:H5)/(COUNTIF(B5:H5,"<>"&"N/A")*5)*100,0) -> 60 | J5: =IF(I5>=90,"A",IF(I5>=80,"B","C")) -> C | K5: LPG/diesel Scope 1
A6: Electricity Landlord — KAVOD (BLOEM) | B6: 3 | C6: 3 | D6: 3 | E6: 3 | F6: 3 | G6: 3 | H6: 3 | I6: =IFERROR(SUM(B6:H6)/(COUNTIF(B6:H6,"<>"&"N/A")*5)*100,0) -> 60 | J6: =IF(I6>=90,"A",IF(I6>=80,"B","C")) -> C | K6: Scope 2 electricity
A7: Electricity Landlord — EXCELLERATE (DBN) | B7: 3 | C7: 3 | D7: 3 | E7: 3 | F7: 3 | G7: 3 | H7: 3 | I7: =IFERROR(SUM(B7:H7)/(COUNTIF(B7:H7,"<>"&"N/A")*5)*100,0) -> 60 | J7: =IF(I7>=90,"A",IF(I7>=80,"B","C")) -> C | K7: Scope 2 electricity
A8: Electricity Landlord — LEXSHELL (ISANDO) | B8: 3 | C8: 3 | D8: 3 | E8: 3 | F8: 3 | G8: 3 | H8: 3 | I8: =IFERROR(SUM(B8:H8)/(COUNTIF(B8:H8,"<>"&"N/A")*5)*100,0) -> 60 | J8: =IF(I8>=90,"A",IF(I8>=80,"B","C")) -> C | K8: Scope 2 electricity
A9: Waste Contractor — Oricol Environmental | B9: 3 | C9: 3 | D9: 3 | E9: 3 | F9: 3 | G9: 3 | H9: 3 | I9: =IFERROR(SUM(B9:H9)/(COUNTIF(B9:H9,"<>"&"N/A")*5)*100,0) -> 60 | J9: =IF(I9>=90,"A",IF(I9>=80,"B","C")) -> C | K9: Waste diversion/Scope 3
A10: Fleet Maintenance — Hino/Scania dealer | B10: 3 | C10: 3 | D10: 3 | E10: 3 | F10: 3 | G10: 3 | H10: 3 | I10: =IFERROR(SUM(B10:H10)/(COUNTIF(B10:H10,"<>"&"N/A")*5)*100,0) -> 60 | J10: =IF(I10>=90,"A",IF(I10>=80,"B","C")) -> C | K10: Fleet efficiency/Scope 1
A11: Telematics — I-CAM / Mix Telematics | B11: 3 | C11: 3 | D11: 3 | E11: 3 | F11: 3 | G11: 3 | H11: 3 | I11: =IFERROR(SUM(B11:H11)/(COUNTIF(B11:H11,"<>"&"N/A")*5)*100,0) -> 60 | J11: =IF(I11>=90,"A",IF(I11>=80,"B","C")) -> C | K11: Fleet data quality
A12: Safety System — Accidently | B12: 3 | C12: 3 | D12: 3 | E12: 3 | F12: 3 | G12: 3 | H12: 3 | I12: =IFERROR(SUM(B12:H12)/(COUNTIF(B12:H12,"<>"&"N/A")*5)*100,0) -> 60 | J12: =IF(I12>=90,"A",IF(I12>=80,"B","C")) -> C | K12: LTIFR data/ISO 45001
A13: EV Supplier — MAXUS (planned) | B13: 3 | C13: 3 | D13: 3 | E13: 3 | F13: 3 | G13: 3 | H13: 3 | I13: =IFERROR(SUM(B13:H13)/(COUNTIF(B13:H13,"<>"&"N/A")*5)*100,0) -> 60 | J13: =IF(I13>=90,"A",IF(I13>=80,"B","C")) -> C | K13: EV transition/net-zero
A14: Cold Chain — Transfrig (fridge units) | B14: 3 | C14: 3 | D14: 3 | E14: 3 | F14: 3 | G14: 3 | H14: 3 | I14: =IFERROR(SUM(B14:H14)/(COUNTIF(B14:H14,"<>"&"N/A")*5)*100,0) -> 60 | J14: =IF(I14>=90,"A",IF(I14>=80,"B","C")) -> C | K14: Cold chain food safety
A15: JDE (warehousing client) | B15: 3 | C15: 3 | D15: 3 | E15: 3 | F15: 3 | G15: 3 | H15: 3 | I15: =IFERROR(SUM(B15:H15)/(COUNTIF(B15:H15,"<>"&"N/A")*5)*100,0) -> 60 | J15: =IF(I15>=90,"A",IF(I15>=80,"B","C")) -> C | K15: Client ESG SAQ requirements
A16: Sanulac/Lactalis (FMCG client) | B16: 3 | C16: 3 | D16: 3 | E16: 3 | F16: 3 | G16: 3 | H16: 3 | I16: =IFERROR(SUM(B16:H16)/(COUNTIF(B16:H16,"<>"&"N/A")*5)*100,0) -> 60 | J16: =IF(I16>=90,"A",IF(I16>=80,"B","C")) -> C | K16: Client sustainability reporting
A18: SANULAC / LACTALIS SUSTAINABILITY DATA [Source: Maxine/Sanulac Sustainability report.xlsx]
A19: Depot | B19: Period | C19: Elec kWh | D19: Rate R/kWh | E19: Solar | F19: Solar Owner | G19: Generator | H19: Forklift Type | I19: Lithium # | J19: Lead-acid # | K19: Fuel Tank L
A20: Gauteng (JHB) | B20: H1 2025 | C20: 5701 | D20: 3.97 | E20: Yes | F20: SG-owned | G20: Yes (diesel) | H20: Electric (Li) | I20: 19 | J20: 40 | K20: 83000
A21: Gauteng (JHB) | B21: H2 2025 | C21: 4712 | D21: 4.33 | E21: Yes | F21: SG-owned | G21: Yes (diesel) | H21: Electric (Li) | I21: 21 | J21: 40 | K21: 83000
A22: Cape Town | B22: H1 2025 | C22: 646 | D22: 2.24 | E22: Yes | F22: Landlord (SPEAR) | G22: Yes (diesel) | H22: Electric (Li) | I22: 3 | J22: 9 | K22: 0
A23: Cape Town | B23: H2 2025 | C23: 510 | D23: 2.75 | E23: Yes | F23: Landlord (SPEAR) | G23: Yes (diesel) | H23: Electric (Li) | I23: 3 | J23: 9 | K23: 0
A24: Port Elizabeth | B24: H1 2025 | C24: 0 | D24: 3.36 | E24: None | F24: — | G24: Yes (diesel) | H24: Electric (Li) | I24: 2 | J24: 6 | K24: 0
A25: Durban | B25: H1 2025 | C25: 0 | D25: 5.53 | E25: None | F25: — | G25: Yes (diesel) | H25: Electric (Li) | I25: 4 | J25: 8 | K25: 0
A26: Bloemfontein | B26: H1 2025 | C26: 0 | D26: 5.87 | E26: None | F26: — | G26: Yes (diesel) | H26: Electric (Li) | I26: 3 | J26: 3 | K26: 13000
A28: JDE ENVIRONMENTAL SAQ — Key Questions [Source: Maxine/JDE/ENVIRONMENTAL Q AND A.xlsx]
A29: SAQ Question | B29: Category | C29: Response | I29: Score
A30: Formalised Environmental policy in place? | B30: Policy | C30: Yes — company-wide policy | I30: 5
A31: GHG/Energy reduction targets set? | B31: Commitments | C31: Yes — SBTi CNZS 2.0 net-zero by 2050 | I31: 5
A32: Water reduction targets? | B32: Commitments | C32: Yes — CT dam project; DBN monitoring | I32: 4
A33: Waste reduction/diversion targets? | B33: Commitments | C33: Yes — Oricol 91% diversion rate (Mar-26) | I33: 5
A34: ISO 14001 certified? | B34: Management | C34: In progress — target date TBC with Maria | I34: 2
A35: GHG measurement methodology? | B35: Measurement | C35: DEFRA 2024 / Eskom NERSA 2024 emission factors | I35: 5
A36: Physical climate risks experienced? | B36: Climate | C36: Yes — Durban floods 2022, heat impact on drivers | I36: 4
A37: Transition plan for net-zero? | B37: Transition | C37: Yes — SBTi CNZS 2.0, EV fleet plan, solar expansion | I37: 4
A38: Biodiversity policy? | B38: Policy | C38: Under development | I38: 1
A39: Chemicals/spill control procedures? | B39: Operations | C39: Yes — depot spill kits, emergency response plans | I39: 4
A41: SUPPLIER CODE OF CONDUCT — Control Framework
A42: Document | B42: Super Group Supplier Code of Conduct and Ethics (Rev 2, 30 Jan 2023) | J42: Public
A43: Coverage | B43: Labour & Human Rights · Business Ethics & Integrity · Health & Safety · Environment & Sustainability
A44: Whistleblower | B44: Be Heard hotline 0800-007-117 — available to suppliers, employees and contractors (24/365 anonymous)
A45: Enforcement | B45: SG reserves right to terminate non-compliant suppliers; mandatory self-reporting of breaches
A46: B-BBEE certificate | B46: All suppliers must hold valid B-BBEE certificate or affidavit (Supplier Code §6)

Sheet NetZero_Roadmap
A1: NET-ZERO ROADMAP — SBTi CNZS 2.0 | OER Tiers | 2030/2040/2050 Milestones [Links: E_Data GHG actual]
A3: SBTi CNZS 2.0 — SCIENCE-BASED TARGETS (Corporate Net-Zero Standard)
A4: Scope / Metric | B4: Baseline | C4: 2025 | D4: 2026 | E4: 2027 | F4: 2028 | G4: 2029 | H4: 2030 | I4: 2035 | J4: 2040 | K4: 2045 | L4: 2050 | M4: Net-Zero By 2050
A5: Scope 1+2 tCO₂e (baseline → 2050) | B5: 0 | C5: =IFERROR(B5*(1-0),0) -> 0 | D5: =IFERROR(B5*(1-0.05),0) -> 0 | E5: =IFERROR(B5*(1-0.12),0) -> 0 | F5: =IFERROR(B5*(1-0.2),0) -> 0 | G5: =IFERROR(B5*(1-0.35),0) -> 0 | H5: =IFERROR(B5*(1-0.5),0) -> 0 | I5: =IFERROR(B5*(1-0.65),0) -> 0 | J5: =IFERROR(B5*(1-0.78),0) -> 0 | K5: =IFERROR(B5*(1-0.9),0) -> 0 | L5: =IFERROR(B5*(1-0.95),0) -> 0 | M5: Link to E_Data GHG total
A6: Scope 1 — Fleet + Gen + LPG | B6: 0 | C6: =IFERROR(B6*(1-0),0) -> 0 | D6: =IFERROR(B6*(1-0.05),0) -> 0 | E6: =IFERROR(B6*(1-0.12),0) -> 0 | F6: =IFERROR(B6*(1-0.2),0) -> 0 | G6: =IFERROR(B6*(1-0.35),0) -> 0 | H6: =IFERROR(B6*(1-0.5),0) -> 0 | I6: =IFERROR(B6*(1-0.65),0) -> 0 | J6: =IFERROR(B6*(1-0.78),0) -> 0 | K6: =IFERROR(B6*(1-0.9),0) -> 0 | L6: =IFERROR(B6*(1-0.95),0) -> 0 | M6: EV fleet transition key lever
A7: Scope 2 Net — Electricity (grid-solar) | B7: 0 | C7: =IFERROR(B7*(1-0),0) -> 0 | D7: =IFERROR(B7*(1-0.05),0) -> 0 | E7: =IFERROR(B7*(1-0.12),0) -> 0 | F7: =IFERROR(B7*(1-0.2),0) -> 0 | G7: =IFERROR(B7*(1-0.35),0) -> 0 | H7: =IFERROR(B7*(1-0.5),0) -> 0 | I7: =IFERROR(B7*(1-0.65),0) -> 0 | J7: =IFERROR(B7*(1-0.78),0) -> 0 | K7: =IFERROR(B7*(1-0.9),0) -> 0 | L7: =IFERROR(B7*(1-0.95),0) -> 0 | M7: Solar expansion at all depots
A8: Scope 3 tCO₂e (30% by 2030) | B8: 0 | C8: =IFERROR(B8*(1-0),0) -> 0 | D8: =IFERROR(B8*(1-0.05),0) -> 0 | E8: =IFERROR(B8*(1-0.1),0) -> 0 | F8: =IFERROR(B8*(1-0.15),0) -> 0 | G8: =IFERROR(B8*(1-0.22),0) -> 0 | H8: =IFERROR(B8*(1-0.3),0) -> 0 | I8: =IFERROR(B8*(1-0.45),0) -> 0 | J8: =IFERROR(B8*(1-0.6),0) -> 0 | K8: =IFERROR(B8*(1-0.75),0) -> 0 | L8: =IFERROR(B8*(1-0.9),0) -> 0 | M8: Water, value chain, business travel
A9: Carbon Credits / Offsets (OER) | B9: 0 | C9: =IFERROR(B9*(1-0),0) -> 0 | D9: =IFERROR(B9*(1-0),0) -> 0 | E9: =IFERROR(B9*(1-0),0) -> 0 | F9: =IFERROR(B9*(1-0),0) -> 0 | G9: =IFERROR(B9*(1-0),0) -> 0 | H9: =IFERROR(B9*(1-0),0) -> 0 | I9: =IFERROR(B9*(1-0),0) -> 0 | J9: =IFERROR(B9*(1-0),0) -> 0 | K9: =IFERROR(B9*(1-0),0) -> 0 | L9: =IFERROR(B9*(1-0),0) -> 0 | M9: OER Pre-recognised → Recognised 2028
A11: OER TIER MILESTONES — SBTi CNZS 2.0 OER (Ongoing Emissions Reductions)
A12: Tier | B12: Target Year | C12: GHG Requirement | D12: Key Initiative | E12: Carbon Credits | F12: SG Consumer Action
A13: Pre-Recognised (Current) | B13: 2025 | C13: Commit to SBTi near-term target | D13: Submit SBTi commitment letter | E13: Any | F13: Baseline established: FY2025/26
A14: Recognised | B14: 2028 | C14: −50% Scope 1+2 from baseline | D14: EV fleet phase-in; solar expansion | E14: Carbon credits optional | F14: KPI: 50% S1+2 reduction from baseline
A15: Leadership | B15: 2035 | C15: −90% Scope 1+2 + 30% S3 + residual offsets | D15: Full EV fleet; 100% renewable energy | E15: High-quality carbon credits for residual | F15: Publish net-zero report
A16: Net-Zero | B16: 2050 | C16: Net-Zero across Scope 1+2+3 | D16: Zero fossil fleet; all renewable | E16: Only residual credits allowed | F16: Legacy net-zero organisation
A18: KEY NET-ZERO LEVERS — SG Consumer Action Plan
A19: Lever | B19: Action | C19: Data Sheet | D19: Target | E19: Timeline | F19: Owner
A20: EV Fleet Transition | B20: MAXUS eDeliver 3/5 — CPT & PE urban routes first | C20: Fleet_Register | D20: 20% EV by 2030 | E20: FY2026/27 | F20: Maxine / Fleet Mgr
A21: Solar Expansion | B21: JHB Graeme Barand confirmed; DBN EDGE cert pending; CPT/BLOEM/PE to assess | C21: E_Data Solar | D21: 50% renewable by 2030 | E21: FY2025/26 | F21: Graeme Barand / Ops
A22: Eco-Driving Training | B22: Reduce fleet L/100km by 10% via driver training | C22: Fleet_Register | D22: L/100km ≤ norm | E22: Q3 FY2025 | F22: WSP training plan
A23: Waste Diversion | B23: Extend Oricol CPT 91% diversion to all depots | C23: Waste_Register | D23: ≥75% all depots | E23: FY2026 | F23: Mariette / SHEQ
A24: Water Conservation | B24: CT dam project; DBN 20kL mezzanine; IE monitoring | C24: E_Data Water | D24: Reduce 10% YoY | E24: Ongoing | F24: Mariette / Richard
A25: Generator Replacement | B25: DBN & BLOEM generators → solar/UPS | C25: E_Data Gen | D25: Zero generator by 2030 | E25: FY2028 | F25: Facilities
A26: SBTi Commitment | B26: Submit near-term targets commitment letter | C26: IFRS_S1_S2 | D26: Submitted 2026 | E26: Q1 FY2026 | F26: Richard / Okiru
A27: Carbon Credits Register | B27: EDGE DBN credit + solar JHB credit tracking | C27: Carbon_Credits_Register | D27: OER Recognised 2028 | E27: FY2027 | F27: Okiru Consulting

Sheet B_BBEE_ESG
A1: ⚖ B-BBEE GENERIC CODE — ESG ELEMENT MAPPING | Statement 000 Series
A2: Generic Scorecard (Statement 000): 109 points + 5 bonus = 114 total. Auto-pulled from E/S/G data where possible. Status level driven by total points.
A4: GENERIC SCORECARD — 5 elements
A5: Element | B5: Weight | C5: Sub-target | D5: Actual | E5: Points Earned | F5: Source / Logic | G5: ESG Pillar
A6: OWNERSHIP (Statement 100) | B6: 25 | C6: ≥25.1% Black ownership | D6: 0 | E6: =IFERROR(IF(D6>=0.251,25,IF(D6>=0.251*Assumptions!$B$9,25*D6/0.251,0)),0) -> 0 | F6: Manual entry — confirm with share register / Modified Flow-Through | G6: Governance | H6: =B6-E6 -> 25
A7: MANAGEMENT CONTROL (Statement 200) | B7: 19 | C7: Black 60% / Black Female 30% | D7: =IFERROR(EE_Scorecard!E15/100,0) -> 0.35 | E7: =IFERROR(D7*19,0) -> 6.65 | F7: EE_Scorecard E15 total/100 × 19 pts (weighted scorecard already aligned) | G7: Social | H7: =B7-E7 -> 12.35
A8: SKILLS DEVELOPMENT (Statement 300) | B8: 25 | C8: 6% payroll spend on Black training | D8: =IFERROR(S_Data!B50/MAX(1,S_Data!B43),0) -> 0 | E8: =IFERROR(IF(D8>=0.06,25,IF(D8>=0.06*Assumptions!$B$9,25*D8/0.06,0)),0) -> 0 | F8: Training spend (S_Data B50) ÷ Leviable payroll (B43); target 6% | G8: Social | H8: =B8-E8 -> 25
A9: ENTERPRISE & SUPPLIER DEVELOPMENT (Statement 400) | B9: 40 | C9: PP 25 + ESD 15 sub-targets | D9: 0 | E9: =IFERROR(D9*40,0) -> 0 | F9: Manual entry — % recognition vs PP 25 + ESD 15 sub-targets | G9: Social / Governance | H9: =B9-E9 -> 40
A10: SOCIO-ECONOMIC DEVELOPMENT (Statement 500) | B10: 5 | C10: 1% NPAT contribution | D10: 0 | E10: =IFERROR(IF(D10>=Assumptions!$B$56,5,IF(D10>=Assumptions!$B$56*Assumptions!$B$9,5*D10/Assumptions!$B$56,0)),0) -> 0 | F10: CSI spend ÷ NPAT; target 1% (THR_CSI) | G10: Social | H10: =B10-E10 -> 5
A11: BONUS POINTS (net job creation, value-adding) | B11: 5 | C11: Up to 5 bonus pts | D11: 0 | E11: =MIN(5,D11) -> 0 | F11: Manual — claim up to 5 bonus points (net job creation / value-add) | G11: — | H11: =B11-E11 -> 5
A12: TOTAL POINTS | B12: =SUM(B6:B11) -> 119 | E12: =SUM(E6:E11) -> 6.65
A14: STATUS LEVEL — Auto-determined from total points
A15: Current Level | B15: =IF(E12>=Assumptions!$B$76,"Level 1",IF(E12>=Assumptions!$B$77,"Level 2",IF(E12>=Assumptions!$B$78,"Level 3",IF(E12>=Assumptions!$B$79,"Level 4",IF(E12>=Assumptions!$B$80,"Level 5",IF(E12>=Assumptions!$B$81,"Level 6",IF(E12>=Assumptions!$B$82,"Level 7",IF(E12>=Assumptions!$B$83,"Level 8","Non-compliant")))))))) -> Level 4 | D15: Procurement Recognition | E15: =IF(E12>=Assumptions!$B$76,Assumptions!$C$76,IF(E12>=Assumptions!$B$77,Assumptions!$C$77,IF(E12>=Assumptions!$B$78,Assumptions!$C$78,IF(E12>=Assumptions!$B$79,Assumptions!$C$79,IF(E12>=Assumptions!$B$80,Assumptions!$C$80,IF(E12>=Assumptions!$B$81,Assumptions!$C$81,IF(E12>=Assumptions!$B$82,Assumptions!$C$82,IF(E12>=Assumptions!$B$83,Assumptions!$C$83,Assumptions!$C$84)))))))) -> 0
A17: GAP TO NEXT LEVEL
A18: Points to next level | B18: =IF(E12>=Assumptions!$B$76,0,IF(E12>=Assumptions!$B$77,Assumptions!$B$76-E12,IF(E12>=Assumptions!$B$78,Assumptions!$B$77-E12,IF(E12>=Assumptions!$B$79,Assumptions!$B$78-E12,IF(E12>=Assumptions!$B$80,Assumptions!$B$79-E12,IF(E12>=Assumptions!$B$81,Assumptions!$B$80-E12,IF(E12>=Assumptions!$B$82,Assumptions!$B$81-E12,IF(E12>=Assumptions!$B$83,Assumptions!$B$82-E12,Assumptions!$B$83-E12)))))))) -> 83.35 | D18: Biggest opportunity | E18: =INDEX(A6:A11,MATCH(MAX(H6:H11),H6:H11,0)) -> ENTERPRISE & SUPPLIER DEVELOPMENT (Statement 400)

Sheet Materiality_Matrix
A1: 🎯 MATERIALITY MATRIX — Impact × Likelihood | Auto-fed from GARP_GRAP risks
A2: Double materiality basis (IFRS S1/S2 + ESRS): financial impact AND impact on environment/society. Change "Materiality basis" toggle in Assumptions B10 to switch between Single/Double/Dynamic.
A4: SECTION 1 — Material risks (auto-pulled from GARP_GRAP)
A5: Risk | B5: Severity | C5: Likelihood | D5: Financial Impact | E5: Impact on E/S | F5: Material Score | G5: Mitigation Priority
A6: =GARP_GRAP!B5 -> Climate Physical Risk | B6: =GARP_GRAP!E5 -> High | C6: =GARP_GRAP!I5 -> 4 | D6: 3 | E6: 3 | F6: =IFERROR(IF(Assumptions!$B$12="Single (financial — IFRS)",IF(B6="High",5,IF(B6="Medium",3,IF(B6="Low",1,IF(B6="Req",4,0))))*C6*D6/5,IF(Assumptions!$B$12="Double (financial + impact — ESRS)",IF(B6="High",5,IF(B6="Medium",3,IF(B6="Low",1,IF(B6="Req",4,0))))*C6*MAX(D6,E6)/5,IF(B6="High",5,IF(B6="Medium",3,IF(B6="Low",1,IF(B6="Req",4,0))))*C6*((D6+E6)/2)/5)),0) -> 12 | G6: =IF(F6>=15,"🔴 Critical — board agenda",IF(F6>=10,"🟠 High — quarterly review",IF(F6>=5,"🟡 Monitor — annual review","🟢 Low — register only"))) -> 🟠 High — quarterly review
A7: =GARP_GRAP!B6 -> Climate Transition Risk | B7: =GARP_GRAP!E6 -> High | C7: =GARP_GRAP!I6 -> 5 | D7: 3 | E7: 3 | F7: =IFERROR(IF(Assumptions!$B$12="Single (financial — IFRS)",IF(B7="High",5,IF(B7="Medium",3,IF(B7="Low",1,IF(B7="Req",4,0))))*C7*D7/5,IF(Assumptions!$B$12="Double (financial + impact — ESRS)",IF(B7="High",5,IF(B7="Medium",3,IF(B7="Low",1,IF(B7="Req",4,0))))*C7*MAX(D7,E7)/5,IF(B7="High",5,IF(B7="Medium",3,IF(B7="Low",1,IF(B7="Req",4,0))))*C7*((D7+E7)/2)/5)),0) -> 15 | G7: =IF(F7>=15,"🔴 Critical — board agenda",IF(F7>=10,"🟠 High — quarterly review",IF(F7>=5,"🟡 Monitor — annual review","🟢 Low — register only"))) -> 🔴 Critical — board agenda
A8: =GARP_GRAP!B7 -> Operational Risk — Fleet | B8: =GARP_GRAP!E7 -> High | C8: =GARP_GRAP!I7 -> 5 | D8: 3 | E8: 3 | F8: =IFERROR(IF(Assumptions!$B$12="Single (financial — IFRS)",IF(B8="High",5,IF(B8="Medium",3,IF(B8="Low",1,IF(B8="Req",4,0))))*C8*D8/5,IF(Assumptions!$B$12="Double (financial + impact — ESRS)",IF(B8="High",5,IF(B8="Medium",3,IF(B8="Low",1,IF(B8="Req",4,0))))*C8*MAX(D8,E8)/5,IF(B8="High",5,IF(B8="Medium",3,IF(B8="Low",1,IF(B8="Req",4,0))))*C8*((D8+E8)/2)/5)),0) -> 15 | G8: =IF(F8>=15,"🔴 Critical — board agenda",IF(F8>=10,"🟠 High — quarterly review",IF(F8>=5,"🟡 Monitor — annual review","🟢 Low — register only"))) -> 🔴 Critical — board agenda
A9: =GARP_GRAP!B8 -> Regulatory Risk — EE Act | B9: =GARP_GRAP!E8 -> Medium | C9: =GARP_GRAP!I8 -> 3 | D9: 3 | E9: 3 | F9: =IFERROR(IF(Assumptions!$B$12="Single (financial — IFRS)",IF(B9="High",5,IF(B9="Medium",3,IF(B9="Low",1,IF(B9="Req",4,0))))*C9*D9/5,IF(Assumptions!$B$12="Double (financial + impact — ESRS)",IF(B9="High",5,IF(B9="Medium",3,IF(B9="Low",1,IF(B9="Req",4,0))))*C9*MAX(D9,E9)/5,IF(B9="High",5,IF(B9="Medium",3,IF(B9="Low",1,IF(B9="Req",4,0))))*C9*((D9+E9)/2)/5)),0) -> 5.4 | G9: =IF(F9>=15,"🔴 Critical — board agenda",IF(F9>=10,"🟠 High — quarterly review",IF(F9>=5,"🟡 Monitor — annual review","🟢 Low — register only"))) -> 🟡 Monitor — annual review
A10: =GARP_GRAP!B9 -> Regulatory Risk — POPIA | B10: =GARP_GRAP!E9 -> Medium | C10: =GARP_GRAP!I9 -> 3 | D10: 3 | E10: 3 | F10: =IFERROR(IF(Assumptions!$B$12="Single (financial — IFRS)",IF(B10="High",5,IF(B10="Medium",3,IF(B10="Low",1,IF(B10="Req",4,0))))*C10*D10/5,IF(Assumptions!$B$12="Double (financial + impact — ESRS)",IF(B10="High",5,IF(B10="Medium",3,IF(B10="Low",1,IF(B10="Req",4,0))))*C10*MAX(D10,E10)/5,IF(B10="High",5,IF(B10="Medium",3,IF(B10="Low",1,IF(B10="Req",4,0))))*C10*((D10+E10)/2)/5)),0) -> 5.4 | G10: =IF(F10>=15,"🔴 Critical — board agenda",IF(F10>=10,"🟠 High — quarterly review",IF(F10>=5,"🟡 Monitor — annual review","🟢 Low — register only"))) -> 🟡 Monitor — annual review
A11: =GARP_GRAP!B10 -> Financial Risk — SDL/WSP | B11: =GARP_GRAP!E10 -> Medium | C11: =GARP_GRAP!I10 -> 3 | D11: 3 | E11: 3 | F11: =IFERROR(IF(Assumptions!$B$12="Single (financial — IFRS)",IF(B11="High",5,IF(B11="Medium",3,IF(B11="Low",1,IF(B11="Req",4,0))))*C11*D11/5,IF(Assumptions!$B$12="Double (financial + impact — ESRS)",IF(B11="High",5,IF(B11="Medium",3,IF(B11="Low",1,IF(B11="Req",4,0))))*C11*MAX(D11,E11)/5,IF(B11="High",5,IF(B11="Medium",3,IF(B11="Low",1,IF(B11="Req",4,0))))*C11*((D11+E11)/2)/5)),0) -> 5.4 | G11: =IF(F11>=15,"🔴 Critical — board agenda",IF(F11>=10,"🟠 High — quarterly review",IF(F11>=5,"🟡 Monitor — annual review","🟢 Low — register only"))) -> 🟡 Monitor — annual review
A12: =GARP_GRAP!B11 -> Reputational Risk — ESG | B12: =GARP_GRAP!E11 -> Medium | C12: =GARP_GRAP!I11 -> 3 | D12: 3 | E12: 3 | F12: =IFERROR(IF(Assumptions!$B$12="Single (financial — IFRS)",IF(B12="High",5,IF(B12="Medium",3,IF(B12="Low",1,IF(B12="Req",4,0))))*C12*D12/5,IF(Assumptions!$B$12="Double (financial + impact — ESRS)",IF(B12="High",5,IF(B12="Medium",3,IF(B12="Low",1,IF(B12="Req",4,0))))*C12*MAX(D12,E12)/5,IF(B12="High",5,IF(B12="Medium",3,IF(B12="Low",1,IF(B12="Req",4,0))))*C12*((D12+E12)/2)/5)),0) -> 5.4 | G12: =IF(F12>=15,"🔴 Critical — board agenda",IF(F12>=10,"🟠 High — quarterly review",IF(F12>=5,"🟡 Monitor — annual review","🟢 Low — register only"))) -> 🟡 Monitor — annual review
A13: =GARP_GRAP!B12 -> Environmental Risk — Waste | B13: =GARP_GRAP!E12 -> Low | C13: =GARP_GRAP!I12 -> 2 | D13: 3 | E13: 3 | F13: =IFERROR(IF(Assumptions!$B$12="Single (financial — IFRS)",IF(B13="High",5,IF(B13="Medium",3,IF(B13="Low",1,IF(B13="Req",4,0))))*C13*D13/5,IF(Assumptions!$B$12="Double (financial + impact — ESRS)",IF(B13="High",5,IF(B13="Medium",3,IF(B13="Low",1,IF(B13="Req",4,0))))*C13*MAX(D13,E13)/5,IF(B13="High",5,IF(B13="Medium",3,IF(B13="Low",1,IF(B13="Req",4,0))))*C13*((D13+E13)/2)/5)),0) -> 1.2 | G13: =IF(F13>=15,"🔴 Critical — board agenda",IF(F13>=10,"🟠 High — quarterly review",IF(F13>=5,"🟡 Monitor — annual review","🟢 Low — register only"))) -> 🟢 Low — register only
A14: =GARP_GRAP!B13 -> Supply Chain Risk | B14: =GARP_GRAP!E13 -> Medium | C14: =GARP_GRAP!I13 -> 4 | D14: 3 | E14: 3 | F14: =IFERROR(IF(Assumptions!$B$12="Single (financial — IFRS)",IF(B14="High",5,IF(B14="Medium",3,IF(B14="Low",1,IF(B14="Req",4,0))))*C14*D14/5,IF(Assumptions!$B$12="Double (financial + impact — ESRS)",IF(B14="High",5,IF(B14="Medium",3,IF(B14="Low",1,IF(B14="Req",4,0))))*C14*MAX(D14,E14)/5,IF(B14="High",5,IF(B14="Medium",3,IF(B14="Low",1,IF(B14="Req",4,0))))*C14*((D14+E14)/2)/5)),0) -> 7.2 | G14: =IF(F14>=15,"🔴 Critical — board agenda",IF(F14>=10,"🟠 High — quarterly review",IF(F14>=5,"🟡 Monitor — annual review","🟢 Low — register only"))) -> 🟡 Monitor — annual review
A15: =GARP_GRAP!B14 -> Technology Risk | B15: =GARP_GRAP!E14 -> Low | C15: =GARP_GRAP!I14 -> 2 | D15: 3 | E15: 3 | F15: =IFERROR(IF(Assumptions!$B$12="Single (financial — IFRS)",IF(B15="High",5,IF(B15="Medium",3,IF(B15="Low",1,IF(B15="Req",4,0))))*C15*D15/5,IF(Assumptions!$B$12="Double (financial + impact — ESRS)",IF(B15="High",5,IF(B15="Medium",3,IF(B15="Low",1,IF(B15="Req",4,0))))*C15*MAX(D15,E15)/5,IF(B15="High",5,IF(B15="Medium",3,IF(B15="Low",1,IF(B15="Req",4,0))))*C15*((D15+E15)/2)/5)),0) -> 1.2 | G15: =IF(F15>=15,"🔴 Critical — board agenda",IF(F15>=10,"🟠 High — quarterly review",IF(F15>=5,"🟡 Monitor — annual review","🟢 Low — register only"))) -> 🟢 Low — register only
A16: SECTION 2 — Compliance requirements (auto-pulled from GARP_GRAP GRAP block)
A17: Risk | B17: Severity | C17: Likelihood | D17: Financial Impact | E17: Impact on E/S | F17: Material Score | G17: Mitigation Priority
A18: =GARP_GRAP!B17 -> Public interest score ≥500 points | B18: =GARP_GRAP!E17 -> Req | C18: =GARP_GRAP!I17 -> 3 | D18: 4 | E18: 3 | F18: =IFERROR(IF(Assumptions!$B$12="Single (financial — IFRS)",IF(B18="High",5,IF(B18="Medium",3,IF(B18="Low",1,IF(B18="Req",4,0))))*C18*D18/5,IF(Assumptions!$B$12="Double (financial + impact — ESRS)",IF(B18="High",5,IF(B18="Medium",3,IF(B18="Low",1,IF(B18="Req",4,0))))*C18*MAX(D18,E18)/5,IF(B18="High",5,IF(B18="Medium",3,IF(B18="Low",1,IF(B18="Req",4,0))))*C18*((D18+E18)/2)/5)),0) -> 9.6 | G18: =IF(F18>=15,"🔴 Critical — board agenda",IF(F18>=10,"🟠 High — quarterly review",IF(F18>=5,"🟡 Monitor — annual review","🟢 Low — register only"))) -> 🟡 Monitor — annual review
A19: =GARP_GRAP!B18 -> Social & Ethics Committee (S&EC) | B19: =GARP_GRAP!E18 -> Req | C19: =GARP_GRAP!I18 -> 3 | D19: 4 | E19: 3 | F19: =IFERROR(IF(Assumptions!$B$12="Single (financial — IFRS)",IF(B19="High",5,IF(B19="Medium",3,IF(B19="Low",1,IF(B19="Req",4,0))))*C19*D19/5,IF(Assumptions!$B$12="Double (financial + impact — ESRS)",IF(B19="High",5,IF(B19="Medium",3,IF(B19="Low",1,IF(B19="Req",4,0))))*C19*MAX(D19,E19)/5,IF(B19="High",5,IF(B19="Medium",3,IF(B19="Low",1,IF(B19="Req",4,0))))*C19*((D19+E19)/2)/5)),0) -> 9.6 | G19: =IF(F19>=15,"🔴 Critical — board agenda",IF(F19>=10,"🟠 High — quarterly review",IF(F19>=5,"🟡 Monitor — annual review","🟢 Low — register only"))) -> 🟡 Monitor — annual review
A20: =GARP_GRAP!B19 -> S&EC — Labour & Employment (EE, BCEA) | B20: =GARP_GRAP!E19 -> Req | C20: =GARP_GRAP!I19 -> 3 | D20: 4 | E20: 3 | F20: =IFERROR(IF(Assumptions!$B$12="Single (financial — IFRS)",IF(B20="High",5,IF(B20="Medium",3,IF(B20="Low",1,IF(B20="Req",4,0))))*C20*D20/5,IF(Assumptions!$B$12="Double (financial + impact — ESRS)",IF(B20="High",5,IF(B20="Medium",3,IF(B20="Low",1,IF(B20="Req",4,0))))*C20*MAX(D20,E20)/5,IF(B20="High",5,IF(B20="Medium",3,IF(B20="Low",1,IF(B20="Req",4,0))))*C20*((D20+E20)/2)/5)),0) -> 9.6 | G20: =IF(F20>=15,"🔴 Critical — board agenda",IF(F20>=10,"🟠 High — quarterly review",IF(F20>=5,"🟡 Monitor — annual review","🟢 Low — register only"))) -> 🟡 Monitor — annual review
A21: =GARP_GRAP!B20 -> S&EC — Environment | B21: =GARP_GRAP!E20 -> Req | C21: =GARP_GRAP!I20 -> 3 | D21: 4 | E21: 3 | F21: =IFERROR(IF(Assumptions!$B$12="Single (financial — IFRS)",IF(B21="High",5,IF(B21="Medium",3,IF(B21="Low",1,IF(B21="Req",4,0))))*C21*D21/5,IF(Assumptions!$B$12="Double (financial + impact — ESRS)",IF(B21="High",5,IF(B21="Medium",3,IF(B21="Low",1,IF(B21="Req",4,0))))*C21*MAX(D21,E21)/5,IF(B21="High",5,IF(B21="Medium",3,IF(B21="Low",1,IF(B21="Req",4,0))))*C21*((D21+E21)/2)/5)),0) -> 9.6 | G21: =IF(F21>=15,"🔴 Critical — board agenda",IF(F21>=10,"🟠 High — quarterly review",IF(F21>=5,"🟡 Monitor — annual review","🟢 Low — register only"))) -> 🟡 Monitor — annual review
A22: =GARP_GRAP!B21 -> S&EC — Anti-corruption | B22: =GARP_GRAP!E21 -> Req | C22: =GARP_GRAP!I21 -> 3 | D22: 4 | E22: 3 | F22: =IFERROR(IF(Assumptions!$B$12="Single (financial — IFRS)",IF(B22="High",5,IF(B22="Medium",3,IF(B22="Low",1,IF(B22="Req",4,0))))*C22*D22/5,IF(Assumptions!$B$12="Double (financial + impact — ESRS)",IF(B22="High",5,IF(B22="Medium",3,IF(B22="Low",1,IF(B22="Req",4,0))))*C22*MAX(D22,E22)/5,IF(B22="High",5,IF(B22="Medium",3,IF(B22="Low",1,IF(B22="Req",4,0))))*C22*((D22+E22)/2)/5)),0) -> 9.6 | G22: =IF(F22>=15,"🔴 Critical — board agenda",IF(F22>=10,"🟠 High — quarterly review",IF(F22>=5,"🟡 Monitor — annual review","🟢 Low — register only"))) -> 🟡 Monitor — annual review
A23: =GARP_GRAP!B22 -> S&EC — Consumer relations | B23: =GARP_GRAP!E22 -> Req | C23: =GARP_GRAP!I22 -> 3 | D23: 4 | E23: 3 | F23: =IFERROR(IF(Assumptions!$B$12="Single (financial — IFRS)",IF(B23="High",5,IF(B23="Medium",3,IF(B23="Low",1,IF(B23="Req",4,0))))*C23*D23/5,IF(Assumptions!$B$12="Double (financial + impact — ESRS)",IF(B23="High",5,IF(B23="Medium",3,IF(B23="Low",1,IF(B23="Req",4,0))))*C23*MAX(D23,E23)/5,IF(B23="High",5,IF(B23="Medium",3,IF(B23="Low",1,IF(B23="Req",4,0))))*C23*((D23+E23)/2)/5)),0) -> 9.6 | G23: =IF(F23>=15,"🔴 Critical — board agenda",IF(F23>=10,"🟠 High — quarterly review",IF(F23>=5,"🟡 Monitor — annual review","🟢 Low — register only"))) -> 🟡 Monitor — annual review
A24: =GARP_GRAP!B23 -> S&EC — Community development | B24: =GARP_GRAP!E23 -> Req | C24: =GARP_GRAP!I23 -> 3 | D24: 4 | E24: 3 | F24: =IFERROR(IF(Assumptions!$B$12="Single (financial — IFRS)",IF(B24="High",5,IF(B24="Medium",3,IF(B24="Low",1,IF(B24="Req",4,0))))*C24*D24/5,IF(Assumptions!$B$12="Double (financial + impact — ESRS)",IF(B24="High",5,IF(B24="Medium",3,IF(B24="Low",1,IF(B24="Req",4,0))))*C24*MAX(D24,E24)/5,IF(B24="High",5,IF(B24="Medium",3,IF(B24="Low",1,IF(B24="Req",4,0))))*C24*((D24+E24)/2)/5)),0) -> 9.6 | G24: =IF(F24>=15,"🔴 Critical — board agenda",IF(F24>=10,"🟠 High — quarterly review",IF(F24>=5,"🟡 Monitor — annual review","🟢 Low — register only"))) -> 🟡 Monitor — annual review
A25: =GARP_GRAP!B24 -> External audit coverage | B25: =GARP_GRAP!E24 -> Req | C25: =GARP_GRAP!I24 -> 3 | D25: 4 | E25: 3 | F25: =IFERROR(IF(Assumptions!$B$12="Single (financial — IFRS)",IF(B25="High",5,IF(B25="Medium",3,IF(B25="Low",1,IF(B25="Req",4,0))))*C25*D25/5,IF(Assumptions!$B$12="Double (financial + impact — ESRS)",IF(B25="High",5,IF(B25="Medium",3,IF(B25="Low",1,IF(B25="Req",4,0))))*C25*MAX(D25,E25)/5,IF(B25="High",5,IF(B25="Medium",3,IF(B25="Low",1,IF(B25="Req",4,0))))*C25*((D25+E25)/2)/5)),0) -> 9.6 | G25: =IF(F25>=15,"🔴 Critical — board agenda",IF(F25>=10,"🟠 High — quarterly review",IF(F25>=5,"🟡 Monitor — annual review","🟢 Low — register only"))) -> 🟡 Monitor — annual review
A27: SECTION 3 — Materiality summary
A28: Materiality basis (from Assumptions) | B28: =Assumptions!B12 -> Single (financial — IFRS)
A29: Critical material risks (≥15) | B29: =COUNTIF(F6:F15,">=15")+COUNTIF(F18:F25,">=15") -> 2
A30: High material risks (10-14) | B30: =COUNTIFS(F6:F15,">=10",F6:F15,"<15")+COUNTIFS(F18:F25,">=10",F18:F25,"<15") -> 1
A31: Average material score | B31: =IFERROR(AVERAGE(F6:F15,F18:F25),0) -> 8.3333333

Sheet Carbon_Tax
A1: 💰 CARBON TAX LIABILITY CALCULATOR | SA Carbon Tax Act, Section 12 | Tier 1 + Tier 2 sensitivity
A2: Liability = (Scope 1+2 tCO₂e × (1 - Basic Allowance)) × Carbon Tax Rate. Display mode controlled by Assumptions!B13. Currency follows Assumptions!B11.
A4: EMISSIONS BASE — pulled from E_Data GHG Summary
A5: Scope | B5: Activity | C5: tCO₂e YTD | D5: Annualised | E5: Taxable (after 60% allow.) | F5: Source
A6: Scope 1A | B6: Fleet diesel | C6: =IFERROR(E_Data!L75,0) -> 589465.53 | D6: =C6*Assumptions!$B$112 -> 785954.04 | E6: =D6*(1-Assumptions!$B$39) -> 314381.62 | F6: E_Data row 75 (annualised × 40% taxable)
A7: Scope 1B | B7: Generator diesel | C7: =IFERROR(E_Data!L76,0) -> 2181.14 | D7: =C7*Assumptions!$B$112 -> 2908.1867 | E7: =D7*(1-Assumptions!$B$39) -> 1163.2747 | F7: E_Data row 76
A8: Scope 1C | B8: LPG (forklifts) | C8: =IFERROR(E_Data!L77,0) -> 2280 | D8: =C8*Assumptions!$B$112 -> 3040 | E8: =D8*(1-Assumptions!$B$39) -> 1216 | F8: E_Data row 77
A9: Scope 1D | B9: Business cars | C9: =IFERROR(E_Data!L78,0) -> 1053.82 | D9: =C9*Assumptions!$B$112 -> 1405.0933 | E9: =D9*(1-Assumptions!$B$39) -> 562.03733 | F9: E_Data row 78
A10: Scope 2 | B10: Electricity (grid, net of solar) | C10: =IFERROR(E_Data!L82,0) -> 2589578.4 | D10: =C10*Assumptions!$B$112 -> 3452771.3 | E10: =D10*(1-Assumptions!$B$39) -> 1381108.5 | F10: E_Data row 82 (Scope 2 NET, after solar offset)
A11: TOTAL TAXABLE | C11: =SUM(C6:C10) -> 3184558.9 | D11: =SUM(D6:D10) -> 4246078.6 | E11: =SUM(E6:E10) -> 1698431.4
A13: LIABILITY CALCULATION — TIER 1 (CURRENT) vs TIER 2 (ESCALATED)
A14: Metric | B14: Tier 1 (Current) | C14: Tier 2 (Escalated) | D14: Delta | E14: Display? | F14: Notes
A15: Rate (currency/tCO₂e) | B15: =Assumptions!B37 -> 236 | C15: =Assumptions!B38 -> 640 | D15: =C15-B15 -> 404 | E15: =IF(Assumptions!$B$15="Both (current + escalated)","Both",IF(Assumptions!$B$15="Escalated Tier 2 only","Tier 2 only","Tier 1 only")) -> Both | F15: Rate from Assumptions TAX_T1 / TAX_T2
A16: Annual liability (taxable × rate) | B16: =E11*B15 -> 4.0082982e+08 | C16: =E11*C15 -> 1.0869961e+09 | D16: =C16-B16 -> 6.861663e+08 | F16: Annualised taxable tCO₂e × rate per tCO₂e
A17: Annual liability (formatted) | B17: =Assumptions!$B$14&" "&TEXT(B16,"#,##0") -> 400,829,817 | C17: =Assumptions!$B$14&" "&TEXT(C16,"#,##0") -> 1,086,996,115 | D17: =Assumptions!$B$14&" "&TEXT(D16,"#,##0") -> 686,166,297
A19: MITIGATION SCENARIOS — what-if liability reduction
A20: Scenario | B20: Tier 1 saving | C20: Tier 2 saving | D20: Capex est. | E20: Payback | F20: Notes
A21: Solar PV → 20% of grid demand | B21: =IFERROR(E10*0.2*B15,0) -> 65188321 | C21: =IFERROR(E10*0.2*C15,0) -> 1.7678189e+08 | D21: 4500000 | E21: =IFERROR(D21/MAX(1,B21+C21/2),"") -> 0.02930083 | F21: Capex assumed R4.5M for 5-depot PV roll-out (R900k per depot)
A22: Eco-driving training → -10% L/100km | B22: =IFERROR(E6*0.1*B15,0) -> 7419406.1 | C22: =IFERROR(E6*0.1*C15,0) -> 20120423 | D22: 350000 | E22: =IFERROR(D22/MAX(1,B22+C22/2),"") -> 0.020023321 | F22: Training cost ~R4,500 per driver × 77 drivers
A23: EV fleet → 20% transition | B23: =IFERROR(E6*0.2*B15,0) -> 14838812 | C23: =IFERROR(E6*0.2*C15,0) -> 40240847 | D23: 18000000 | E23: =IFERROR(D23/MAX(1,B23+C23/2),"") -> 0.5148854 | F23: Capex est: 27 vehicles × R670k diff vs diesel
A24: TOTAL MITIGATION POTENTIAL | B24: =SUM(B21:B23) -> 87446540 | C24: =SUM(C21:C23) -> 2.3714316e+08 | D24: =SUM(D21:D23) -> 22850000
A26: NET LIABILITY POSITION — pre and post mitigation
A27: Pre-mitigation annual liability | B27: =Assumptions!$B$14&" "&TEXT(B16,"#,##0") -> 400,829,817 | C27: =Assumptions!$B$14&" "&TEXT(C16,"#,##0") -> 1,086,996,115
A28: Post-mitigation (all 3 scenarios) | B28: =Assumptions!$B$14&" "&TEXT(MAX(0,B16-B24),"#,##0") -> 313,383,278 | C28: =Assumptions!$B$14&" "&TEXT(MAX(0,C16-C24),"#,##0") -> 849,852,956
A29: % reduction | B29: =IFERROR(B24/B16,0) -> 0.21816376 | C29: =IFERROR(C24/C16,0) -> 0.21816376

Sheet Standards_Map
A1: STANDARDS CROSS-REFERENCE MAP | All indicators mapped across GRI · IFRS S1/S2 · King V · ISO · B-BBEE · SBTi
A3: ESG Indicator | B3: GRI Ref | C3: IFRS S1 | D3: IFRS S2 | E3: King V | F3: ISO Std | G3: B-BBEE | H3: SBTi | I3: Toolkit Sheet
A4: Fleet Diesel — Scope 1 tCO₂e | B4: GRI 305-1 | C4: S1.5(a) | D4: S2.29 | E4: P4/P10/P15 | F4: ISO14001 c9.1 | G4: — | H4: Near-term target | I4: E_Data
A5: Generator Diesel — Scope 1 | B5: GRI 305-1 | C5: S1.5(a) | D5: S2.29 | E5: P4 | F5: ISO14001 c6.1.2 | G5: — | H5: Near-term | I5: E_Data
A6: LPG Forklifts — Scope 1 (DBN) | B6: GRI 305-1 | C6: S1.5(a) | D6: S2.29 | E6: P4 | F6: ISO14001 | G6: — | H6: Near-term | I6: E_Data
A7: Business Cars — Scope 1 | B7: GRI 305-1 | C7: S1.5(a) | D7: S2.29 | E7: P4 | F7: ISO14001 | G7: — | H7: Near-term | I7: E_Data
A8: Electricity Grid — Scope 2 | B8: GRI 305-2 | C8: S1.5(a) | D8: S2.30 | E8: P4 | F8: ISO14001 c6.2 | G8: — | H8: Near-term | I8: E_Data
A9: Solar PV offset — Scope 2 | B9: GRI 302-4 | C9: S1.33 | D9: S2.32 | E9: P4 | F9: ISO14001 | G9: — | H9: RE100 | I9: E_Data
A10: Water consumption | B10: GRI 303-1 | C10: S1.5 | D10: — | E10: P3 | F10: ISO14001 c6.1.2 | G10: — | H10: — | I10: E_Data
A11: Waste diversion % (Oricol) | B11: GRI 306-3 | C11: — | D11: — | E11: P3 | F11: ISO14001 c8.1 | G11: — | H11: — | I11: Waste_Register
A12: Fleet L/100km vs norm | B12: GRI 302-3 | C12: — | D12: S2.29 | E12: P4 | F12: SASB TR-AU | G12: — | H12: Scope 1 lever | I12: Fleet_Register
A13: EV Fleet mix % | B13: GRI 302-4 | C13: S1.33 | D13: S2.34 | E13: P4/P13 | F13: — | G13: — | H13: Scope 1&3 | I13: Fleet_Register
A14: ISO 14001 certification | B14: GRI 307-1 | C14: S1.22 | D14: — | E14: P12 | F14: ISO14001 | G14: — | H14: — | I14: ISO_Tracker
... A37: Net-Zero commitment (SBTi) | B37: GRI 305-5 | C37: S1.33 | D37: S2.32 | E37: P4/P15 | F37: — | G37: — | H37: CNZS 2.0 | I37: NetZero_Roadmap

Sheet Glossary
A1: 📖 GLOSSARY — Technical terminology, definitions, and source citations
A2: Every technical term used in this toolkit with its plain-English definition and authoritative source. Cell comments throughout the workbook point back to this glossary. Where a term has both an international standard reference and a South African legal reference, both are cited.
A3: Term | B3: Acronym | C3: Definition | D3: Source / Standard | E3: See also
A4: GHG / EMISSIONS
A5: Greenhouse Gas | B5: GHG | C5: Atmospheric gases that trap heat: CO₂, CH₄ (methane), N₂O (nitrous oxide), HFCs, PFCs, SF₆, NF₃. | D5: Kyoto Protocol; IPCC AR6
A6: Carbon dioxide equivalent | B6: CO₂e / tCO₂e | C6: Common unit for GHGs. Converts each gas to equivalent warming impact of CO₂ over 100 years using GWP factors. | D6: IPCC AR6 GWP100 | E6: GWP
A7: Global Warming Potential | B7: GWP | C7: Multiplier converting non-CO₂ gases to CO₂e. CH₄ = 27.9, N₂O = 273, SF₆ = 25,200. | D7: IPCC AR6
A8: Scope 1 emissions | B8: Scope 1 | C8: Direct emissions from owned/controlled sources. Fleet fuel, generators, on-site combustion, refrigerant leaks. | D8: GHG Protocol Corp. Standard Ch. 4 | E8: GHG Protocol
A9: Scope 2 emissions | B9: Scope 2 | C9: Indirect emissions from purchased electricity, steam, heating, cooling. | D9: GHG Protocol Scope 2 Guidance | E9: Location-based, Market-based
A10: Scope 3 emissions | B10: Scope 3 | C10: All other indirect emissions across the value chain (15 categories incl. purchased goods, business travel, employee commute, waste, water, downstream transport). | D10: GHG Protocol Corp. Value Chain Standard | E10: 15 Scope 3 categories
A11: Emission Factor | B11: EF | C11: Coefficient converting activity data (litres, kWh, kg) into emissions (kgCO₂e). e.g. diesel = 2.68 kgCO₂e/L. | D11: DEFRA 2024; IPCC; Eskom NERSA
A12: GHG Protocol | C12: World Resources Institute/WBCSD standard for corporate GHG accounting. The foundational reference for Scope 1/2/3 classification. | D12: ghgprotocol.org
A13: Science Based Targets initiative | B13: SBTi | C13: Voluntary framework defining "credible" emissions reduction targets aligned to limiting warming to 1.5°C / well-below 2°C. | D13: sciencebasedtargets.org | E13: CNZS 2.0
A14: Corporate Net Zero Standard | B14: CNZS 2.0 | C14: SBTi standard requiring ≥90% emissions reduction across all scopes by long-term target year, with residuals neutralised via permanent removals. | D14: SBTi CNZS v2.0 (2024) | E14: Net-zero, Neutralisation
A15: RE100 | C15: Global initiative committing members to 100% renewable electricity. | D15: there100.org
A16: Carbon Tax (SA) | C16: South African Carbon Tax Act 15 of 2019, Section 12L. Levy on Scope 1+2 emissions above the basic 60% tax-free allowance. Tier 1 rate R236/tCO₂e (2025); escalating. | D16: Carbon Tax Act 15 of 2019 | E16: Section 12L allowance
A17: Section 12L allowance | B17: 12L | C17: Income Tax Act §12L. 60% basic tax-free emissions allowance for industrial/commercial firms. Reduces taxable Scope 1+2 base. | D17: Income Tax Act s12L; SARS guidance
A18: TRANSPORT EMISSIONS (ISO 14083 / GLEC)
A19: ISO 14083 | C19: International standard for quantifying GHG emissions from transport chains. Defines journey-level calculation, allocation methods, and intensity metrics. | D19: ISO 14083:2023 | E19: GLEC, tonne-km
A20: GLEC Framework | B20: GLEC | C20: Global Logistics Emissions Council framework. The practical methodology that operationalises ISO 14083 for industry. Maintained by Smart Freight Centre. | D20: smartfreightcentre.org | E20: ISO 14083
A21: Tonne-kilometre | B21: t·km / TKM | C21: Activity unit for transport emissions: 1 tonne of cargo moved 1 km. Calculated as Load (t) × Distance (km). | D21: ISO 14083 §6.2
A22: Emissions intensity (transport) | B22: gCO₂e/t·km | C22: Grams of CO₂e per tonne-kilometre. Standard transport KPI. Benchmark for heavy road freight: 80 g/t·km (GLEC). | D22: GLEC Framework v3.0 | E22: TKM
A23: Fuel-based method | C23: ISO 14083 preferred method. Calculate emissions from actual fuel consumed × emission factor. Highest data quality. | D23: ISO 14083 §7.2
A24: Distance-based method | C24: Fallback when fuel data unavailable. Multiplies distance × vehicle-class default emission factor. | D24: ISO 14083 §7.3
A25: Allocation (transport) | C25: Splitting trip emissions across multiple customers/shipments. Bases: weight, volume, distance, revenue, equal-share. | D25: ISO 14083 §8
A26: Backhaul / Empty trip | C26: Unloaded return leg. Emissions of an empty trip are typically allocated to the loaded trip(s). | D26: GLEC Framework
A27: ESG REPORTING STANDARDS
A28: Environmental, Social, Governance | B28: ESG | C28: Three-pillar framework for non-financial corporate performance disclosure.
A29: IFRS S1 | B29: S1 | C29: IFRS Sustainability Disclosure Standard 1: General requirements for sustainability-related financial disclosures. | D29: ISSB IFRS S1 (2023)
A30: IFRS S2 | B30: S2 | C30: IFRS Sustainability Disclosure Standard 2: Climate-related disclosures. Incorporates TCFD recommendations. | D30: ISSB IFRS S2 (2023) | E30: TCFD
A31: TCFD | B31: TCFD | C31: Task Force on Climate-related Financial Disclosures. Four-pillar climate disclosure framework: Governance, Strategy, Risk Management, Metrics & Targets. Subsumed by IFRS S2 from 2024. | D31: TCFD Recommendations (2017) | E31: IFRS S2
A32: GRI Standards | B32: GRI | C32: Global Reporting Initiative — most widely used voluntary sustainability disclosure standard. Universal (GRI 1-3) + Topic (200/300/400 series). | D32: globalreporting.org
A33: ESRS | B33: ESRS | C33: European Sustainability Reporting Standards. Mandatory under EU CSRD. Stricter than IFRS — requires double materiality. | D33: EFRAG / EU CSRD | E33: CSRD, Double Materiality
A34: CSRD | B34: CSRD | C34: Corporate Sustainability Reporting Directive (EU). Phased mandate from 2024. Requires ESRS-compliant reporting + assurance. | D34: EU Directive 2022/2464 | E34: ESRS
A35: Single materiality | C35: Financial materiality only — what impacts the company. IFRS approach. | D35: IFRS S1
A36: Double materiality | C36: Financial materiality + impact materiality (how company impacts environment/society). ESRS approach. | D36: EFRAG / ESRS 1
A37: Materiality | C37: Information is material if its omission/misstatement would influence stakeholder decisions. Quantified via materiality matrix. | D37: IASB Conceptual Framework
A38: Materiality Matrix | C38: Plot of issues by impact (x-axis) vs likelihood/stakeholder interest (y-axis). Highlights priority topics. | D38: GRI 3 (2021)
A39: GOVERNANCE (KING V / SA)
A40: King V Code | B40: King V | C40: South African corporate governance code. 17 principles applying "Apply & Explain" methodology. Mandatory for JSE-listed firms. | D40: IoDSA King V Report (2024) | E40: Apply & Explain
A41: Apply & Explain | C41: King V methodology: governing body either confirms application of a principle (and explains how) or explains non-application. | D41: King V Code
A42: Public Interest Score | B42: PI Score | C42: Companies Act §1 calculation determining audit/S&EC requirements. Based on turnover, employee count, beneficial holders, third-party liabilities. ≥500 = mandatory S&EC + independent audit. | D42: Companies Act 71 of 2008 §1 | E42: S&EC
A43: Social & Ethics Committee | B43: S&EC | C43: Mandatory committee for companies with PI score ≥500 or listed. Monitors EE, B-BBEE, anti-corruption, consumer relations, CSI, environment. | D43: Companies Act s72; Reg 43 | E43: PI Score
A44: King V Principle 10 | B44: P10 | C44: Risk Governance — board oversight of opportunities and risks (incl. ESG/climate). | D44: King V P10
A45: King V Principle 15 | B45: P15 | C45: Disclosure — transparent reporting on the organisation's performance and prospects. | D45: King V P15
A46: Combined Assurance | C46: Coordinated assurance from management, internal audit, external audit, and specialists across the same risk areas. | D46: King V P11
A47: B-BBEE / TRANSFORMATION
A48: Broad-Based Black Economic Empowerment | B48: B-BBEE | C48: South African legislation driving economic transformation. Generic Scorecard has 5 elements + bonus = 114 points. | D48: B-BBEE Act 53 of 2003 (amended 2013)
A49: Generic Code (Statement 000) | C49: Default B-BBEE scorecard applicable to firms not under a sector charter. 5 elements: Ownership, MC, SD, ESD, SED. | D49: Codes of Good Practice (2013, amended 2019)
A50: Ownership | B50: BB_OWN | C50: B-BBEE Element 1 (25 pts). % Black ownership in entity. Statement 100. | D50: Statement 100
A51: Management Control | B51: MC | C51: B-BBEE Element 2 (19 pts). Black representation at board/senior management. Statement 200. | D51: Statement 200
A52: Skills Development | B52: SD | C52: B-BBEE Element 3 (25 pts). 6% payroll spend on Black training. Statement 300. | D52: Statement 300 | E52: SDL, WSP, ATR
A53: Enterprise & Supplier Development | B53: ESD | C53: B-BBEE Element 4 (40 pts). Preferential procurement + supplier dev contributions. Statement 400. | D53: Statement 400 | E53: Preferential Procurement
A54: Socio-Economic Development | B54: SED | C54: B-BBEE Element 5 (5 pts). 1% NPAT spend on CSI for Black beneficiaries. Statement 500. | D54: Statement 500 | E54: CSI, NPAT
A55: Modified Flow-Through | B55: MFT | C55: Ownership calculation method. Where a Black-owned entity holds ≥51% of a measured entity, treat that holding as 100% Black for one level only. | D55: Statement 100 §3.2.10 | E55: Flow-Through
A56: Flow-Through Principle | C56: Default ownership calculation — multiply Black % through each level of holding company structure. | D56: Statement 100 §3.2.9
A57: Exempt Micro Enterprise | B57: EME | C57: Annual turnover ≤R10m. Auto-Level 4 (Generic) or Level 2 (≥51% Black-owned). Affidavit-based. | D57: B-BBEE Codes
A58: Qualifying Small Enterprise | B58: QSE | C58: Annual turnover R10m–R50m. Simplified scorecard with 4 elements. | D58: B-BBEE Codes
A59: Affidavit | B59: AFR | C59: Sworn statement confirming EME/QSE status. Replaces verified certificate for EMEs. | D59: B-BBEE Practice Note
A60: Preferential Procurement | B60: PP | C60: B-BBEE points awarded for buying from Level 1-8 suppliers. 25 of the 40 ESD points. | D60: Statement 400
A61: EMPLOYMENT EQUITY / SKILLS
A62: Employment Equity Act | B62: EEA | C62: South African legislation requiring designated employers to eliminate unfair discrimination and implement affirmative action. | D62: EEA 55 of 1998 (amended 2022)
A63: EEA2 Report | B63: EEA2 | C63: Annual employment equity report submitted to Department of Employment & Labour (DoEL). Breaks down workforce by race, gender, disability across 6 occupational levels. | D63: EEA s21
A64: Occupational Levels | B64: EEA2 L1-L6 | C64: Standard SA occupational level classification: L1 Top Mgmt, L2 Senior Mgmt, L3 Professionally Qualified, L4 Skilled Technical, L5 Semi-Skilled, L6 Unskilled. | D64: EEA2 schedule
A65: Persons with Disabilities | B65: PWD | C65: EEA-recognised disabled persons. Target: ≥2% of workforce. | D65: EEA s6 + Code of Good Practice on PWD
A66: Workplace Skills Plan | B66: WSP | C66: Annual training plan submitted to SETA by 30 April. Sets out training to be delivered. | D66: Skills Development Act 97 of 1998 s10 | E66: SETA, ATR
A67: Annual Training Report | B67: ATR | C67: Annual report on training actually delivered. Submitted with WSP by 30 April. | D67: SDL Act s10 | E67: WSP
